Workbook

Sheet README
A1: Rolodex price data
A2: New-home prices by builder in Greater Houston and Dallas-Fort Worth masterplanned communities. Read 2026-09-27. Prepared by Héctor Ibarzábal.
A4: Tables
A5: Sheet | B5: Rows | C5: What it holds
A6: Homes | B6: =COUNTA('Homes'!A:A)-1 | C6: One row per move-in-ready home: list price, size, rooms, garage, stories, status, lot width, builder, community, location, ZIP resale. The table for a hedonic model.
A7: ProductLines | B7: =COUNTA('ProductLines'!A:A)-1 | C7: One row per builder product line in a community: starting price, lot widths, size range, incentive text. The unit the builder prices.
A8: Communities | B8: =COUNTA('Communities'!A:A)-1 | C8: One row per masterplanned community, with its ZIP resale figures and a computed distance to downtown.
A9: Builders | B9: =COUNTA('Builders'!A:A)-1 | C9: One row per builder per market, with the Rolodex counts and published closings.
A10: Developers | B10: =COUNTA('Developers'!A:A)-1 | C10: One row per land developer per market.
A11: CommunityFacts | B11: =COUNTA('CommunityFacts'!A:A)-1 | C11: Sourced facts about each community, one per row (qualitative).
A12: Text | B12: =COUNTA('Text'!A:A)-1 | C12: Every free-text field in long form for text analysis: facts, incentives, price wording, land-record source lines.
A13: Land | B13: =COUNTA('Land'!A:A)-1 | C13: Land and lot records: Howard Hughes price an acre, lot prices, lot supply. Source text kept.
A14: Filings | B14: =COUNTA('Filings'!A:A)-1 | C14: Figures read from public builders' SEC filings, with the source line.
A15: ZIPs | B15: =COUNTA('ZIPs'!A:A)-1 | C15: Latest Zillow and Redfin figures for each ZIP with a community in it.
A16: ZIP_ZHVI_Monthly | B16: =COUNTA('ZIP_ZHVI_Monthly'!A:A)-1 | C16: Zillow home value index by ZIP and month (long).
A17: ZIP_Redfin_Quarterly | B17: =COUNTA('ZIP_Redfin_Quarterly'!A:A)-1 | C17: Redfin median sale price and price a sq ft by ZIP and quarter (long).
A18: Metro_Monthly | B18: =COUNTA('Metro_Monthly'!A:A)-1 | C18: Zillow metro series by month (long): zhvi_sfr, newcon_price, newcon_ppsf, newcon_sales, sales_all, median_sale_sfr, inventory.
A19: Permits | B19: =COUNTA('Permits'!A:A)-1 | C19: Census Building Permits Survey, single-family, by county and year.
A20: Model_Summary | B20: =COUNTA('Model_Summary'!A:A)-1 | C20: Baseline hedonic regressions of log list price (fit here in Python; see Model_Terms).
A21: Model_Terms | B21: =COUNTA('Model_Terms'!A:A)-1 | C21: Coefficients of the baseline models, standard errors clustered by community. Community and builder fixed effects not listed.
A22: Community_Premium | B22: =COUNTA('Community_Premium'!A:A)-1 | C22: Model P community effects: what a home of the same floor area lists for in each community, against the market's median community.
A24: How it was read
A25: Prices are list prices on each builder or community page, found again on the page by a script before they were kept. No listing portal is a source. List prices are not sale prices.
A26: Room counts, garage, stories, address and status were read from the same pages: the listing card that carries the home's price and floor area. A field the card does not print is blank; nothing is imputed.
A27: Lot width is known for a home only when its product line offers one width. Location is the community's point: where the Census geocoder places its homes, or its ZIP center. Not the lot.
A28: Up to five move-in-ready homes were read a product line, so a line with many homes on sale counts no more than one with five. qmi_listed in ProductLines gives how many each line listed.
A29: Every home was read again on its page the day it was read; a home no longer on its page was dropped. Perry Homes homes carry the address, rooms and status from Perry's own section pages.
A30: Rows flagged possible_duplicate repeat a home earlier in the table. The models keep the first copy.
A32: For a hedonic model
A33: Homes is the frame: log list_price on log sqft, beds, baths_total, garage_spaces, stories, lot_width_ft, status, with community and builder fixed effects. Model_Summary gives a baseline fit.
A34: Missing here, and worth adding: lot area, MUD or PID tax rate and HOA dues (large in Texas), exact lot coordinates, finish level, and sale prices with dates for a time index.
A35: Selection: move-in-ready inventory is what was unsold on the day read. It may differ from the homes that sold.
A37: Sources: builder and community pages (linked per row), Zillow Research, Redfin Data Center, US Census Building Permits Survey, SEC EDGAR, RCLCO, and published reports linked in Land.
... A40: Every column is described in the Dictionary sheet, the last tab.

Sheet Homes
A1: home_id | B1: market | C1: community_id | D1: community | E1: county | F1: city | G1: zip | H1: developer | I1: school_district | J1: builder | K1: builder_id | L1: rolodex_section | M1: rolodex_repetition | N1: rolodex_printer_fit | O1: rolodex_track_record | P1: builder_sec_filer | Q1: line_id | R1: product_line | S1: lot_width_ft | T1: lot_widths_offered_ft | U1: plan | V1: list_price | W1: sqft | X1: price_per_sqft | Y1: beds | Z1: full_baths | AA1: half_baths | AB1: baths_total | AC1: garage_spaces | AD1: stories | AE1: status | AF1: status_text | AG1: was_price | AH1: cut_from_was | AI1: savings_stated | AJ1: line_incentive_text | AK1: address | AL1: miles_to_nearest_cbd | AM1: nearest_cbd | AN1: zip_zhvi | AO1: zip_zhvi_yoy | AP1: zip_redfin_median_sale | AQ1: zip_redfin_ppsf | AR1: community_acres | AS1: community_rclco_rank | AT1: possible_duplicate | AU1: listing_url | AV1: attributes_read_from | AW1: home_key | AX1: read_on
A2: 1 | B2: houston | C2: hou-artavia | D2: ARTAVIA | E2: Montgomery | F2: Conroe | G2: 77302 | H2: AIRIA Development Company | I2: Conroe ISD | J2: Beazer Homes | K2: b-houston-beazer-homes | L2: National builder | M2: Yes | N2: No | O2: No | P2: Beazer Homes | Q2: hou-artavia#1 | S2: 65 | T2: 65 | U2: Fredericksburg | V2: 499567 | W2: 2948 | X2: =IF(W2>0,V2/W2,"") | Y2: 4 | Z2: 3 | AA2: 1 | AB2: =IF(Z2="","",Z2+0.5*N(AA2)) | AE2: ready | AF2: Available Now | AH2: =IF(AG2="","",1-V2/AG2) | AJ2: For a limited time, receive 50% off options up to $100,000 for your new to-be-built home when you use a Choice Lender!* | AK2: 17016 Sweet Iris Court | AL2: 30.7 | AM2: Houston | AN2: 326778 | AO2: -0.0227 | AP2: 335775 | AQ2: 153 | AR2: 2842 | AU2: https://www.beazer.com/houston-TX/conroe/artavia | AV2: https://www.beazer.com/houston-TX/conroe/artavia | AW2: hcb2de693b | AX2: 2026-09-27
A3: 2 | B3: houston | C3: hou-artavia | D3: ARTAVIA | E3: Montgomery | F3: Conroe | G3: 77302 | H3: AIRIA Development Company | I3: Conroe ISD | J3: Beazer Homes | K3: b-houston-beazer-homes | L3: National builder | M3: Yes | N3: No | O3: No | P3: Beazer Homes | Q3: hou-artavia#1 | S3: 65 | T3: 65 | U3: Harper | V3: 499987 | W3: 3639 | X3: =IF(W3>0,V3/W3,"") | Y3: 4 | Z3: 3 | AA3: 1 | AB3: =IF(Z3="","",Z3+0.5*N(AA3)) | AE3: ready | AF3: Available Now | AH3: =IF(AG3="","",1-V3/AG3) | AJ3: For a limited time, receive 50% off options up to $100,000 for your new to-be-built home when you use a Choice Lender!* | AK3: 17315 July Moon Lane | AL3: 30.7 | AM3: Houston | AN3: 326778 | AO3: -0.0227 | AP3: 335775 | AQ3: 153 | AR3: 2842 | AU3: https://www.beazer.com/houston-TX/conroe/artavia | AV3: https://www.beazer.com/houston-TX/conroe/artavia | AW3: h0d9de8ea7 | AX3: 2026-09-27
A4: 3 | B4: houston | C4: hou-artavia | D4: ARTAVIA | E4: Montgomery | F4: Conroe | G4: 77302 | H4: AIRIA Development Company | I4: Conroe ISD | J4: Beazer Homes | K4: b-houston-beazer-homes | L4: National builder | M4: Yes | N4: No | O4: No | P4: Beazer Homes | Q4: hou-artavia#1 | S4: 65 | T4: 65 | U4: Northcliffe | V4: 568701 | W4: 3908 | X4: =IF(W4>0,V4/W4,"") | Y4: 5 | Z4: 4 | AA4: 1 | AB4: =IF(Z4="","",Z4+0.5*N(AA4)) | AE4: ready | AF4: Available Now | AH4: =IF(AG4="","",1-V4/AG4) | AJ4: For a limited time, receive 50% off options up to $100,000 for your new to-be-built home when you use a Choice Lender!* | AK4: 17211 Begonia Bend Dr | AL4: 30.7 | AM4: Houston | AN4: 326778 | AO4: -0.0227 | AP4: 335775 | AQ4: 153 | AR4: 2842 | AU4: https://www.beazer.com/houston-TX/conroe/artavia | AV4: https://www.beazer.com/houston-TX/conroe/artavia | AW4: h97ec9879a | AX4: 2026-09-27
A5: 4 | B5: houston | C5: hou-artavia | D5: ARTAVIA | E5: Montgomery | F5: Conroe | G5: 77302 | H5: AIRIA Development Company | I5: Conroe ISD | J5: David Weekley Homes | K5: b-houston-david-weekley-homes | L5: National builder | M5: Yes | N5: No | O5: No | Q5: hou-artavia#3 | R5: Reserve Collection | S5: 45 | T5: 45 | U5: Plan A297 | V5: 449990 | W5: 2600 | X5: =IF(W5>0,V5/W5,"") | Y5: 4 | Z5: 3 | AA5: 1 | AB5: =IF(Z5="","",Z5+0.5*N(AA5)) | AC5: 2 | AD5: 2 | AE5: ready | AF5: Ready Now | AH5: =IF(AG5="","",1-V5/AG5) | AK5: 15231 Osie Limestone Lane | AL5: 30.7 | AM5: Houston | AN5: 326778 | AO5: -0.0227 | AP5: 335775 | AQ5: 153 | AR5: 2842 | AU5: https://www.davidweekleyhomes.com/new-homes/tx/houston/conroe/artavia-45-homesites | AV5: https://www.davidweekleyhomes.com/new-homes/tx/houston/conroe/artavia-45-homesites | AW5: h0b42d27d6 | AX5: 2026-09-27
A6: 5 | B6: houston | C6: hou-artavia | D6: ARTAVIA | E6: Montgomery | F6: Conroe | G6: 77302 | H6: AIRIA Development Company | I6: Conroe ISD | J6: David Weekley Homes | K6: b-houston-david-weekley-homes | L6: National builder | M6: Yes | N6: No | O6: No | Q6: hou-artavia#3 | R6: Reserve Collection | S6: 45 | T6: 45 | U6: Plan B257 | V6: 425990 | W6: 2288 | X6: =IF(W6>0,V6/W6,"") | Y6: 4 | Z6: 3 | AA6: 1 | AB6: =IF(Z6="","",Z6+0.5*N(AA6)) | AC6: 2 | AD6: 1 | AH6: =IF(AG6="","",1-V6/AG6) | AK6: 15110 London Gavroche Lane | AL6: 30.7 | AM6: Houston | AN6: 326778 | AO6: -0.0227 | AP6: 335775 | AQ6: 153 | AR6: 2842 | AU6: https://www.davidweekleyhomes.com/new-homes/tx/houston/conroe/artavia-45-homesites | AV6: https://www.davidweekleyhomes.com/new-homes/tx/houston/conroe/artavia-45-homesites | AW6: he080bdf7b | AX6: 2026-09-27
A7: 6 | B7: houston | C7: hou-artavia | D7: ARTAVIA | E7: Montgomery | F7: Conroe | G7: 77302 | H7: AIRIA Development Company | I7: Conroe ISD | J7: David Weekley Homes | K7: b-houston-david-weekley-homes | L7: National builder | M7: Yes | N7: No | O7: No | Q7: hou-artavia#3 | R7: Reserve Collection | S7: 45 | T7: 45 | U7: Plan T103 | V7: 409990 | W7: 2105 | X7: =IF(W7>0,V7/W7,"") | Y7: 3 | Z7: 2 | AB7: =IF(Z7="","",Z7+0.5*N(AA7)) | AC7: 2 | AD7: 1 | AH7: =IF(AG7="","",1-V7/AG7) | AK7: 15130 London Gavroche Lane | AL7: 30.7 | AM7: Houston | AN7: 326778 | AO7: -0.0227 | AP7: 335775 | AQ7: 153 | AR7: 2842 | AU7: https://www.davidweekleyhomes.com/new-homes/tx/houston/conroe/artavia-45-homesites | AV7: https://www.davidweekleyhomes.com/new-homes/tx/houston/conroe/artavia-45-homesites | AW7: h29addb459 | AX7: 2026-09-27
A8: 7 | B8: houston | C8: hou-artavia | D8: ARTAVIA | E8: Montgomery | F8: Conroe | G8: 77302 | H8: AIRIA Development Company | I8: Conroe ISD | J8: David Weekley Homes | K8: b-houston-david-weekley-homes | L8: National builder | M8: Yes | N8: No | O8: No | Q8: hou-artavia#3 | R8: Reserve Collection | S8: 45 | T8: 45 | U8: Plan T101 | V8: 394990 | W8: 1713 | X8: =IF(W8>0,V8/W8,"") | Y8: 3 | Z8: 2 | AB8: =IF(Z8="","",Z8+0.5*N(AA8)) | AC8: 2 | AD8: 1 | AH8: =IF(AG8="","",1-V8/AG8) | AK8: 15007 Silvano Street | AL8: 30.7 | AM8: Houston | AN8: 326778 | AO8: -0.0227 | AP8: 335775 | AQ8: 153 | AR8: 2842 | AU8: https://www.davidweekleyhomes.com/new-homes/tx/houston/conroe/artavia-45-homesites | AV8: https://www.davidweekleyhomes.com/new-homes/tx/houston/conroe/artavia-45-homesites | AW8: h310e66e2b | AX8: 2026-09-27
A9: 8 | B9: houston | C9: hou-artavia | D9: ARTAVIA | E9: Montgomery | F9: Conroe | G9: 77302 | H9: AIRIA Development Company | I9: Conroe ISD | J9: David Weekley Homes | K9: b-houston-david-weekley-homes | L9: National builder | M9: Yes | N9: No | O9: No | Q9: hou-artavia#3 | R9: Reserve Collection | S9: 45 | T9: 45 | U9: Plan T102 | V9: 394990 | W9: 1910 | X9: =IF(W9>0,V9/W9,"") | Y9: 3 | Z9: 2 | AB9: =IF(Z9="","",Z9+0.5*N(AA9)) | AC9: 2 | AD9: 1 | AH9: =IF(AG9="","",1-V9/AG9) | AK9: 18319 Bon Brothers Drive | AL9: 30.7 | AM9: Houston | AN9: 326778 | AO9: -0.0227 | AP9: 335775 | AQ9: 153 | AR9: 2842 | AU9: https://www.davidweekleyhomes.com/new-homes/tx/houston/conroe/artavia-45-homesites | AV9: https://www.davidweekleyhomes.com/new-homes/tx/houston/conroe/artavia-45-homesites | AW9: hadcf4e27d | AX9: 2026-09-27
A10: 9 | B10: houston | C10: hou-artavia | D10: ARTAVIA | E10: Montgomery | F10: Conroe | G10: 77302 | H10: AIRIA Development Company | I10: Conroe ISD | J10: David Weekley Homes | K10: b-houston-david-weekley-homes | L10: National builder | M10: Yes | N10: No | O10: No | Q10: hou-artavia#4 | R10: Enclave Collection | S10: 50 | T10: 50 | U10: Plan T004 | V10: 459990 | W10: 2216 | X10: =IF(W10>0,V10/W10,"") | Y10: 4 | Z10: 3 | AA10: 1 | AB10: =IF(Z10="","",Z10+0.5*N(AA10)) | AC10: 2 | AD10: 1 | AE10: ready | AF10: Ready Now | AH10: =IF(AG10="","",1-V10/AG10) | AK10: 16138 Rita Road | AL10: 30.7 | AM10: Houston | AN10: 326778 | AO10: -0.0227 | AP10: 335775 | AQ10: 153 | AR10: 2842 | AU10: https://www.davidweekleyhomes.com/new-homes/tx/houston/conroe/artavia-50-homesites | AV10: https://www.davidweekleyhomes.com/new-homes/tx/houston/conroe/artavia-50-homesites | AW10: h2b9ac2c2d | AX10: 2026-09-27
A11: 10 | B11: houston | C11: hou-artavia | D11: ARTAVIA | E11: Montgomery | F11: Conroe | G11: 77302 | H11: AIRIA Development Company | I11: Conroe ISD | J11: David Weekley Homes | K11: b-houston-david-weekley-homes | L11: National builder | M11: Yes | N11: No | O11: No | Q11: hou-artavia#4 | R11: Enclave Collection | S11: 50 | T11: 50 | U11: Plan T010 | V11: 469990 | W11: 2618 | X11: =IF(W11>0,V11/W11,"") | Y11: 4 | Z11: 3 | AA11: 1 | AB11: =IF(Z11="","",Z11+0.5*N(AA11)) | AC11: 2 | AD11: 2 | AE11: ready | AF11: Ready Now | AH11: =IF(AG11="","",1-V11/AG11) | AK11: 16146 Rita Road | AL11: 30.7 | AM11: Houston | AN11: 326778 | AO11: -0.0227 | AP11: 335775 | AQ11: 153 | AR11: 2842 | AU11: https://www.davidweekleyhomes.com/new-homes/tx/houston/conroe/artavia-50-homesites | AV11: https://www.davidweekleyhomes.com/new-homes/tx/houston/conroe/artavia-50-homesites | AW11: h50041d7b8 | AX11: 2026-09-27
A12: 11 | B12: houston | C12: hou-artavia | D12: ARTAVIA | E12: Montgomery | F12: Conroe | G12: 77302 | H12: AIRIA Development Company | I12: Conroe ISD | J12: David Weekley Homes | K12: b-houston-david-weekley-homes | L12: National builder | M12: Yes | N12: No | O12: No | Q12: hou-artavia#4 | R12: Enclave Collection | S12: 50 | T12: 50 | U12: Plan T005 | V12: 449990 | W12: 2286 | X12: =IF(W12>0,V12/W12,"") | Y12: 3 | Z12: 2 | AA12: 1 | AB12: =IF(Z12="","",Z12+0.5*N(AA12)) | AC12: 3 | AD12: 1 | AE12: ready | AF12: Ready Now | AH12: =IF(AG12="","",1-V12/AG12) | AK12: 18607 Rumba Court | AL12: 30.7 | AM12: Houston | AN12: 326778 | AO12: -0.0227 | AP12: 335775 | AQ12: 153 | AR12: 2842 | AU12: https://www.davidweekleyhomes.com/new-homes/tx/houston/conroe/artavia-50-homesites | AV12: https://www.davidweekleyhomes.com/new-homes/tx/houston/conroe/artavia-50-homesites | AW12: h0ff7e7f82 | AX12: 2026-09-27
A13: 12 | B13: houston | C13: hou-artavia | D13: ARTAVIA | E13: Montgomery | F13: Conroe | G13: 77302 | H13: AIRIA Development Company | I13: Conroe ISD | J13: David Weekley Homes | K13: b-houston-david-weekley-homes | L13: National builder | M13: Yes | N13: No | O13: No | Q13: hou-artavia#4 | R13: Enclave Collection | S13: 50 | T13: 50 | U13: Plan T014 | V13: 517990 | W13: 3101 | X13: =IF(W13>0,V13/W13,"") | Y13: 5 | Z13: 4 | AB13: =IF(Z13="","",Z13+0.5*N(AA13)) | AC13: 4 | AD13: 2 | AH13: =IF(AG13="","",1-V13/AG13) | AK13: 18611 Rumba Court | AL13: 30.7 | AM13: Houston | AN13: 326778 | AO13: -0.0227 | AP13: 335775 | AQ13: 153 | AR13: 2842 | AU13: https://www.davidweekleyhomes.com/new-homes/tx/houston/conroe/artavia-50-homesites | AV13: https://www.davidweekleyhomes.com/new-homes/tx/houston/conroe/artavia-50-homesites | AW13: hb49ab8cb1 | AX13: 2026-09-27
A14: 13 | B14: houston | C14: hou-artavia | D14: ARTAVIA | E14: Montgomery | F14: Conroe | G14: 77302 | H14: AIRIA Development Company | I14: Conroe ISD | J14: David Weekley Homes | K14: b-houston-david-weekley-homes | L14: National builder | M14: Yes | N14: No | O14: No | Q14: hou-artavia#4 | R14: Enclave Collection | S14: 50 | T14: 50 | U14: Plan T008 | V14: 496990 | W14: 2545 | X14: =IF(W14>0,V14/W14,"") | Y14: 4 | Z14: 3 | AA14: 1 | AB14: =IF(Z14="","",Z14+0.5*N(AA14)) | AC14: 3 | AD14: 1 | AH14: =IF(AG14="","",1-V14/AG14) | AK14: 18606 Rumba Court | AL14: 30.7 | AM14: Houston | AN14: 326778 | AO14: -0.0227 | AP14: 335775 | AQ14: 153 | AR14: 2842 | AU14: https://www.davidweekleyhomes.com/new-homes/tx/houston/conroe/artavia-50-homesites | AV14: https://www.davidweekleyhomes.com/new-homes/tx/houston/conroe/artavia-50-homesites | AW14: h8a337a77f | AX14: 2026-09-27
A15: 14 | B15: houston | C15: hou-artavia | D15: ARTAVIA | E15: Montgomery | F15: Conroe | G15: 77302 | H15: AIRIA Development Company | I15: Conroe ISD | J15: David Weekley Homes | K15: b-houston-david-weekley-homes | L15: National builder | M15: Yes | N15: No | O15: No | Q15: hou-artavia#5 | R15: Parkview Collection | S15: 65 | T15: 65 | U15: Plan B679 | V15: 589990 | W15: 3121 | X15: =IF(W15>0,V15/W15,"") | Y15: 4 | Z15: 3 | AA15: 1 | AB15: =IF(Z15="","",Z15+0.5*N(AA15)) | AC15: 3 | AD15: 1 | AE15: ready | AF15: Ready Now | AH15: =IF(AG15="","",1-V15/AG15) | AK15: 15748 Terracotta Terrace Lane | AL15: 30.7 | AM15: Houston | AN15: 326778 | AO15: -0.0227 | AP15: 335775 | AQ15: 153 | AR15: 2842 | AU15: https://www.davidweekleyhomes.com/new-homes/tx/houston/conroe/artavia | AV15: https://www.davidweekleyhomes.com/new-homes/tx/houston/conroe/artavia | AW15: h6a2d65679 | AX15: 2026-09-27
A16: 15 | B16: houston | C16: hou-artavia | D16: ARTAVIA | E16: Montgomery | F16: Conroe | G16: 77302 | H16: AIRIA Development Company | I16: Conroe ISD | J16: David Weekley Homes | K16: b-houston-david-weekley-homes | L16: National builder | M16: Yes | N16: No | O16: No | Q16: hou-artavia#5 | R16: Parkview Collection | S16: 65 | T16: 65 | U16: Plan B679 | V16: 583990 | W16: 3100 | X16: =IF(W16>0,V16/W16,"") | Y16: 4 | Z16: 3 | AB16: =IF(Z16="","",Z16+0.5*N(AA16)) | AC16: 3 | AD16: 1 | AE16: ready | AF16: Ready Now | AH16: =IF(AG16="","",1-V16/AG16) | AK16: 15829 Moran Meadow Street | AL16: 30.7 | AM16: Houston | AN16: 326778 | AO16: -0.0227 | AP16: 335775 | AQ16: 153 | AR16: 2842 | AU16: https://www.davidweekleyhomes.com/new-homes/tx/houston/conroe/artavia | AV16: https://www.davidweekleyhomes.com/new-homes/tx/houston/conroe/artavia | AW16: h85506c7d7 | AX16: 2026-09-27
A17: 16 | B17: houston | C17: hou-artavia | D17: ARTAVIA | E17: Montgomery | F17: Conroe | G17: 77302 | H17: AIRIA Development Company | I17: Conroe ISD | J17: David Weekley Homes | K17: b-houston-david-weekley-homes | L17: National builder | M17: Yes | N17: No | O17: No | Q17: hou-artavia#5 | R17: Parkview Collection | S17: 65 | T17: 65 | U17: Plan B071 | V17: 624990 | W17: 3076 | X17: =IF(W17>0,V17/W17,"") | Y17: 4 | Z17: 3 | AB17: =IF(Z17="","",Z17+0.5*N(AA17)) | AC17: 4 | AD17: 1 | AE17: ready | AF17: Ready Now | AH17: =IF(AG17="","",1-V17/AG17) | AK17: 18023 Lobos Point Lane | AL17: 30.7 | AM17: Houston | AN17: 326778 | AO17: -0.0227 | AP17: 335775 | AQ17: 153 | AR17: 2842 | AU17: https://www.davidweekleyhomes.com/new-homes/tx/houston/conroe/artavia | AV17: https://www.davidweekleyhomes.com/new-homes/tx/houston/conroe/artavia | AW17: h19b7298a5 | AX17: 2026-09-27
A18: 17 | B18: houston | C18: hou-artavia | D18: ARTAVIA | E18: Montgomery | F18: Conroe | G18: 77302 | H18: AIRIA Development Company | I18: Conroe ISD | J18: David Weekley Homes | K18: b-houston-david-weekley-homes | L18: National builder | M18: Yes | N18: No | O18: No | Q18: hou-artavia#5 | R18: Parkview Collection | S18: 65 | T18: 65 | U18: Plan T045 | V18: 649990 | W18: 3317 | X18: =IF(W18>0,V18/W18,"") | Y18: 4 | Z18: 3 | AA18: 1 | AB18: =IF(Z18="","",Z18+0.5*N(AA18)) | AC18: 4 | AD18: 1 | AE18: ready | AF18: Ready Now | AH18: =IF(AG18="","",1-V18/AG18) | AK18: 18015 Lobos Point Lane | AL18: 30.7 | AM18: Houston | AN18: 326778 | AO18: -0.0227 | AP18: 335775 | AQ18: 153 | AR18: 2842 | AU18: https://www.davidweekleyhomes.com/new-homes/tx/houston/conroe/artavia | AV18: https://www.davidweekleyhomes.com/new-homes/tx/houston/conroe/artavia | AW18: hecce56ccd | AX18: 2026-09-27
A19: 18 | B19: houston | C19: hou-artavia | D19: ARTAVIA | E19: Montgomery | F19: Conroe | G19: 77302 | H19: AIRIA Development Company | I19: Conroe ISD | J19: David Weekley Homes | K19: b-houston-david-weekley-homes | L19: National builder | M19: Yes | N19: No | O19: No | Q19: hou-artavia#5 | R19: Parkview Collection | S19: 65 | T19: 65 | U19: Plan B443 | V19: 649990 | W19: 4086 | X19: =IF(W19>0,V19/W19,"") | Y19: 4 | Z19: 3 | AA19: 1 | AB19: =IF(Z19="","",Z19+0.5*N(AA19)) | AC19: 3 | AD19: 2 | AE19: ready | AF19: Ready Now | AH19: =IF(AG19="","",1-V19/AG19) | AK19: 15730 Terracotta Terrace Lane | AL19: 30.7 | AM19: Houston | AN19: 326778 | AO19: -0.0227 | AP19: 335775 | AQ19: 153 | AR19: 2842 | AU19: https://www.davidweekleyhomes.com/new-homes/tx/houston/conroe/artavia | AV19: https://www.davidweekleyhomes.com/new-homes/tx/houston/conroe/artavia | AW19: h0357f55ab | AX19: 2026-09-27
A20: 19 | B20: houston | C20: hou-artavia | D20: ARTAVIA | E20: Montgomery | F20: Conroe | G20: 77302 | H20: AIRIA Development Company | I20: Conroe ISD | J20: Highland Homes | K20: b-houston-highland-homes | L20: Two of three counts | M20: Yes | N20: Partly | O20: No | Q20: hou-artavia#6 | R20: 50ft. lots | S20: 50 | T20: 50 | U20: VanGogh Plan | V20: 484990 | W20: 2663 | X20: =IF(W20>0,V20/W20,"") | Y20: 4 | Z20: 3 | AB20: =IF(Z20="","",Z20+0.5*N(AA20)) | AC20: 2 | AD20: 1 | AE20: ready | AF20: Complete | AH20: =IF(AG20="","",1-V20/AG20) | AJ20: $30K Your Way! | AK20: 16642 Jolie Street | AL20: 30.7 | AM20: Houston | AN20: 326778 | AO20: -0.0227 | AP20: 335775 | AQ20: 153 | AR20: 2842 | AU20: https://www.highlandhomes.com/houston/conroe/artavia/50ft-lots/section | AV20: https://www.highlandhomes.com/houston/conroe/artavia/50ft-lots/section | AW20: h142491f78 | AX20: 2026-09-27
A21: 20 | B21: houston | C21: hou-artavia | D21: ARTAVIA | E21: Montgomery | F21: Conroe | G21: 77302 | H21: AIRIA Development Company | I21: Conroe ISD | J21: Highland Homes | K21: b-houston-highland-homes | L21: Two of three counts | M21: Yes | N21: Partly | O21: No | Q21: hou-artavia#6 | R21: 50ft. lots | S21: 50 | T21: 50 | U21: Davenport Plan | V21: 414990 | W21: 2317 | X21: =IF(W21>0,V21/W21,"") | Y21: 4 | Z21: 3 | AB21: =IF(Z21="","",Z21+0.5*N(AA21)) | AC21: 2 | AD21: 1 | AE21: ready | AF21: Move-in Ready | AH21: =IF(AG21="","",1-V21/AG21) | AJ21: $30K Your Way! | AK21: 16622 Jolie Street | AL21: 30.7 | AM21: Houston | AN21: 326778 | AO21: -0.0227 | AP21: 335775 | AQ21: 153 | AR21: 2842 | AU21: https://www.highlandhomes.com/houston/conroe/artavia/50ft-lots/section | AV21: https://www.highlandhomes.com/houston/conroe/artavia/50ft-lots/section | AW21: hb1ada6194 | AX21: 2026-09-27
A22: 21 | B22: houston | C22: hou-artavia | D22: ARTAVIA | E22: Montgomery | F22: Conroe | G22: 77302 | H22: AIRIA Development Company | I22: Conroe ISD | J22: Highland Homes | K22: b-houston-highland-homes | L22: Two of three counts | M22: Yes | N22: Partly | O22: No | Q22: hou-artavia#6 | R22: 50ft. lots | S22: 50 | T22: 50 | U22: Cambridge Plan | V22: 499990 | W22: 2982 | X22: =IF(W22>0,V22/W22,"") | Y22: 4 | Z22: 4 | AB22: =IF(Z22="","",Z22+0.5*N(AA22)) | AC22: 2 | AD22: 2 | AE22: ready | AF22: Move-in Ready | AH22: =IF(AG22="","",1-V22/AG22) | AJ22: $30K Your Way! | AK22: 16543 Mandora Lane | AL22: 30.7 | AM22: Houston | AN22: 326778 | AO22: -0.0227 | AP22: 335775 | AQ22: 153 | AR22: 2842 | AU22: https://www.highlandhomes.com/houston/conroe/artavia/50ft-lots/section | AV22: https://www.highlandhomes.com/houston/conroe/artavia/50ft-lots/section | AW22: hfb86be92f | AX22: 2026-09-27
A23: 22 | B23: houston | C23: hou-artavia | D23: ARTAVIA | E23: Montgomery | F23: Conroe | G23: 77302 | H23: AIRIA Development Company | I23: Conroe ISD | J23: Highland Homes | K23: b-houston-highland-homes | L23: Two of three counts | M23: Yes | N23: Partly | O23: No | Q23: hou-artavia#6 | R23: 50ft. lots | S23: 50 | T23: 50 | U23: Matisse Plan | V23: 424990 | W23: 2264 | X23: =IF(W23>0,V23/W23,"") | Y23: 4 | Z23: 2 | AB23: =IF(Z23="","",Z23+0.5*N(AA23)) | AC23: 2 | AD23: 1 | AE23: ready | AF23: Move-in Ready | AH23: =IF(AG23="","",1-V23/AG23) | AJ23: $30K Your Way! | AK23: 16519 Mandora Lane | AL23: 30.7 | AM23: Houston | AN23: 326778 | AO23: -0.0227 | AP23: 335775 | AQ23: 153 | AR23: 2842 | AU23: https://www.highlandhomes.com/houston/conroe/artavia/50ft-lots/section | AV23: https://www.highlandhomes.com/houston/conroe/artavia/50ft-lots/section | AW23: h65c45f2cd | AX23: 2026-09-27
A24: 23 | B24: houston | C24: hou-artavia | D24: ARTAVIA | E24: Montgomery | F24: Conroe | G24: 77302 | H24: AIRIA Development Company | I24: Conroe ISD | J24: Highland Homes | K24: b-houston-highland-homes | L24: Two of three counts | M24: Yes | N24: Partly | O24: No | Q24: hou-artavia#7 | R24: 60ft. lots | S24: 60 | T24: 60 | U24: Ramsey Plan | V24: 524990 | W24: 2862 | X24: =IF(W24>0,V24/W24,"") | Y24: 4 | Z24: 3 | AA24: 1 | AB24: =IF(Z24="","",Z24+0.5*N(AA24)) | AC24: 3 | AD24: 1 | AE24: ready | AF24: Complete | AH24: =IF(AG24="","",1-V24/AG24) | AJ24: $30K Your Way! | AK24: 15630 Broadway Bend Drive | AL24: 30.7 | AM24: Houston | AN24: 326778 | AO24: -0.0227 | AP24: 335775 | AQ24: 153 | AR24: 2842 | AU24: https://www.highlandhomes.com/houston/conroe/artavia/60ft-lots/section | AV24: https://www.highlandhomes.com/houston/conroe/artavia/60ft-lots/section | AW24: hdab1c5012 | AX24: 2026-09-27
A25: 24 | B25: houston | C25: hou-artavia | D25: ARTAVIA | E25: Montgomery | F25: Conroe | G25: 77302 | H25: AIRIA Development Company | I25: Conroe ISD | J25: Highland Homes | K25: b-houston-highland-homes | L25: Two of three counts | M25: Yes | N25: Partly | O25: No | Q25: hou-artavia#7 | R25: 60ft. lots | S25: 60 | T25: 60 | U25: Birchwood Plan | V25: 549990 | W25: 2815 | X25: =IF(W25>0,V25/W25,"") | Y25: 4 | Z25: 3 | AA25: 1 | AB25: =IF(Z25="","",Z25+0.5*N(AA25)) | AC25: 3 | AD25: 1 | AE25: ready | AF25: Move-in Ready | AH25: =IF(AG25="","",1-V25/AG25) | AJ25: $30K Your Way! | AK25: 16435 Cat Court | AL25: 30.7 | AM25: Houston | AN25: 326778 | AO25: -0.0227 | AP25: 335775 | AQ25: 153 | AR25: 2842 | AU25: https://www.highlandhomes.com/houston/conroe/artavia/60ft-lots/section | AV25: https://www.highlandhomes.com/houston/conroe/artavia/60ft-lots/section | AW25: h84ae9dc89 | AX25: 2026-09-27
A26: 25 | B26: houston | C26: hou-artavia | D26: ARTAVIA | E26: Montgomery | F26: Conroe | G26: 77302 | H26: AIRIA Development Company | I26: Conroe ISD | J26: Highland Homes | K26: b-houston-highland-homes | L26: Two of three counts | M26: Yes | N26: Partly | O26: No | Q26: hou-artavia#7 | R26: 60ft. lots | S26: 60 | T26: 60 | U26: Ramsey Plan | V26: 564990 | W26: 2881 | X26: =IF(W26>0,V26/W26,"") | Y26: 4 | Z26: 3 | AA26: 1 | AB26: =IF(Z26="","",Z26+0.5*N(AA26)) | AC26: 3 | AD26: 1 | AH26: =IF(AG26="","",1-V26/AG26) | AJ26: $30K Your Way! | AK26: 18918 Moonriver Street | AL26: 30.7 | AM26: Houston | AN26: 326778 | AO26: -0.0227 | AP26: 335775 | AQ26: 153 | AR26: 2842 | AU26: https://www.highlandhomes.com/houston/conroe/artavia/60ft-lots/section | AV26: https://www.highlandhomes.com/houston/conroe/artavia/60ft-lots/section | AW26: h26c1e8a5e | AX26: 2026-09-27
A27: 26 | B27: houston | C27: hou-artavia | D27: ARTAVIA | E27: Montgomery | F27: Conroe | G27: 77302 | H27: AIRIA Development Company | I27: Conroe ISD | J27: Highland Homes | K27: b-houston-highland-homes | L27: Two of three counts | M27: Yes | N27: Partly | O27: No | Q27: hou-artavia#7 | R27: 60ft. lots | S27: 60 | T27: 60 | U27: Bradford Plan | V27: 559990 | W27: 3057 | X27: =IF(W27>0,V27/W27,"") | Y27: 4 | Z27: 3 | AA27: 1 | AB27: =IF(Z27="","",Z27+0.5*N(AA27)) | AC27: 3 | AD27: 1 | AH27: =IF(AG27="","",1-V27/AG27) | AJ27: $30K Your Way! | AK27: 18206 Hairpin Banksia Lane | AL27: 30.7 | AM27: Houston | AN27: 326778 | AO27: -0.0227 | AP27: 335775 | AQ27: 153 | AR27: 2842 | AU27: https://www.highlandhomes.com/houston/conroe/artavia/60ft-lots/section | AV27: https://www.highlandhomes.com/houston/conroe/artavia/60ft-lots/section | AW27: h7f8dd0326 | AX27: 2026-09-27
A28: 27 | B28: houston | C28: hou-artavia | D28: ARTAVIA | E28: Montgomery | F28: Conroe | G28: 77302 | H28: AIRIA Development Company | I28: Conroe ISD | J28: Jamestown Estate Homes | K28: b-houston-jamestown-estate-homes | L28: Two of three counts | M28: Partly | N28: Yes | O28: No | Q28: hou-artavia#10 | S28: 80 | T28: 80 | V28: 850000 | W28: 3536 | X28: =IF(W28>0,V28/W28,"") | Y28: 4 | AB28: =IF(Z28="","",Z28+0.5*N(AA28)) | AC28: 3 | AH28: =IF(AG28="","",1-V28/AG28) | AK28: 15910 Mango Tango Dr | AL28: 30.7 | AM28: Houston | AN28: 326778 | AO28: -0.0227 | AP28: 335775 | AQ28: 153 | AR28: 2842 | AU28: https://jamestownestatehomes.com/artavia-homebuilders/ | AV28: https://jamestownestatehomes.com/artavia-homebuilders/ | AW28: he8dae311f | AX28: 2026-09-27
A29: 28 | B29: houston | C29: hou-artavia | D29: ARTAVIA | E29: Montgomery | F29: Conroe | G29: 77302 | H29: AIRIA Development Company | I29: Conroe ISD | J29: Jamestown Estate Homes | K29: b-houston-jamestown-estate-homes | L29: Two of three counts | M29: Partly | N29: Yes | O29: No | Q29: hou-artavia#10 | S29: 80 | T29: 80 | V29: 885000 | W29: 3554 | X29: =IF(W29>0,V29/W29,"") | Y29: 4 | AB29: =IF(Z29="","",Z29+0.5*N(AA29)) | AC29: 3 | AH29: =IF(AG29="","",1-V29/AG29) | AL29: 30.7 | AM29: Houston | AN29: 326778 | AO29: -0.0227 | AP29: 335775 | AQ29: 153 | AR29: 2842 | AU29: https://jamestownestatehomes.com/artavia-homebuilders/ | AV29: https://jamestownestatehomes.com/artavia-homebuilders/ | AW29: h414962bc3 | AX29: 2026-09-27
A30: 29 | B30: houston | C30: hou-artavia | D30: ARTAVIA | E30: Montgomery | F30: Conroe | G30: 77302 | H30: AIRIA Development Company | I30: Conroe ISD | J30: Jamestown Estate Homes | K30: b-houston-jamestown-estate-homes | L30: Two of three counts | M30: Partly | N30: Yes | O30: No | Q30: hou-artavia#10 | S30: 80 | T30: 80 | V30: 1059990 | W30: 4318 | X30: =IF(W30>0,V30/W30,"") | Y30: 5 | Z30: 5 | AA30: 1 | AB30: =IF(Z30="","",Z30+0.5*N(AA30)) | AC30: 3 | AH30: =IF(AG30="","",1-V30/AG30) | AL30: 30.7 | AM30: Houston | AN30: 326778 | AO30: -0.0227 | AP30: 335775 | AQ30: 153 | AR30: 2842 | AU30: https://jamestownestatehomes.com/artavia-homebuilders/ | AV30: https://jamestownestatehomes.com/artavia-homebuilders/ | AW30: h4670f7814 | AX30: 2026-09-27
A31: 30 | B31: houston | C31: hou-artavia | D31: ARTAVIA | E31: Montgomery | F31: Conroe | G31: 77302 | H31: AIRIA Development Company | I31: Conroe ISD | J31: Lennar | K31: b-houston-lennar | L31: Lennar and the firms it owns | M31: Yes | N31: No | O31: Yes | P31: Lennar | Q31: hou-artavia#11 | R31: Fairway Collection | S31: 55 | T31: 55 | U31: Cabotll | V31: 330991 | W31: 2386 | X31: =IF(W31>0,V31/W31,"") | Y31: 3 | Z31: 2 | AA31: 1 | AB31: =IF(Z31="","",Z31+0.5*N(AA31)) | AH31: =IF(AG31="","",1-V31/AG31) | AK31: 15047 Goujon Gates Drive | AL31: 30.7 | AM31: Houston | AN31: 326778 | AO31: -0.0227 | AP31: 335775 | AQ31: 153 | AR31: 2842 | AU31: https://www.lennar.com/new-homes/texas/houston/conroe/artavia | AV31: https://www.lennar.com/new-homes/texas/houston/conroe/artavia | AW31: hbf4ca5b27 | AX31: 2026-09-27
A32: 31 | B32: houston | C32: hou-artavia | D32: ARTAVIA | E32: Montgomery | F32: Conroe | G32: 77302 | H32: AIRIA Development Company | I32: Conroe ISD | J32: Lennar | K32: b-houston-lennar | L32: Lennar and the firms it owns | M32: Yes | N32: No | O32: Yes | P32: Lennar | Q32: hou-artavia#11 | R32: Fairway Collection | S32: 55 | T32: 55 | U32: Cabotll | V32: 340990 | W32: 2386 | X32: =IF(W32>0,V32/W32,"") | Y32: 3 | Z32: 2 | AA32: 1 | AB32: =IF(Z32="","",Z32+0.5*N(AA32)) | AH32: =IF(AG32="","",1-V32/AG32) | AK32: 14948 Calluna Heather Lane | AL32: 30.7 | AM32: Houston | AN32: 326778 | AO32: -0.0227 | AP32: 335775 | AQ32: 153 | AR32: 2842 | AU32: https://www.lennar.com/new-homes/texas/houston/conroe/artavia | AV32: https://www.lennar.com/new-homes/texas/houston/conroe/artavia | AW32: h71c3e5995 | AX32: 2026-09-27
A33: 32 | B33: houston | C33: hou-artavia | D33: ARTAVIA | E33: Montgomery | F33: Conroe | G33: 77302 | H33: AIRIA Development Company | I33: Conroe ISD | J33: Lennar | K33: b-houston-lennar | L33: Lennar and the firms it owns | M33: Yes | N33: No | O33: Yes | P33: Lennar | Q33: hou-artavia#11 | R33: Fairway Collection | S33: 55 | T33: 55 | U33: Cabotll | V33: 345990 | W33: 2386 | X33: =IF(W33>0,V33/W33,"") | Y33: 3 | Z33: 2 | AA33: 1 | AB33: =IF(Z33="","",Z33+0.5*N(AA33)) | AH33: =IF(AG33="","",1-V33/AG33) | AK33: 17915 Rillette Road | AL33: 30.7 | AM33: Houston | AN33: 326778 | AO33: -0.0227 | AP33: 335775 | AQ33: 153 | AR33: 2842 | AU33: https://www.lennar.com/new-homes/texas/houston/conroe/artavia | AV33: https://www.lennar.com/new-homes/texas/houston/conroe/artavia | AW33: h068f9e89c | AX33: 2026-09-27
A34: 33 | B34: houston | C34: hou-artavia | D34: ARTAVIA | E34: Montgomery | F34: Conroe | G34: 77302 | H34: AIRIA Development Company | I34: Conroe ISD | J34: Lennar | K34: b-houston-lennar | L34: Lennar and the firms it owns | M34: Yes | N34: No | O34: Yes | P34: Lennar | Q34: hou-artavia#11 | R34: Fairway Collection | S34: 55 | T34: 55 | U34: Glenbrookll | V34: 356990 | W34: 2517 | X34: =IF(W34>0,V34/W34,"") | Y34: 3 | Z34: 2 | AA34: 1 | AB34: =IF(Z34="","",Z34+0.5*N(AA34)) | AE34: ready | AF34: Move-in ready | AH34: =IF(AG34="","",1-V34/AG34) | AK34: 17859 Aile Pierre Pass | AL34: 30.7 | AM34: Houston | AN34: 326778 | AO34: -0.0227 | AP34: 335775 | AQ34: 153 | AR34: 2842 | AU34: https://www.lennar.com/new-homes/texas/houston/conroe/artavia | AV34: https://www.lennar.com/new-homes/texas/houston/conroe/artavia | AW34: h7a0999d05 | AX34: 2026-09-27
A35: 34 | B35: houston | C35: hou-artavia | D35: ARTAVIA | E35: Montgomery | F35: Conroe | G35: 77302 | H35: AIRIA Development Company | I35: Conroe ISD | J35: Ravenna Homes | K35: b-houston-ravenna-homes | L35: Two of three counts | M35: Partly | N35: Partly | O35: No | Q35: hou-artavia#15 | R35: ARTAVIA 70' | S35: 70 | T35: 70 | U35: Plan 4195 | V35: 788900 | W35: 4195 | X35: =IF(W35>0,V35/W35,"") | Y35: 2 | Z35: 2 | AB35: =IF(Z35="","",Z35+0.5*N(AA35)) | AD35: 2 | AE35: ready | AF35: complete | AG35: 870900 | AH35: =IF(AG35="","",1-V35/AG35) | AK35: 15607 Early Bird Lane | AL35: 30.7 | AM35: Houston | AN35: 326778 | AO35: -0.0227 | AP35: 335775 | AQ35: 153 | AR35: 2842 | AU35: https://www.ravennahomes.com/communities/artavia-70/ | AV35: https://www.ravennahomes.com/communities/artavia-70/ | AW35: h97788cc92 | AX35: 2026-09-27
A36: 35 | B36: houston | C36: hou-artavia | D36: ARTAVIA | E36: Montgomery | F36: Conroe | G36: 77302 | H36: AIRIA Development Company | I36: Conroe ISD | J36: Ravenna Homes | K36: b-houston-ravenna-homes | L36: Two of three counts | M36: Partly | N36: Partly | O36: No | Q36: hou-artavia#15 | R36: ARTAVIA 70' | S36: 70 | T36: 70 | U36: Plan 3865 | V36: 850000 | W36: 4013 | X36: =IF(W36>0,V36/W36,"") | Y36: 2 | Z36: 2 | AB36: =IF(Z36="","",Z36+0.5*N(AA36)) | AC36: 4 | AD36: 2 | AE36: ready | AF36: complete | AG36: 931900 | AH36: =IF(AG36="","",1-V36/AG36) | AK36: 15707 Dandelion Dreams Street | AL36: 30.7 | AM36: Houston | AN36: 326778 | AO36: -0.0227 | AP36: 335775 | AQ36: 153 | AR36: 2842 | AU36: https://www.ravennahomes.com/communities/artavia-70/ | AV36: https://www.ravennahomes.com/communities/artavia-70/ | AW36: h9674ebd10 | AX36: 2026-09-27
A37: 36 | B37: houston | C37: hou-artavia | D37: ARTAVIA | E37: Montgomery | F37: Conroe | G37: 77302 | H37: AIRIA Development Company | I37: Conroe ISD | J37: Ravenna Homes | K37: b-houston-ravenna-homes | L37: Two of three counts | M37: Partly | N37: Partly | O37: No | Q37: hou-artavia#15 | R37: ARTAVIA 70' | S37: 70 | T37: 70 | U37: Plan 4094 | V37: 849900 | W37: 4094 | X37: =IF(W37>0,V37/W37,"") | AB37: =IF(Z37="","",Z37+0.5*N(AA37)) | AC37: 4 | AD37: 2 | AE37: ready | AF37: complete | AG37: 857900 | AH37: =IF(AG37="","",1-V37/AG37) | AL37: 30.7 | AM37: Houston | AN37: 326778 | AO37: -0.0227 | AP37: 335775 | AQ37: 153 | AR37: 2842 | AU37: https://www.ravennahomes.com/communities/artavia-70/ | AV37: https://www.ravennahomes.com/communities/artavia-70/ | AW37: had93dbf29 | AX37: 2026-09-27
A38: 37 | B38: houston | C38: hou-artavia | D38: ARTAVIA | E38: Montgomery | F38: Conroe | G38: 77302 | H38: AIRIA Development Company | I38: Conroe ISD | J38: Ravenna Homes | K38: b-houston-ravenna-homes | L38: Two of three counts | M38: Partly | N38: Partly | O38: No | Q38: hou-artavia#15 | R38: ARTAVIA 70' | S38: 70 | T38: 70 | U38: Plan 4290 | V38: 878900 | W38: 4290 | X38: =IF(W38>0,V38/W38,"") | AB38: =IF(Z38="","",Z38+0.5*N(AA38)) | AC38: 1 | AD38: 1 | AE38: ready | AF38: completed | AG38: 886900 | AH38: =IF(AG38="","",1-V38/AG38) | AK38: 17576 Watercolor Way | AL38: 30.7 | AM38: Houston | AN38: 326778 | AO38: -0.0227 | AP38: 335775 | AQ38: 153 | AR38: 2842 | AU38: https://www.ravennahomes.com/communities/artavia-70/ | AV38: https://www.ravennahomes.com/communities/artavia-70/ | AW38: h817279876 | AX38: 2026-09-27
A39: 38 | B39: houston | C39: hou-artavia | D39: ARTAVIA | E39: Montgomery | F39: Conroe | G39: 77302 | H39: AIRIA Development Company | I39: Conroe ISD | J39: Westin Homes | K39: b-houston-westin-homes | L39: Two of three counts | M39: Yes | N39: Partly | O39: No | Q39: hou-artavia#16 | R39: ARTAVIA 40' | S39: 40 | T39: 40 | U39: The Haven X | V39: 419630 | W39: 2580 | X39: =IF(W39>0,V39/W39,"") | Y39: 4 | Z39: 3 | AA39: 1 | AB39: =IF(Z39="","",Z39+0.5*N(AA39)) | AC39: 2 | AH39: =IF(AG39="","",1-V39/AG39) | AK39: 15819 Swan Lake Lane | AL39: 30.7 | AM39: Houston | AN39: 326778 | AO39: -0.0227 | AP39: 335775 | AQ39: 153 | AR39: 2842 | AU39: https://www.westin-homes.com/communities/houston/artavia/artavia-40 | AV39: https://www.westin-homes.com/communities/houston/artavia/artavia-40 | AW39: h001de6d11 | AX39: 2026-09-27
A40: 39 | B40: houston | C40: hou-artavia | D40: ARTAVIA | E40: Montgomery | F40: Conroe | G40: 77302 | H40: AIRIA Development Company | I40: Conroe ISD | J40: Westin Homes | K40: b-houston-westin-homes | L40: Two of three counts | M40: Yes | N40: Partly | O40: No | Q40: hou-artavia#16 | R40: ARTAVIA 40' | S40: 40 | T40: 40 | U40: The Dominion | V40: 439496 | W40: 2600 | X40: =IF(W40>0,V40/W40,"") | Y40: 4 | Z40: 3 | AA40: 1 | AB40: =IF(Z40="","",Z40+0.5*N(AA40)) | AC40: 2 | AH40: =IF(AG40="","",1-V40/AG40) | AK40: 15710 Juliet Court | AL40: 30.7 | AM40: Houston | AN40: 326778 | AO40: -0.0227 | AP40: 335775 | AQ40: 153 | AR40: 2842 | AU40: https://www.westin-homes.com/communities/houston/artavia/artavia-40 | AV40: https://www.westin-homes.com/communities/houston/artavia/artavia-40 | AW40: h18d2705b2 | AX40: 2026-09-27
A41: 40 | B41: houston | C41: hou-artavia | D41: ARTAVIA | E41: Montgomery | F41: Conroe | G41: 77302 | H41: AIRIA Development Company | I41: Conroe ISD | J41: Westin Homes | K41: b-houston-westin-homes | L41: Two of three counts | M41: Yes | N41: Partly | O41: No | Q41: hou-artavia#16 | R41: ARTAVIA 40' | S41: 40 | T41: 40 | U41: The Dominion | V41: 449374 | W41: 2600 | X41: =IF(W41>0,V41/W41,"") | Y41: 4 | Z41: 3 | AA41: 1 | AB41: =IF(Z41="","",Z41+0.5*N(AA41)) | AC41: 2 | AH41: =IF(AG41="","",1-V41/AG41) | AK41: 15823 Swan Lake Lane | AL41: 30.7 | AM41: Houston | AN41: 326778 | AO41: -0.0227 | AP41: 335775 | AQ41: 153 | AR41: 2842 | AU41: https://www.westin-homes.com/communities/houston/artavia/artavia-40 | AV41: https://www.westin-homes.com/communities/houston/artavia/artavia-40 | AW41: h0ddfa0741 | AX41: 2026-09-27
A42: 41 | B42: houston | C42: hou-artavia | D42: ARTAVIA | E42: Montgomery | F42: Conroe | G42: 77302 | H42: AIRIA Development Company | I42: Conroe ISD | J42: Westin Homes | K42: b-houston-westin-homes | L42: Two of three counts | M42: Yes | N42: Partly | O42: No | Q42: hou-artavia#16 | R42: ARTAVIA 40' | S42: 40 | T42: 40 | U42: The Manor | V42: 458280 | W42: 2633 | X42: =IF(W42>0,V42/W42,"") | Y42: 4 | Z42: 3 | AB42: =IF(Z42="","",Z42+0.5*N(AA42)) | AC42: 2 | AH42: =IF(AG42="","",1-V42/AG42) | AK42: 15815 Swan Lake Lane | AL42: 30.7 | AM42: Houston | AN42: 326778 | AO42: -0.0227 | AP42: 335775 | AQ42: 153 | AR42: 2842 | AU42: https://www.westin-homes.com/communities/houston/artavia/artavia-40 | AV42: https://www.westin-homes.com/communities/houston/artavia/artavia-40 | AW42: h7e1dc0000 | AX42: 2026-09-27
A43: 42 | B43: houston | C43: hou-artavia | D43: ARTAVIA | E43: Montgomery | F43: Conroe | G43: 77302 | H43: AIRIA Development Company | I43: Conroe ISD | J43: Westin Homes | K43: b-houston-westin-homes | L43: Two of three counts | M43: Yes | N43: Partly | O43: No | Q43: hou-artavia#16 | R43: ARTAVIA 40' | S43: 40 | T43: 40 | U43: The Park Avenue II | V43: 484748 | W43: 2800 | X43: =IF(W43>0,V43/W43,"") | Y43: 5 | Z43: 4 | AB43: =IF(Z43="","",Z43+0.5*N(AA43)) | AC43: 2 | AH43: =IF(AG43="","",1-V43/AG43) | AK43: 15703 Juliet Court | AL43: 30.7 | AM43: Houston | AN43: 326778 | AO43: -0.0227 | AP43: 335775 | AQ43: 153 | AR43: 2842 | AU43: https://www.westin-homes.com/communities/houston/artavia/artavia-40 | AV43: https://www.westin-homes.com/communities/houston/artavia/artavia-40 | AW43: h5252515c5 | AX43: 2026-09-27
A44: 43 | B44: houston | C44: hou-artavia | D44: ARTAVIA | E44: Montgomery | F44: Conroe | G44: 77302 | H44: AIRIA Development Company | I44: Conroe ISD | J44: Westin Homes | K44: b-houston-westin-homes | L44: Two of three counts | M44: Yes | N44: Partly | O44: No | Q44: hou-artavia#17 | R44: ARTAVIA 60' | S44: 60 | T44: 60 | U44: The Collins | V44: 569918 | W44: 3498 | X44: =IF(W44>0,V44/W44,"") | Y44: 4 | Z44: 3 | AA44: 1 | AB44: =IF(Z44="","",Z44+0.5*N(AA44)) | AC44: 3 | AH44: =IF(AG44="","",1-V44/AG44) | AK44: 16419 Cat Court | AL44: 30.7 | AM44: Houston | AN44: 326778 | AO44: -0.0227 | AP44: 335775 | AQ44: 153 | AR44: 2842 | AU44: https://www.westin-homes.com/communities/houston/artavia/artavia-60 | AV44: https://www.westin-homes.com/communities/houston/artavia/artavia-60 | AW44: hbc3df5ebd | AX44: 2026-09-27
A45: 44 | B45: houston | C45: hou-artavia | D45: ARTAVIA | E45: Montgomery | F45: Conroe | G45: 77302 | H45: AIRIA Development Company | I45: Conroe ISD | J45: Westin Homes | K45: b-houston-westin-homes | L45: Two of three counts | M45: Yes | N45: Partly | O45: No | Q45: hou-artavia#17 | R45: ARTAVIA 60' | S45: 60 | T45: 60 | U45: The Carter IX | V45: 599209 | W45: 3700 | X45: =IF(W45>0,V45/W45,"") | Y45: 5 | Z45: 4 | AA45: 1 | AB45: =IF(Z45="","",Z45+0.5*N(AA45)) | AC45: 2 | AH45: =IF(AG45="","",1-V45/AG45) | AK45: 16407 Cat Court | AL45: 30.7 | AM45: Houston | AN45: 326778 | AO45: -0.0227 | AP45: 335775 | AQ45: 153 | AR45: 2842 | AU45: https://www.westin-homes.com/communities/houston/artavia/artavia-60 | AV45: https://www.westin-homes.com/communities/houston/artavia/artavia-60 | AW45: h20664e4c5 | AX45: 2026-09-27
A46: 45 | B46: houston | C46: hou-artavia | D46: ARTAVIA | E46: Montgomery | F46: Conroe | G46: 77302 | H46: AIRIA Development Company | I46: Conroe ISD | J46: Westin Homes | K46: b-houston-westin-homes | L46: Two of three counts | M46: Yes | N46: Partly | O46: No | Q46: hou-artavia#17 | R46: ARTAVIA 60' | S46: 60 | T46: 60 | U46: The Asher X | V46: 599408 | W46: 3682 | X46: =IF(W46>0,V46/W46,"") | Y46: 5 | Z46: 4 | AA46: 1 | AB46: =IF(Z46="","",Z46+0.5*N(AA46)) | AC46: 3 | AH46: =IF(AG46="","",1-V46/AG46) | AK46: 18834 Truman Trail | AL46: 30.7 | AM46: Houston | AN46: 326778 | AO46: -0.0227 | AP46: 335775 | AQ46: 153 | AR46: 2842 | AU46: https://www.westin-homes.com/communities/houston/artavia/artavia-60 | AV46: https://www.westin-homes.com/communities/houston/artavia/artavia-60 | AW46: h432243983 | AX46: 2026-09-27
A47: 46 | B47: houston | C47: hou-artavia | D47: ARTAVIA | E47: Montgomery | F47: Conroe | G47: 77302 | H47: AIRIA Development Company | I47: Conroe ISD | J47: Westin Homes | K47: b-houston-westin-homes | L47: Two of three counts | M47: Yes | N47: Partly | O47: No | Q47: hou-artavia#17 | R47: ARTAVIA 60' | S47: 60 | T47: 60 | U47: The Asher X | V47: 599508 | W47: 3682 | X47: =IF(W47>0,V47/W47,"") | Y47: 5 | Z47: 4 | AA47: 1 | AB47: =IF(Z47="","",Z47+0.5*N(AA47)) | AC47: 3 | AH47: =IF(AG47="","",1-V47/AG47) | AK47: 16423 Cat Court | AL47: 30.7 | AM47: Houston | AN47: 326778 | AO47: -0.0227 | AP47: 335775 | AQ47: 153 | AR47: 2842 | AU47: https://www.westin-homes.com/communities/houston/artavia/artavia-60 | AV47: https://www.westin-homes.com/communities/houston/artavia/artavia-60 | AW47: hfa3fff884 | AX47: 2026-09-27
A48: 47 | B48: houston | C48: hou-artavia | D48: ARTAVIA | E48: Montgomery | F48: Conroe | G48: 77302 | H48: AIRIA Development Company | I48: Conroe ISD | J48: Westin Homes | K48: b-houston-westin-homes | L48: Two of three counts | M48: Yes | N48: Partly | O48: No | Q48: hou-artavia#17 | R48: ARTAVIA 60' | S48: 60 | T48: 60 | U48: The Stella | V48: 599592 | W48: 3593 | X48: =IF(W48>0,V48/W48,"") | Y48: 4 | Z48: 3 | AA48: 1 | AB48: =IF(Z48="","",Z48+0.5*N(AA48)) | AC48: 3 | AH48: =IF(AG48="","",1-V48/AG48) | AK48: 18826 Truman Trail | AL48: 30.7 | AM48: Houston | AN48: 326778 | AO48: -0.0227 | AP48: 335775 | AQ48: 153 | AR48: 2842 | AU48: https://www.westin-homes.com/communities/houston/artavia/artavia-60 | AV48: https://www.westin-homes.com/communities/houston/artavia/artavia-60 | AW48: h85ad81618 | AX48: 2026-09-27
A49: 48 | B49: houston | C49: hou-artavia | D49: ARTAVIA | E49: Montgomery | F49: Conroe | G49: 77302 | H49: AIRIA Development Company | I49: Conroe ISD | J49: Westin Homes | K49: b-houston-westin-homes | L49: Two of three counts | M49: Yes | N49: Partly | O49: No | Q49: hou-artavia#18 | R49: ARTAVIA 65' Art Collection | S49: 65 | T49: 65 | U49: The St. Helena | V49: 739685 | W49: 4077 | X49: =IF(W49>0,V49/W49,"") | Y49: 4 | Z49: 4 | AA49: 1 | AB49: =IF(Z49="","",Z49+0.5*N(AA49)) | AC49: 3 | AH49: =IF(AG49="","",1-V49/AG49) | AK49: 15114 Parasol Place | AL49: 30.7 | AM49: Houston | AN49: 326778 | AO49: -0.0227 | AP49: 335775 | AQ49: 153 | AR49: 2842 | AU49: https://www.westin-homes.com/communities/houston/artavia/artavia-65-art-collection | AV49: https://www.westin-homes.com/communities/houston/artavia/artavia-65-art-collection | AW49: hdb8023be3 | AX49: 2026-09-27
A50: 49 | B50: houston | C50: hou-artavia | D50: ARTAVIA | E50: Montgomery | F50: Conroe | G50: 77302 | H50: AIRIA Development Company | I50: Conroe ISD | J50: Westin Homes | K50: b-houston-westin-homes | L50: Two of three counts | M50: Yes | N50: Partly | O50: No | Q50: hou-artavia#18 | R50: ARTAVIA 65' Art Collection | S50: 65 | T50: 65 | U50: The Napa | V50: 773830 | W50: 4112 | X50: =IF(W50>0,V50/W50,"") | Y50: 4 | Z50: 3 | AA50: 1 | AB50: =IF(Z50="","",Z50+0.5*N(AA50)) | AC50: 3 | AH50: =IF(AG50="","",1-V50/AG50) | AK50: 15133 Parasol Place | AL50: 30.7 | AM50: Houston | AN50: 326778 | AO50: -0.0227 | AP50: 335775 | AQ50: 153 | AR50: 2842 | AU50: https://www.westin-homes.com/communities/houston/artavia/artavia-65-art-collection | AV50: https://www.westin-homes.com/communities/houston/artavia/artavia-65-art-collection | AW50: he71dfb7ec | AX50: 2026-09-27
A51: 50 | B51: houston | C51: hou-amira | D51: Amira | E51: Harris | F51: Tomball | G51: 77377 | H51: Johnson Development | I51: Tomball ISD | J51: Beazer Homes | K51: b-houston-beazer-homes | L51: National builder | M51: Yes | N51: No | O51: No | P51: Beazer Homes | Q51: hou-amira#1 | R51: Amira 45' and 50' Homesites | T51: 45, 50 | U51: Maxwell | V51: 349067 | W51: 1767 | X51: =IF(W51>0,V51/W51,"") | Y51: 3 | Z51: 2 | AB51: =IF(Z51="","",Z51+0.5*N(AA51)) | AE51: under construction | AF51: Available OCT | AH51: =IF(AG51="","",1-V51/AG51) | AJ51: For a limited time, receive up to $75,000 in options on your new to-be-built home when you use a Choice Lender!* | AK51: 21114 Secret Garden Ln | AL51: 29.8 | AM51: Houston | AN51: 396798 | AO51: -0.0119 | AP51: 380000 | AQ51: 164 | AR51: 554 | AU51: https://www.beazer.com/houston-TX/tomball/amira | AV51: https://www.beazer.com/houston-TX/tomball/amira | AW51: h61281e9c7 | AX51: 2026-09-27
A52: 51 | B52: houston | C52: hou-amira | D52: Amira | E52: Harris | F52: Tomball | G52: 77377 | H52: Johnson Development | I52: Tomball ISD | J52: Beazer Homes | K52: b-houston-beazer-homes | L52: National builder | M52: Yes | N52: No | O52: No | P52: Beazer Homes | Q52: hou-amira#1 | R52: Amira 45' and 50' Homesites | T52: 45, 50 | U52: Abilene | V52: 396439 | W52: 2175 | X52: =IF(W52>0,V52/W52,"") | Y52: 4 | Z52: 3 | AB52: =IF(Z52="","",Z52+0.5*N(AA52)) | AE52: under construction | AF52: Available DEC | AH52: =IF(AG52="","",1-V52/AG52) | AJ52: For a limited time, receive up to $75,000 in options on your new to-be-built home when you use a Choice Lender!* | AK52: 20735 Open Range Ct | AL52: 29.8 | AM52: Houston | AN52: 396798 | AO52: -0.0119 | AP52: 380000 | AQ52: 164 | AR52: 554 | AU52: https://www.beazer.com/houston-TX/tomball/amira | AV52: https://www.beazer.com/houston-TX/tomball/amira | AW52: hc71197016 | AX52: 2026-09-27
A53: 52 | B53: houston | C53: hou-amira | D53: Amira | E53: Harris | F53: Tomball | G53: 77377 | H53: Johnson Development | I53: Tomball ISD | J53: Beazer Homes | K53: b-houston-beazer-homes | L53: National builder | M53: Yes | N53: No | O53: No | P53: Beazer Homes | Q53: hou-amira#1 | R53: Amira 45' and 50' Homesites | T53: 45, 50 | U53: Somerset | V53: 418112 | W53: 2562 | X53: =IF(W53>0,V53/W53,"") | Y53: 4 | Z53: 3 | AA53: 1 | AB53: =IF(Z53="","",Z53+0.5*N(AA53)) | AE53: under construction | AF53: Available OCT | AH53: =IF(AG53="","",1-V53/AG53) | AJ53: For a limited time, receive up to $75,000 in options on your new to-be-built home when you use a Choice Lender!* | AK53: 21210 Pony Valley Ln | AL53: 29.8 | AM53: Houston | AN53: 396798 | AO53: -0.0119 | AP53: 380000 | AQ53: 164 | AR53: 554 | AU53: https://www.beazer.com/houston-TX/tomball/amira | AV53: https://www.beazer.com/houston-TX/tomball/amira | AW53: h0dd1a788d | AX53: 2026-09-27
A54: 53 | B54: houston | C54: hou-amira | D54: Amira | E54: Harris | F54: Tomball | G54: 77377 | H54: Johnson Development | I54: Tomball ISD | J54: Beazer Homes | K54: b-houston-beazer-homes | L54: National builder | M54: Yes | N54: No | O54: No | P54: Beazer Homes | Q54: hou-amira#1 | R54: Amira 45' and 50' Homesites | T54: 45, 50 | U54: Summerfield | V54: 499250 | W54: 3196 | X54: =IF(W54>0,V54/W54,"") | Y54: 4 | Z54: 3 | AA54: 1 | AB54: =IF(Z54="","",Z54+0.5*N(AA54)) | AE54: under construction | AF54: Available OCT | AH54: =IF(AG54="","",1-V54/AG54) | AJ54: For a limited time, receive up to $75,000 in options on your new to-be-built home when you use a Choice Lender!* | AK54: 20522 Galineers Cob Dr | AL54: 29.8 | AM54: Houston | AN54: 396798 | AO54: -0.0119 | AP54: 380000 | AQ54: 164 | AR54: 554 | AU54: https://www.beazer.com/houston-TX/tomball/amira | AV54: https://www.beazer.com/houston-TX/tomball/amira | AW54: h3e0d926d0 | AX54: 2026-09-27
A55: 54 | B55: houston | C55: hou-amira | D55: Amira | E55: Harris | F55: Tomball | G55: 77377 | H55: Johnson Development | I55: Tomball ISD | J55: Beazer Homes | K55: b-houston-beazer-homes | L55: National builder | M55: Yes | N55: No | O55: No | P55: Beazer Homes | Q55: hou-amira#1 | R55: Amira 45' and 50' Homesites | T55: 45, 50 | U55: Sedona | V55: 548462 | W55: 2947 | X55: =IF(W55>0,V55/W55,"") | Y55: 4 | Z55: 3 | AA55: 1 | AB55: =IF(Z55="","",Z55+0.5*N(AA55)) | AE55: under construction | AF55: Available DEC | AH55: =IF(AG55="","",1-V55/AG55) | AJ55: For a limited time, receive up to $75,000 in options on your new to-be-built home when you use a Choice Lender!* | AK55: 20515 Wagon Chase Dr | AL55: 29.8 | AM55: Houston | AN55: 396798 | AO55: -0.0119 | AP55: 380000 | AQ55: 164 | AR55: 554 | AU55: https://www.beazer.com/houston-TX/tomball/amira | AV55: https://www.beazer.com/houston-TX/tomball/amira | AW55: h2ad7882c1 | AX55: 2026-09-27
A56: 55 | B56: houston | C56: hou-anniston | D56: Anniston | E56: Harris | F56: Katy | G56: 77493 | H56: Friendswood Development Company | I56: Katy ISD | J56: Lennar | K56: b-houston-lennar | L56: Lennar and the firms it owns | M56: Yes | N56: No | O56: Yes | P56: Lennar | Q56: hou-anniston#1 | R56: Cottage Collection | U56: Oakridge | V56: 229990 | W56: 1311 | X56: =IF(W56>0,V56/W56,"") | Y56: 3 | Z56: 2 | AB56: =IF(Z56="","",Z56+0.5*N(AA56)) | AE56: ready | AF56: Move-in ready | AH56: =IF(AG56="","",1-V56/AG56) | AK56: 26850 Lollipop Pink Lane | AL56: 28.4 | AM56: Houston | AN56: 336733 | AO56: -0.0396 | AP56: 340000 | AQ56: 159 | AS56: 12 | AU56: https://www.lennar.com/new-homes/texas/houston/katy/anniston/cottage-collection | AV56: https://www.lennar.com/new-homes/texas/houston/katy/anniston/cottage-collection | AW56: ha3dfbc147 | AX56: 2026-09-27
A57: 56 | B57: houston | C57: hou-anniston | D57: Anniston | E57: Harris | F57: Katy | G57: 77493 | H57: Friendswood Development Company | I57: Katy ISD | J57: Lennar | K57: b-houston-lennar | L57: Lennar and the firms it owns | M57: Yes | N57: No | O57: Yes | P57: Lennar | Q57: hou-anniston#1 | R57: Cottage Collection | U57: Kitson | V57: 229990 | W57: 1451 | X57: =IF(W57>0,V57/W57,"") | Y57: 3 | Z57: 2 | AB57: =IF(Z57="","",Z57+0.5*N(AA57)) | AE57: ready | AF57: Move-in ready | AH57: =IF(AG57="","",1-V57/AG57) | AK57: 26854 Lollipop Pink Lane | AL57: 28.4 | AM57: Houston | AN57: 336733 | AO57: -0.0396 | AP57: 340000 | AQ57: 159 | AS57: 12 | AU57: https://www.lennar.com/new-homes/texas/houston/katy/anniston/cottage-collection | AV57: https://www.lennar.com/new-homes/texas/houston/katy/anniston/cottage-collection | AW57: h66b7b3ab2 | AX57: 2026-09-27
A58: 57 | B58: houston | C58: hou-anniston | D58: Anniston | E58: Harris | F58: Katy | G58: 77493 | H58: Friendswood Development Company | I58: Katy ISD | J58: Lennar | K58: b-houston-lennar | L58: Lennar and the firms it owns | M58: Yes | N58: No | O58: Yes | P58: Lennar | Q58: hou-anniston#1 | R58: Cottage Collection | U58: Idlewood | V58: 236990 | W58: 1461 | X58: =IF(W58>0,V58/W58,"") | Y58: 3 | Z58: 2 | AB58: =IF(Z58="","",Z58+0.5*N(AA58)) | AE58: ready | AF58: Move-in ready | AH58: =IF(AG58="","",1-V58/AG58) | AK58: 26715 Cascade Sunrise Street | AL58: 28.4 | AM58: Houston | AN58: 336733 | AO58: -0.0396 | AP58: 340000 | AQ58: 159 | AS58: 12 | AU58: https://www.lennar.com/new-homes/texas/houston/katy/anniston/cottage-collection | AV58: https://www.lennar.com/new-homes/texas/houston/katy/anniston/cottage-collection | AW58: h3ca2986a0 | AX58: 2026-09-27
A59: 58 | B59: houston | C59: hou-anniston | D59: Anniston | E59: Harris | F59: Katy | G59: 77493 | H59: Friendswood Development Company | I59: Katy ISD | J59: Lennar | K59: b-houston-lennar | L59: Lennar and the firms it owns | M59: Yes | N59: No | O59: Yes | P59: Lennar | Q59: hou-anniston#1 | R59: Cottage Collection | U59: Pinehollow | V59: 243990 | W59: 1656 | X59: =IF(W59>0,V59/W59,"") | Y59: 4 | Z59: 2 | AB59: =IF(Z59="","",Z59+0.5*N(AA59)) | AE59: ready | AF59: Move-in ready | AH59: =IF(AG59="","",1-V59/AG59) | AK59: 6118 Bayberry Blooms Lane | AL59: 28.4 | AM59: Houston | AN59: 336733 | AO59: -0.0396 | AP59: 340000 | AQ59: 159 | AS59: 12 | AU59: https://www.lennar.com/new-homes/texas/houston/katy/anniston/cottage-collection | AV59: https://www.lennar.com/new-homes/texas/houston/katy/anniston/cottage-collection | AW59: hd8b4f8b11 | AX59: 2026-09-27
A60: 59 | B60: houston | C60: hou-anniston | D60: Anniston | E60: Harris | F60: Katy | G60: 77493 | H60: Friendswood Development Company | I60: Katy ISD | J60: Lennar | K60: b-houston-lennar | L60: Lennar and the firms it owns | M60: Yes | N60: No | O60: Yes | P60: Lennar | Q60: hou-anniston#1 | R60: Cottage Collection | U60: Whitetail | V60: 288990 | W60: 2039 | X60: =IF(W60>0,V60/W60,"") | Y60: 4 | Z60: 2 | AA60: 1 | AB60: =IF(Z60="","",Z60+0.5*N(AA60)) | AE60: ready | AF60: Move-in ready | AH60: =IF(AG60="","",1-V60/AG60) | AK60: 26842 Lollipop Pink Lane | AL60: 28.4 | AM60: Houston | AN60: 336733 | AO60: -0.0396 | AP60: 340000 | AQ60: 159 | AS60: 12 | AU60: https://www.lennar.com/new-homes/texas/houston/katy/anniston/cottage-collection | AV60: https://www.lennar.com/new-homes/texas/houston/katy/anniston/cottage-collection | AW60: hd09f0c7bb | AX60: 2026-09-27
A61: 60 | B61: houston | C61: hou-anniston | D61: Anniston | E61: Harris | F61: Katy | G61: 77493 | H61: Friendswood Development Company | I61: Katy ISD | J61: Lennar | K61: b-houston-lennar | L61: Lennar and the firms it owns | M61: Yes | N61: No | O61: Yes | P61: Lennar | Q61: hou-anniston#2 | R61: Watermill Collection | U61: Beckman | V61: 235990 | W61: 1302 | X61: =IF(W61>0,V61/W61,"") | Y61: 3 | Z61: 2 | AB61: =IF(Z61="","",Z61+0.5*N(AA61)) | AE61: ready | AF61: Move-in ready | AH61: =IF(AG61="","",1-V61/AG61) | AK61: 26903 Scarlet Willow Drive | AL61: 28.4 | AM61: Houston | AN61: 336733 | AO61: -0.0396 | AP61: 340000 | AQ61: 159 | AS61: 12 | AU61: https://www.lennar.com/new-homes/texas/houston/katy/anniston/watermill-collection | AV61: https://www.lennar.com/new-homes/texas/houston/katy/anniston/watermill-collection | AW61: h4116ff586 | AX61: 2026-09-27
A62: 61 | B62: houston | C62: hou-anniston | D62: Anniston | E62: Harris | F62: Katy | G62: 77493 | H62: Friendswood Development Company | I62: Katy ISD | J62: Lennar | K62: b-houston-lennar | L62: Lennar and the firms it owns | M62: Yes | N62: No | O62: Yes | P62: Lennar | Q62: hou-anniston#2 | R62: Watermill Collection | U62: Newlin | V62: 240990 | W62: 1522 | X62: =IF(W62>0,V62/W62,"") | Y62: 3 | Z62: 2 | AB62: =IF(Z62="","",Z62+0.5*N(AA62)) | AE62: ready | AF62: Move-in ready | AH62: =IF(AG62="","",1-V62/AG62) | AK62: 26906 Scarlet Willow Drive | AL62: 28.4 | AM62: Houston | AN62: 336733 | AO62: -0.0396 | AP62: 340000 | AQ62: 159 | AS62: 12 | AU62: https://www.lennar.com/new-homes/texas/houston/katy/anniston/watermill-collection | AV62: https://www.lennar.com/new-homes/texas/houston/katy/anniston/watermill-collection | AW62: hd01949005 | AX62: 2026-09-27
A63: 62 | B63: houston | C63: hou-anniston | D63: Anniston | E63: Harris | F63: Katy | G63: 77493 | H63: Friendswood Development Company | I63: Katy ISD | J63: Lennar | K63: b-houston-lennar | L63: Lennar and the firms it owns | M63: Yes | N63: No | O63: Yes | P63: Lennar | Q63: hou-anniston#2 | R63: Watermill Collection | U63: Oxford | V63: 261990 | W63: 1760 | X63: =IF(W63>0,V63/W63,"") | Y63: 4 | Z63: 2 | AB63: =IF(Z63="","",Z63+0.5*N(AA63)) | AE63: ready | AF63: Move-in ready | AH63: =IF(AG63="","",1-V63/AG63) | AK63: 26911 Scarlet Willow Drive | AL63: 28.4 | AM63: Houston | AN63: 336733 | AO63: -0.0396 | AP63: 340000 | AQ63: 159 | AS63: 12 | AU63: https://www.lennar.com/new-homes/texas/houston/katy/anniston/watermill-collection | AV63: https://www.lennar.com/new-homes/texas/houston/katy/anniston/watermill-collection | AW63: h0e275c024 | AX63: 2026-09-27
A64: 63 | B64: houston | C64: hou-anniston | D64: Anniston | E64: Harris | F64: Katy | G64: 77493 | H64: Friendswood Development Company | I64: Katy ISD | J64: Lennar | K64: b-houston-lennar | L64: Lennar and the firms it owns | M64: Yes | N64: No | O64: Yes | P64: Lennar | Q64: hou-anniston#2 | R64: Watermill Collection | U64: Ramsey | V64: 267990 | W64: 1720 | X64: =IF(W64>0,V64/W64,"") | Y64: 4 | Z64: 2 | AB64: =IF(Z64="","",Z64+0.5*N(AA64)) | AE64: ready | AF64: Move-in ready | AH64: =IF(AG64="","",1-V64/AG64) | AK64: 26923 Scarlet Willow Drive | AL64: 28.4 | AM64: Houston | AN64: 336733 | AO64: -0.0396 | AP64: 340000 | AQ64: 159 | AS64: 12 | AU64: https://www.lennar.com/new-homes/texas/houston/katy/anniston/watermill-collection | AV64: https://www.lennar.com/new-homes/texas/houston/katy/anniston/watermill-collection | AW64: h80d5aedc2 | AX64: 2026-09-27
A65: 64 | B65: houston | C65: hou-anniston | D65: Anniston | E65: Harris | F65: Katy | G65: 77493 | H65: Friendswood Development Company | I65: Katy ISD | J65: Lennar | K65: b-houston-lennar | L65: Lennar and the firms it owns | M65: Yes | N65: No | O65: Yes | P65: Lennar | Q65: hou-anniston#2 | R65: Watermill Collection | U65: Littleton | V65: 279990 | W65: 1968 | X65: =IF(W65>0,V65/W65,"") | Y65: 4 | Z65: 2 | AA65: 1 | AB65: =IF(Z65="","",Z65+0.5*N(AA65)) | AE65: ready | AF65: Move-in ready | AH65: =IF(AG65="","",1-V65/AG65) | AK65: 6307 Green Pedal Lane | AL65: 28.4 | AM65: Houston | AN65: 336733 | AO65: -0.0396 | AP65: 340000 | AQ65: 159 | AS65: 12 | AU65: https://www.lennar.com/new-homes/texas/houston/katy/anniston/watermill-collection | AV65: https://www.lennar.com/new-homes/texas/houston/katy/anniston/watermill-collection | AW65: h54552b844 | AX65: 2026-09-27
A66: 65 | B66: houston | C66: hou-anniston | D66: Anniston | E66: Harris | F66: Katy | G66: 77493 | H66: Friendswood Development Company | I66: Katy ISD | J66: Lennar | K66: b-houston-lennar | L66: Lennar and the firms it owns | M66: Yes | N66: No | O66: Yes | P66: Lennar | Q66: hou-anniston#3 | R66: Classic Collection | U66: Frey | V66: 277990 | W66: 1629 | X66: =IF(W66>0,V66/W66,"") | Y66: 3 | Z66: 2 | AB66: =IF(Z66="","",Z66+0.5*N(AA66)) | AE66: ready | AF66: Move-in ready | AH66: =IF(AG66="","",1-V66/AG66) | AK66: 26522 Cascade Sunrise Street | AL66: 28.4 | AM66: Houston | AN66: 336733 | AO66: -0.0396 | AP66: 340000 | AQ66: 159 | AS66: 12 | AU66: https://www.lennar.com/new-homes/texas/houston/katy/anniston/classic-collection | AV66: https://www.lennar.com/new-homes/texas/houston/katy/anniston/classic-collection | AW66: h7ad550597 | AX66: 2026-09-27
A67: 66 | B67: houston | C67: hou-anniston | D67: Anniston | E67: Harris | F67: Katy | G67: 77493 | H67: Friendswood Development Company | I67: Katy ISD | J67: Lennar | K67: b-houston-lennar | L67: Lennar and the firms it owns | M67: Yes | N67: No | O67: Yes | P67: Lennar | Q67: hou-anniston#3 | R67: Classic Collection | U67: Walsh | V67: 293990 | W67: 1924 | X67: =IF(W67>0,V67/W67,"") | Y67: 4 | Z67: 2 | AB67: =IF(Z67="","",Z67+0.5*N(AA67)) | AE67: ready | AF67: Move-in ready | AH67: =IF(AG67="","",1-V67/AG67) | AK67: 26514 Cascade Sunrise Street | AL67: 28.4 | AM67: Houston | AN67: 336733 | AO67: -0.0396 | AP67: 340000 | AQ67: 159 | AS67: 12 | AU67: https://www.lennar.com/new-homes/texas/houston/katy/anniston/classic-collection | AV67: https://www.lennar.com/new-homes/texas/houston/katy/anniston/classic-collection | AW67: hafbfd3cc3 | AX67: 2026-09-27
A68: 67 | B68: houston | C68: hou-anniston | D68: Anniston | E68: Harris | F68: Katy | G68: 77493 | H68: Friendswood Development Company | I68: Katy ISD | J68: Lennar | K68: b-houston-lennar | L68: Lennar and the firms it owns | M68: Yes | N68: No | O68: Yes | P68: Lennar | Q68: hou-anniston#3 | R68: Classic Collection | U68: Springsteen | V68: 303990 | W68: 2083 | X68: =IF(W68>0,V68/W68,"") | Y68: 4 | Z68: 2 | AB68: =IF(Z68="","",Z68+0.5*N(AA68)) | AE68: ready | AF68: Move-in ready | AH68: =IF(AG68="","",1-V68/AG68) | AK68: 6315 Mountain Lily Lane | AL68: 28.4 | AM68: Houston | AN68: 336733 | AO68: -0.0396 | AP68: 340000 | AQ68: 159 | AS68: 12 | AU68: https://www.lennar.com/new-homes/texas/houston/katy/anniston/classic-collection | AV68: https://www.lennar.com/new-homes/texas/houston/katy/anniston/classic-collection | AW68: h7771ca03d | AX68: 2026-09-27
A69: 68 | B69: houston | C69: hou-anniston | D69: Anniston | E69: Harris | F69: Katy | G69: 77493 | H69: Friendswood Development Company | I69: Katy ISD | J69: Lennar | K69: b-houston-lennar | L69: Lennar and the firms it owns | M69: Yes | N69: No | O69: Yes | P69: Lennar | Q69: hou-anniston#3 | R69: Classic Collection | U69: Steely | V69: 407990 | W69: 3249 | X69: =IF(W69>0,V69/W69,"") | Y69: 5 | Z69: 4 | AB69: =IF(Z69="","",Z69+0.5*N(AA69)) | AE69: ready | AF69: Move-in ready | AH69: =IF(AG69="","",1-V69/AG69) | AK69: 6303 Lavender Sunset Lane | AL69: 28.4 | AM69: Houston | AN69: 336733 | AO69: -0.0396 | AP69: 340000 | AQ69: 159 | AS69: 12 | AU69: https://www.lennar.com/new-homes/texas/houston/katy/anniston/classic-collection | AV69: https://www.lennar.com/new-homes/texas/houston/katy/anniston/classic-collection | AW69: hf43df9f1a | AX69: 2026-09-27
A70: 69 | B70: houston | C70: hou-anniston | D70: Anniston | E70: Harris | F70: Katy | G70: 77493 | H70: Friendswood Development Company | I70: Katy ISD | J70: Lennar | K70: b-houston-lennar | L70: Lennar and the firms it owns | M70: Yes | N70: No | O70: Yes | P70: Lennar | Q70: hou-anniston#3 | R70: Classic Collection | U70: Steely | V70: 416990 | W70: 3249 | X70: =IF(W70>0,V70/W70,"") | Y70: 5 | Z70: 4 | AB70: =IF(Z70="","",Z70+0.5*N(AA70)) | AE70: under construction | AF70: Under construction | AH70: =IF(AG70="","",1-V70/AG70) | AK70: 26502 Honeysuckle Bloom Circle | AL70: 28.4 | AM70: Houston | AN70: 336733 | AO70: -0.0396 | AP70: 340000 | AQ70: 159 | AS70: 12 | AU70: https://www.lennar.com/new-homes/texas/houston/katy/anniston/classic-collection | AV70: https://www.lennar.com/new-homes/texas/houston/katy/anniston/classic-collection | AW70: hf66007ff0 | AX70: 2026-09-27
A71: 70 | B71: houston | C71: hou-anniston | D71: Anniston | E71: Harris | F71: Katy | G71: 77493 | H71: Friendswood Development Company | I71: Katy ISD | J71: Lennar | K71: b-houston-lennar | L71: Lennar and the firms it owns | M71: Yes | N71: No | O71: Yes | P71: Lennar | Q71: hou-anniston#4 | R71: Eventide Collection | U71: Rio | V71: 280990 | W71: 1724 | X71: =IF(W71>0,V71/W71,"") | Y71: 3 | Z71: 2 | AB71: =IF(Z71="","",Z71+0.5*N(AA71)) | AE71: ready | AF71: Move-in ready | AH71: =IF(AG71="","",1-V71/AG71) | AK71: 6530 Olive Twilight Lane | AL71: 28.4 | AM71: Houston | AN71: 336733 | AO71: -0.0396 | AP71: 340000 | AQ71: 159 | AS71: 12 | AU71: https://www.lennar.com/new-homes/texas/houston/katy/anniston/eventide-collection | AV71: https://www.lennar.com/new-homes/texas/houston/katy/anniston/eventide-collection | AW71: hdf8b4f8cd | AX71: 2026-09-27
A72: 71 | B72: houston | C72: hou-anniston | D72: Anniston | E72: Harris | F72: Katy | G72: 77493 | H72: Friendswood Development Company | I72: Katy ISD | J72: Lennar | K72: b-houston-lennar | L72: Lennar and the firms it owns | M72: Yes | N72: No | O72: Yes | P72: Lennar | Q72: hou-anniston#4 | R72: Eventide Collection | U72: Cornwall | V72: 288990 | W72: 1868 | X72: =IF(W72>0,V72/W72,"") | Y72: 4 | Z72: 3 | AB72: =IF(Z72="","",Z72+0.5*N(AA72)) | AE72: ready | AF72: Move-in ready | AH72: =IF(AG72="","",1-V72/AG72) | AK72: 6518 Olive Twilight Lane | AL72: 28.4 | AM72: Houston | AN72: 336733 | AO72: -0.0396 | AP72: 340000 | AQ72: 159 | AS72: 12 | AU72: https://www.lennar.com/new-homes/texas/houston/katy/anniston/eventide-collection | AV72: https://www.lennar.com/new-homes/texas/houston/katy/anniston/eventide-collection | AW72: h76ac70ebe | AX72: 2026-09-27
A73: 72 | B73: houston | C73: hou-anniston | D73: Anniston | E73: Harris | F73: Katy | G73: 77493 | H73: Friendswood Development Company | I73: Katy ISD | J73: Lennar | K73: b-houston-lennar | L73: Lennar and the firms it owns | M73: Yes | N73: No | O73: Yes | P73: Lennar | Q73: hou-anniston#4 | R73: Eventide Collection | U73: Bergen | V73: 292990 | W73: 1875 | X73: =IF(W73>0,V73/W73,"") | Y73: 4 | Z73: 3 | AB73: =IF(Z73="","",Z73+0.5*N(AA73)) | AE73: ready | AF73: Move-in ready | AH73: =IF(AG73="","",1-V73/AG73) | AK73: 6514 Olive Twilight Lane | AL73: 28.4 | AM73: Houston | AN73: 336733 | AO73: -0.0396 | AP73: 340000 | AQ73: 159 | AS73: 12 | AU73: https://www.lennar.com/new-homes/texas/houston/katy/anniston/eventide-collection | AV73: https://www.lennar.com/new-homes/texas/houston/katy/anniston/eventide-collection | AW73: hf57a3502d | AX73: 2026-09-27
A74: 73 | B74: houston | C74: hou-anniston | D74: Anniston | E74: Harris | F74: Katy | G74: 77493 | H74: Friendswood Development Company | I74: Katy ISD | J74: Lennar | K74: b-houston-lennar | L74: Lennar and the firms it owns | M74: Yes | N74: No | O74: Yes | P74: Lennar | Q74: hou-anniston#4 | R74: Eventide Collection | U74: Bryce | V74: 317990 | W74: 2393 | X74: =IF(W74>0,V74/W74,"") | Y74: 4 | Z74: 3 | AB74: =IF(Z74="","",Z74+0.5*N(AA74)) | AE74: ready | AF74: Move-in ready | AH74: =IF(AG74="","",1-V74/AG74) | AK74: 6543 Olive Twilight Lane | AL74: 28.4 | AM74: Houston | AN74: 336733 | AO74: -0.0396 | AP74: 340000 | AQ74: 159 | AS74: 12 | AU74: https://www.lennar.com/new-homes/texas/houston/katy/anniston/eventide-collection | AV74: https://www.lennar.com/new-homes/texas/houston/katy/anniston/eventide-collection | AW74: h12926027b | AX74: 2026-09-27
A75: 74 | B75: houston | C75: hou-anniston | D75: Anniston | E75: Harris | F75: Katy | G75: 77493 | H75: Friendswood Development Company | I75: Katy ISD | J75: Lennar | K75: b-houston-lennar | L75: Lennar and the firms it owns | M75: Yes | N75: No | O75: Yes | P75: Lennar | Q75: hou-anniston#4 | R75: Eventide Collection | U75: Santo | V75: 356990 | W75: 2637 | X75: =IF(W75>0,V75/W75,"") | Y75: 5 | Z75: 3 | AB75: =IF(Z75="","",Z75+0.5*N(AA75)) | AE75: ready | AF75: Move-in ready | AH75: =IF(AG75="","",1-V75/AG75) | AK75: 26134 Sea Rosemary Lane | AL75: 28.4 | AM75: Houston | AN75: 336733 | AO75: -0.0396 | AP75: 340000 | AQ75: 159 | AS75: 12 | AU75: https://www.lennar.com/new-homes/texas/houston/katy/anniston/eventide-collection | AV75: https://www.lennar.com/new-homes/texas/houston/katy/anniston/eventide-collection | AW75: h784bbdcfa | AX75: 2026-09-27
A76: 75 | B76: houston | C76: hou-anniston | D76: Anniston | E76: Harris | F76: Katy | G76: 77493 | H76: Friendswood Development Company | I76: Katy ISD | J76: Lennar | K76: b-houston-lennar | L76: Lennar and the firms it owns | M76: Yes | N76: No | O76: Yes | P76: Lennar | Q76: hou-anniston#5 | R76: Richmond Collection | U76: Astoria | V76: 299990 | W76: 2013 | X76: =IF(W76>0,V76/W76,"") | Y76: 4 | Z76: 2 | AB76: =IF(Z76="","",Z76+0.5*N(AA76)) | AE76: ready | AF76: Move-in ready | AH76: =IF(AG76="","",1-V76/AG76) | AK76: 26615 Cascade Sunrise Street | AL76: 28.4 | AM76: Houston | AN76: 336733 | AO76: -0.0396 | AP76: 340000 | AQ76: 159 | AS76: 12 | AU76: https://www.lennar.com/new-homes/texas/houston/katy/anniston/richmond-collection | AV76: https://www.lennar.com/new-homes/texas/houston/katy/anniston/richmond-collection | AW76: h05e3feedc | AX76: 2026-09-27
A77: 76 | B77: houston | C77: hou-anniston | D77: Anniston | E77: Harris | F77: Katy | G77: 77493 | H77: Friendswood Development Company | I77: Katy ISD | J77: Lennar | K77: b-houston-lennar | L77: Lennar and the firms it owns | M77: Yes | N77: No | O77: Yes | P77: Lennar | Q77: hou-anniston#5 | R77: Richmond Collection | U77: Winstead | V77: 320990 | W77: 2263 | X77: =IF(W77>0,V77/W77,"") | Y77: 4 | Z77: 3 | AA77: 1 | AB77: =IF(Z77="","",Z77+0.5*N(AA77)) | AE77: ready | AF77: Move-in ready | AH77: =IF(AG77="","",1-V77/AG77) | AK77: 26523 Cascade Sunrise Street | AL77: 28.4 | AM77: Houston | AN77: 336733 | AO77: -0.0396 | AP77: 340000 | AQ77: 159 | AS77: 12 | AU77: https://www.lennar.com/new-homes/texas/houston/katy/anniston/richmond-collection | AV77: https://www.lennar.com/new-homes/texas/houston/katy/anniston/richmond-collection | AW77: h21ef856ba | AX77: 2026-09-27
A78: 77 | B78: houston | C78: hou-anniston | D78: Anniston | E78: Harris | F78: Katy | G78: 77493 | H78: Friendswood Development Company | I78: Katy ISD | J78: Lennar | K78: b-houston-lennar | L78: Lennar and the firms it owns | M78: Yes | N78: No | O78: Yes | P78: Lennar | Q78: hou-anniston#5 | R78: Richmond Collection | U78: Roseman | V78: 362990 | W78: 2731 | X78: =IF(W78>0,V78/W78,"") | Y78: 4 | Z78: 3 | AA78: 1 | AB78: =IF(Z78="","",Z78+0.5*N(AA78)) | AE78: ready | AF78: Move-in ready | AH78: =IF(AG78="","",1-V78/AG78) | AK78: 26611 Golden Heather Lane | AL78: 28.4 | AM78: Houston | AN78: 336733 | AO78: -0.0396 | AP78: 340000 | AQ78: 159 | AS78: 12 | AU78: https://www.lennar.com/new-homes/texas/houston/katy/anniston/richmond-collection | AV78: https://www.lennar.com/new-homes/texas/houston/katy/anniston/richmond-collection | AW78: h8f95eea6f | AX78: 2026-09-27
A79: 78 | B79: houston | C79: hou-anniston | D79: Anniston | E79: Harris | F79: Katy | G79: 77493 | H79: Friendswood Development Company | I79: Katy ISD | J79: Lennar | K79: b-houston-lennar | L79: Lennar and the firms it owns | M79: Yes | N79: No | O79: Yes | P79: Lennar | Q79: hou-anniston#5 | R79: Richmond Collection | U79: Larwood | V79: 376990 | W79: 2902 | X79: =IF(W79>0,V79/W79,"") | Y79: 4 | Z79: 3 | AA79: 1 | AB79: =IF(Z79="","",Z79+0.5*N(AA79)) | AE79: ready | AF79: Move-in ready | AH79: =IF(AG79="","",1-V79/AG79) | AK79: 26607 Cascade Sunrise Street | AL79: 28.4 | AM79: Houston | AN79: 336733 | AO79: -0.0396 | AP79: 340000 | AQ79: 159 | AS79: 12 | AU79: https://www.lennar.com/new-homes/texas/houston/katy/anniston/richmond-collection | AV79: https://www.lennar.com/new-homes/texas/houston/katy/anniston/richmond-collection | AW79: h594fcbf6e | AX79: 2026-09-27
A80: 79 | B80: houston | C80: hou-anniston | D80: Anniston | E80: Harris | F80: Katy | G80: 77493 | H80: Friendswood Development Company | I80: Katy ISD | J80: Lennar | K80: b-houston-lennar | L80: Lennar and the firms it owns | M80: Yes | N80: No | O80: Yes | P80: Lennar | Q80: hou-anniston#5 | R80: Richmond Collection | U80: Newfield | V80: 393990 | W80: 3198 | X80: =IF(W80>0,V80/W80,"") | Y80: 4 | Z80: 3 | AA80: 1 | AB80: =IF(Z80="","",Z80+0.5*N(AA80)) | AE80: ready | AF80: Move-in ready | AH80: =IF(AG80="","",1-V80/AG80) | AK80: 26519 Golden Heather Lane | AL80: 28.4 | AM80: Houston | AN80: 336733 | AO80: -0.0396 | AP80: 340000 | AQ80: 159 | AS80: 12 | AU80: https://www.lennar.com/new-homes/texas/houston/katy/anniston/richmond-collection | AV80: https://www.lennar.com/new-homes/texas/houston/katy/anniston/richmond-collection | AW80: h133a97b1b | AX80: 2026-09-27
A81: 80 | B81: houston | C81: hou-anniston | D81: Anniston | E81: Harris | F81: Katy | G81: 77493 | H81: Friendswood Development Company | I81: Katy ISD | J81: Lennar | K81: b-houston-lennar | L81: Lennar and the firms it owns | M81: Yes | N81: No | O81: Yes | P81: Lennar | Q81: hou-anniston#6 | R81: Pinnacle Collection | U81: Charleston | V81: 335990 | W81: 2423 | X81: =IF(W81>0,V81/W81,"") | Y81: 3 | Z81: 2 | AA81: 1 | AB81: =IF(Z81="","",Z81+0.5*N(AA81)) | AE81: ready | AF81: Move-in ready | AH81: =IF(AG81="","",1-V81/AG81) | AK81: 26315 Little Flower Lane | AL81: 28.4 | AM81: Houston | AN81: 336733 | AO81: -0.0396 | AP81: 340000 | AQ81: 159 | AS81: 12 | AU81: https://www.lennar.com/new-homes/texas/houston/katy/anniston/pinnacle-collection | AV81: https://www.lennar.com/new-homes/texas/houston/katy/anniston/pinnacle-collection | AW81: h98412b457 | AX81: 2026-09-27
A82: 81 | B82: houston | C82: hou-anniston | D82: Anniston | E82: Harris | F82: Katy | G82: 77493 | H82: Friendswood Development Company | I82: Katy ISD | J82: Lennar | K82: b-houston-lennar | L82: Lennar and the firms it owns | M82: Yes | N82: No | O82: Yes | P82: Lennar | Q82: hou-anniston#6 | R82: Pinnacle Collection | U82: Charleston | V82: 338990 | W82: 2423 | X82: =IF(W82>0,V82/W82,"") | Y82: 3 | Z82: 2 | AA82: 1 | AB82: =IF(Z82="","",Z82+0.5*N(AA82)) | AE82: ready | AF82: Move-in ready | AH82: =IF(AG82="","",1-V82/AG82) | AK82: 6302 Firefly Fields Lane | AL82: 28.4 | AM82: Houston | AN82: 336733 | AO82: -0.0396 | AP82: 340000 | AQ82: 159 | AS82: 12 | AU82: https://www.lennar.com/new-homes/texas/houston/katy/anniston/pinnacle-collection | AV82: https://www.lennar.com/new-homes/texas/houston/katy/anniston/pinnacle-collection | AW82: h44ec9451c | AX82: 2026-09-27
A83: 82 | B83: houston | C83: hou-anniston | D83: Anniston | E83: Harris | F83: Katy | G83: 77493 | H83: Friendswood Development Company | I83: Katy ISD | J83: Lennar | K83: b-houston-lennar | L83: Lennar and the firms it owns | M83: Yes | N83: No | O83: Yes | P83: Lennar | Q83: hou-anniston#6 | R83: Pinnacle Collection | U83: Denali | V83: 344990 | W83: 2614 | X83: =IF(W83>0,V83/W83,"") | Y83: 4 | Z83: 3 | AA83: 1 | AB83: =IF(Z83="","",Z83+0.5*N(AA83)) | AE83: ready | AF83: Move-in ready | AH83: =IF(AG83="","",1-V83/AG83) | AK83: 26331 Little Flower Lane | AL83: 28.4 | AM83: Houston | AN83: 336733 | AO83: -0.0396 | AP83: 340000 | AQ83: 159 | AS83: 12 | AU83: https://www.lennar.com/new-homes/texas/houston/katy/anniston/pinnacle-collection | AV83: https://www.lennar.com/new-homes/texas/houston/katy/anniston/pinnacle-collection | AW83: h9b6307c41 | AX83: 2026-09-27
A84: 83 | B84: houston | C84: hou-anniston | D84: Anniston | E84: Harris | F84: Katy | G84: 77493 | H84: Friendswood Development Company | I84: Katy ISD | J84: Lennar | K84: b-houston-lennar | L84: Lennar and the firms it owns | M84: Yes | N84: No | O84: Yes | P84: Lennar | Q84: hou-anniston#6 | R84: Pinnacle Collection | U84: Teton | V84: 426990 | W84: 3671 | X84: =IF(W84>0,V84/W84,"") | Y84: 4 | Z84: 4 | AA84: 1 | AB84: =IF(Z84="","",Z84+0.5*N(AA84)) | AE84: ready | AF84: Move-in ready | AH84: =IF(AG84="","",1-V84/AG84) | AK84: 26311 Little Flower Lane | AL84: 28.4 | AM84: Houston | AN84: 336733 | AO84: -0.0396 | AP84: 340000 | AQ84: 159 | AS84: 12 | AU84: https://www.lennar.com/new-homes/texas/houston/katy/anniston/pinnacle-collection | AV84: https://www.lennar.com/new-homes/texas/houston/katy/anniston/pinnacle-collection | AW84: h722d2cf7e | AX84: 2026-09-27
A85: 84 | B85: houston | C85: hou-anniston | D85: Anniston | E85: Harris | F85: Katy | G85: 77493 | H85: Friendswood Development Company | I85: Katy ISD | J85: Lennar | K85: b-houston-lennar | L85: Lennar and the firms it owns | M85: Yes | N85: No | O85: Yes | P85: Lennar | Q85: hou-anniston#7 | R85: Fairway Collection | U85: Cabot II | V85: 335990 | W85: 2386 | X85: =IF(W85>0,V85/W85,"") | Y85: 3 | Z85: 2 | AA85: 1 | AB85: =IF(Z85="","",Z85+0.5*N(AA85)) | AE85: ready | AF85: Move-in ready | AH85: =IF(AG85="","",1-V85/AG85) | AK85: 26007 Hazel Summit Drive | AL85: 28.4 | AM85: Houston | AN85: 336733 | AO85: -0.0396 | AP85: 340000 | AQ85: 159 | AS85: 12 | AU85: https://www.lennar.com/new-homes/texas/houston/katy/anniston/fairway-collection | AV85: https://www.lennar.com/new-homes/texas/houston/katy/anniston/fairway-collection | AW85: ha56b8da83 | AX85: 2026-09-27
A86: 85 | B86: houston | C86: hou-anniston | D86: Anniston | E86: Harris | F86: Katy | G86: 77493 | H86: Friendswood Development Company | I86: Katy ISD | J86: Lennar | K86: b-houston-lennar | L86: Lennar and the firms it owns | M86: Yes | N86: No | O86: Yes | P86: Lennar | Q86: hou-anniston#7 | R86: Fairway Collection | U86: Somerset | V86: 341990 | W86: 2666 | X86: =IF(W86>0,V86/W86,"") | Y86: 4 | Z86: 3 | AA86: 1 | AB86: =IF(Z86="","",Z86+0.5*N(AA86)) | AE86: ready | AF86: Move-in ready | AH86: =IF(AG86="","",1-V86/AG86) | AK86: 26023 Hazel Summit Drive | AL86: 28.4 | AM86: Houston | AN86: 336733 | AO86: -0.0396 | AP86: 340000 | AQ86: 159 | AS86: 12 | AU86: https://www.lennar.com/new-homes/texas/houston/katy/anniston/fairway-collection | AV86: https://www.lennar.com/new-homes/texas/houston/katy/anniston/fairway-collection | AW86: h4f9a50e88 | AX86: 2026-09-27
A87: 86 | B87: houston | C87: hou-anniston | D87: Anniston | E87: Harris | F87: Katy | G87: 77493 | H87: Friendswood Development Company | I87: Katy ISD | J87: Lennar | K87: b-houston-lennar | L87: Lennar and the firms it owns | M87: Yes | N87: No | O87: Yes | P87: Lennar | Q87: hou-anniston#7 | R87: Fairway Collection | U87: Cantaron II | V87: 352990 | W87: 2548 | X87: =IF(W87>0,V87/W87,"") | Y87: 4 | Z87: 3 | AA87: 1 | AB87: =IF(Z87="","",Z87+0.5*N(AA87)) | AE87: ready | AF87: Move-in ready | AH87: =IF(AG87="","",1-V87/AG87) | AK87: 26011 Hazel Summit Drive | AL87: 28.4 | AM87: Houston | AN87: 336733 | AO87: -0.0396 | AP87: 340000 | AQ87: 159 | AS87: 12 | AU87: https://www.lennar.com/new-homes/texas/houston/katy/anniston/fairway-collection | AV87: https://www.lennar.com/new-homes/texas/houston/katy/anniston/fairway-collection | AW87: he7e48c7ca | AX87: 2026-09-27
A88: 87 | B88: houston | C88: hou-anniston | D88: Anniston | E88: Harris | F88: Katy | G88: 77493 | H88: Friendswood Development Company | I88: Katy ISD | J88: Lennar | K88: b-houston-lennar | L88: Lennar and the firms it owns | M88: Yes | N88: No | O88: Yes | P88: Lennar | Q88: hou-anniston#7 | R88: Fairway Collection | U88: Wakefield II | V88: 382990 | W88: 2795 | X88: =IF(W88>0,V88/W88,"") | Y88: 4 | Z88: 3 | AA88: 1 | AB88: =IF(Z88="","",Z88+0.5*N(AA88)) | AE88: ready | AF88: Move-in ready | AH88: =IF(AG88="","",1-V88/AG88) | AK88: 26019 Hazel Summit Drive | AL88: 28.4 | AM88: Houston | AN88: 336733 | AO88: -0.0396 | AP88: 340000 | AQ88: 159 | AS88: 12 | AU88: https://www.lennar.com/new-homes/texas/houston/katy/anniston/fairway-collection | AV88: https://www.lennar.com/new-homes/texas/houston/katy/anniston/fairway-collection | AW88: h58325abad | AX88: 2026-09-27
A89: 88 | B89: houston | C89: hou-anniston | D89: Anniston | E89: Harris | F89: Katy | G89: 77493 | H89: Friendswood Development Company | I89: Katy ISD | J89: Lennar | K89: b-houston-lennar | L89: Lennar and the firms it owns | M89: Yes | N89: No | O89: Yes | P89: Lennar | Q89: hou-anniston#7 | R89: Fairway Collection | U89: Wakefield II | V89: 384990 | W89: 2795 | X89: =IF(W89>0,V89/W89,"") | Y89: 4 | Z89: 3 | AA89: 1 | AB89: =IF(Z89="","",Z89+0.5*N(AA89)) | AE89: ready | AF89: Move-in ready | AH89: =IF(AG89="","",1-V89/AG89) | AK89: 26002 Overlook Haven Path | AL89: 28.4 | AM89: Houston | AN89: 336733 | AO89: -0.0396 | AP89: 340000 | AQ89: 159 | AS89: 12 | AU89: https://www.lennar.com/new-homes/texas/houston/katy/anniston/fairway-collection | AV89: https://www.lennar.com/new-homes/texas/houston/katy/anniston/fairway-collection | AW89: hb7fbc1e28 | AX89: 2026-09-27
A90: 89 | B90: houston | C90: hou-audubon | D90: Audubon | E90: Montgomery | F90: Magnolia | G90: 77354 | H90: Audubon Magnolia Development, LLC (managed by Sam Yager Inc.) | I90: Magnolia ISD | J90: Century Communities | K90: b-houston-century-communities | L90: National builder | M90: Yes | N90: Partly | O90: No | P90: Century Communities | Q90: hou-audubon#2 | R90: Lonestar Collection | U90: Darlington | V90: 274900 | W90: 1464 | X90: =IF(W90>0,V90/W90,"") | AB90: =IF(Z90="","",Z90+0.5*N(AA90)) | AH90: =IF(AG90="","",1-V90/AG90) | AJ90: Explore Our Special Financing Offers – Available for a Limited Time! | AL90: 38.1 | AM90: Houston | AN90: 378164 | AO90: -0.0149 | AP90: 338065 | AQ90: 164 | AR90: 3000 | AU90: https://www.centurycommunities.com/find-your-new-home/texas/houston-metro/magnolia/audubon/ | AW90: hfd72068c5 | AX90: 2026-09-27
A91: 90 | B91: houston | C91: hou-audubon | D91: Audubon | E91: Montgomery | F91: Magnolia | G91: 77354 | H91: Audubon Magnolia Development, LLC (managed by Sam Yager Inc.) | I91: Magnolia ISD | J91: Century Communities | K91: b-houston-century-communities | L91: National builder | M91: Yes | N91: Partly | O91: No | P91: Century Communities | Q91: hou-audubon#2 | R91: Lonestar Collection | U91: Paisley | V91: 279900 | W91: 1614 | X91: =IF(W91>0,V91/W91,"") | AB91: =IF(Z91="","",Z91+0.5*N(AA91)) | AH91: =IF(AG91="","",1-V91/AG91) | AJ91: Explore Our Special Financing Offers – Available for a Limited Time! | AL91: 38.1 | AM91: Houston | AN91: 378164 | AO91: -0.0149 | AP91: 338065 | AQ91: 164 | AR91: 3000 | AU91: https://www.centurycommunities.com/find-your-new-home/texas/houston-metro/magnolia/audubon/ | AW91: h98dff3c32 | AX91: 2026-09-27
A92: 91 | B92: houston | C92: hou-audubon | D92: Audubon | E92: Montgomery | F92: Magnolia | G92: 77354 | H92: Audubon Magnolia Development, LLC (managed by Sam Yager Inc.) | I92: Magnolia ISD | J92: Century Communities | K92: b-houston-century-communities | L92: National builder | M92: Yes | N92: Partly | O92: No | P92: Century Communities | Q92: hou-audubon#2 | R92: Lonestar Collection | U92: Beckenham | V92: 334900 | W92: 2502 | X92: =IF(W92>0,V92/W92,"") | AB92: =IF(Z92="","",Z92+0.5*N(AA92)) | AH92: =IF(AG92="","",1-V92/AG92) | AJ92: Explore Our Special Financing Offers – Available for a Limited Time! | AL92: 38.1 | AM92: Houston | AN92: 378164 | AO92: -0.0149 | AP92: 338065 | AQ92: 164 | AR92: 3000 | AU92: https://www.centurycommunities.com/find-your-new-home/texas/houston-metro/magnolia/audubon/ | AW92: h341fb965f | AX92: 2026-09-27
A93: 92 | B93: houston | C93: hou-audubon | D93: Audubon | E93: Montgomery | F93: Magnolia | G93: 77354 | H93: Audubon Magnolia Development, LLC (managed by Sam Yager Inc.) | I93: Magnolia ISD | J93: Century Communities | K93: b-houston-century-communities | L93: National builder | M93: Yes | N93: Partly | O93: No | P93: Century Communities | Q93: hou-audubon#2 | R93: Lonestar Collection | U93: Addington | V93: 338900 | W93: 2064 | X93: =IF(W93>0,V93/W93,"") | AB93: =IF(Z93="","",Z93+0.5*N(AA93)) | AH93: =IF(AG93="","",1-V93/AG93) | AJ93: Explore Our Special Financing Offers – Available for a Limited Time! | AL93: 38.1 | AM93: Houston | AN93: 378164 | AO93: -0.0149 | AP93: 338065 | AQ93: 164 | AR93: 3000 | AU93: https://www.centurycommunities.com/find-your-new-home/texas/houston-metro/magnolia/audubon/ | AW93: h3f6582324 | AX93: 2026-09-27
A94: 93 | B94: houston | C94: hou-audubon | D94: Audubon | E94: Montgomery | F94: Magnolia | G94: 77354 | H94: Audubon Magnolia Development, LLC (managed by Sam Yager Inc.) | I94: Magnolia ISD | J94: Century Communities | K94: b-houston-century-communities | L94: National builder | M94: Yes | N94: Partly | O94: No | P94: Century Communities | Q94: hou-audubon#3 | R94: Liberty Collection | U94: Weatherby | V94: 299900 | W94: 1848 | X94: =IF(W94>0,V94/W94,"") | AB94: =IF(Z94="","",Z94+0.5*N(AA94)) | AH94: =IF(AG94="","",1-V94/AG94) | AJ94: Explore Our Special Financing Offers – Available for a Limited Time! | AL94: 38.1 | AM94: Houston | AN94: 378164 | AO94: -0.0149 | AP94: 338065 | AQ94: 164 | AR94: 3000 | AU94: https://www.centurycommunities.com/find-your-new-home/texas/houston-metro/magnolia/audubon/ | AW94: h543e3bd9a | AX94: 2026-09-27
A95: 94 | B95: houston | C95: hou-audubon | D95: Audubon | E95: Montgomery | F95: Magnolia | G95: 77354 | H95: Audubon Magnolia Development, LLC (managed by Sam Yager Inc.) | I95: Magnolia ISD | J95: David Weekley Homes | K95: b-houston-david-weekley-homes | L95: National builder | M95: Yes | N95: No | O95: No | Q95: hou-audubon#6 | R95: Ascent Collection | S95: 55 | T95: 55 | U95: The Wildflower | V95: 465000 | W95: 2095 | X95: =IF(W95>0,V95/W95,"") | Y95: 3 | Z95: 2 | AB95: =IF(Z95="","",Z95+0.5*N(AA95)) | AC95: 2 | AD95: 1 | AH95: =IF(AG95="","",1-V95/AG95) | AJ95: NEW EMPLOYEE PRICING EVENT | UP TO $40,000 IN NEW HOME SAVINGS | AK95: 16741 Heron Oaks Run | AL95: 38.1 | AM95: Houston | AN95: 378164 | AO95: -0.0149 | AP95: 338065 | AQ95: 164 | AR95: 3000 | AU95: https://www.davidweekleyhomes.com/new-homes/tx/houston/magnolia/audubon-55 | AV95: https://www.davidweekleyhomes.com/new-homes/tx/houston/magnolia/audubon-55 | AW95: hba435c7a2 | AX95: 2026-09-27
A96: 95 | B96: houston | C96: hou-audubon | D96: Audubon | E96: Montgomery | F96: Magnolia | G96: 77354 | H96: Audubon Magnolia Development, LLC (managed by Sam Yager Inc.) | I96: Magnolia ISD | J96: David Weekley Homes | K96: b-houston-david-weekley-homes | L96: National builder | M96: Yes | N96: No | O96: No | Q96: hou-audubon#6 | R96: Ascent Collection | S96: 55 | T96: 55 | U96: The Chamomile | V96: 475000 | W96: 2421 | X96: =IF(W96>0,V96/W96,"") | Y96: 4 | Z96: 3 | AA96: 1 | AB96: =IF(Z96="","",Z96+0.5*N(AA96)) | AC96: 3 | AD96: 1 | AH96: =IF(AG96="","",1-V96/AG96) | AJ96: NEW EMPLOYEE PRICING EVENT | UP TO $40,000 IN NEW HOME SAVINGS | AK96: 16855 Deep Wingbeat Way | AL96: 38.1 | AM96: Houston | AN96: 378164 | AO96: -0.0149 | AP96: 338065 | AQ96: 164 | AR96: 3000 | AU96: https://www.davidweekleyhomes.com/new-homes/tx/houston/magnolia/audubon-55 | AV96: https://www.davidweekleyhomes.com/new-homes/tx/houston/magnolia/audubon-55 | AW96: h5abcc4335 | AX96: 2026-09-27
A97: 96 | B97: houston | C97: hou-audubon | D97: Audubon | E97: Montgomery | F97: Magnolia | G97: 77354 | H97: Audubon Magnolia Development, LLC (managed by Sam Yager Inc.) | I97: Magnolia ISD | J97: David Weekley Homes | K97: b-houston-david-weekley-homes | L97: National builder | M97: Yes | N97: No | O97: No | Q97: hou-audubon#6 | R97: Ascent Collection | S97: 55 | T97: 55 | U97: The Larkspur | V97: 511000 | W97: 2359 | X97: =IF(W97>0,V97/W97,"") | Y97: 3 | Z97: 2 | AA97: 1 | AB97: =IF(Z97="","",Z97+0.5*N(AA97)) | AC97: 2 | AD97: 1 | AH97: =IF(AG97="","",1-V97/AG97) | AJ97: NEW EMPLOYEE PRICING EVENT | UP TO $40,000 IN NEW HOME SAVINGS | AK97: 38511 Dancing Pair Way | AL97: 38.1 | AM97: Houston | AN97: 378164 | AO97: -0.0149 | AP97: 338065 | AQ97: 164 | AR97: 3000 | AU97: https://www.davidweekleyhomes.com/new-homes/tx/houston/magnolia/audubon-55 | AV97: https://www.davidweekleyhomes.com/new-homes/tx/houston/magnolia/audubon-55 | AW97: h7f280ceab | AX97: 2026-09-27
A98: 97 | B98: houston | C98: hou-audubon | D98: Audubon | E98: Montgomery | F98: Magnolia | G98: 77354 | H98: Audubon Magnolia Development, LLC (managed by Sam Yager Inc.) | I98: Magnolia ISD | J98: David Weekley Homes | K98: b-houston-david-weekley-homes | L98: National builder | M98: Yes | N98: No | O98: No | Q98: hou-audubon#6 | R98: Ascent Collection | S98: 55 | T98: 55 | U98: The Thistle | V98: 526000 | W98: 2691 | X98: =IF(W98>0,V98/W98,"") | Y98: 4 | Z98: 3 | AA98: 1 | AB98: =IF(Z98="","",Z98+0.5*N(AA98)) | AC98: 3 | AD98: 1 | AH98: =IF(AG98="","",1-V98/AG98) | AJ98: NEW EMPLOYEE PRICING EVENT | UP TO $40,000 IN NEW HOME SAVINGS | AK98: 16725 Heron Oaks Run | AL98: 38.1 | AM98: Houston | AN98: 378164 | AO98: -0.0149 | AP98: 338065 | AQ98: 164 | AR98: 3000 | AU98: https://www.davidweekleyhomes.com/new-homes/tx/houston/magnolia/audubon-55 | AV98: https://www.davidweekleyhomes.com/new-homes/tx/houston/magnolia/audubon-55 | AW98: h80ad44f55 | AX98: 2026-09-27
A99: 98 | B99: houston | C99: hou-audubon | D99: Audubon | E99: Montgomery | F99: Magnolia | G99: 77354 | H99: Audubon Magnolia Development, LLC (managed by Sam Yager Inc.) | I99: Magnolia ISD | J99: David Weekley Homes | K99: b-houston-david-weekley-homes | L99: National builder | M99: Yes | N99: No | O99: No | Q99: hou-audubon#6 | R99: Ascent Collection | S99: 55 | T99: 55 | U99: The Begonia | V99: 545620 | W99: 2788 | X99: =IF(W99>0,V99/W99,"") | Y99: 4 | Z99: 3 | AA99: 1 | AB99: =IF(Z99="","",Z99+0.5*N(AA99)) | AC99: 3 | AD99: 1 | AH99: =IF(AG99="","",1-V99/AG99) | AJ99: NEW EMPLOYEE PRICING EVENT | UP TO $40,000 IN NEW HOME SAVINGS | AK99: 16859 Deep Wingbeat Way | AL99: 38.1 | AM99: Houston | AN99: 378164 | AO99: -0.0149 | AP99: 338065 | AQ99: 164 | AR99: 3000 | AU99: https://www.davidweekleyhomes.com/new-homes/tx/houston/magnolia/audubon-55 | AV99: https://www.davidweekleyhomes.com/new-homes/tx/houston/magnolia/audubon-55 | AW99: hf512360b4 | AX99: 2026-09-27
A100: 99 | B100: houston | C100: hou-audubon | D100: Audubon | E100: Montgomery | F100: Magnolia | G100: 77354 | H100: Audubon Magnolia Development, LLC (managed by Sam Yager Inc.) | I100: Magnolia ISD | J100: Drees Custom Homes | K100: b-houston-drees-custom-homes | L100: National builder | M100: Partly | N100: No | O100: No | Q100: hou-audubon#7 | S100: 80 | T100: 80 | V100: 769990 | W100: 3096 | X100: =IF(W100>0,V100/W100,"") | Y100: 4 | Z100: 3 | AA100: 1 | AB100: =IF(Z100="","",Z100+0.5*N(AA100)) | AE100: ready | AF100: MOVE-IN READY | AH100: =IF(AG100="","",1-V100/AG100) | AK100: 38285 Heron Nest Way | AL100: 38.1 | AM100: Houston | AN100: 378164 | AO100: -0.0149 | AP100: 338065 | AQ100: 164 | AR100: 3000 | AU100: https://audubonliving.com/drees-custom-homes/ | AV100: https://audubonliving.com/drees-custom-homes/ | AW100: h1ac7b5d04 | AX100: 2026-09-27
...

Sheet ProductLines
A1: line_id | B1: market | C1: community_id | D1: community | E1: builder | F1: product_line | G1: lot_widths_ft | H1: lot_width_ft | I1: stories_offered | J1: from_price | K1: from_is_band_floor | L1: from_text | M1: to_price | N1: to_text | O1: sqft_min | P1: sqft_max | Q1: n_plans | R1: qmi_listed | S1: qmi_read | T1: qmi_median_ppsf | U1: incentive_text | V1: source_url | W1: read_on
A2: hou-artavia#1 | B2: houston | C2: hou-artavia | D2: ARTAVIA | E2: Beazer Homes | G2: 65 | H2: 65 | J2: 487990 | L2: Starting $487,990 | M2: 568701 | N2: $568,701 (quick move-in, Northcliffe) | O2: 2754 | P2: 3908 | R2: 3 | S2: 3 | T2: 146 | U2: For a limited time, receive 50% off options up to $100,000 for your new to-be-built home when you use a Choice Lender!* | V2: https://www.beazer.com/houston-TX/conroe/artavia | W2: 2026-09-27
A3: hou-artavia#2 | B3: houston | C3: hou-artavia | D3: ARTAVIA | E3: Chesmar Homes | G3: 55 | H3: 55 | J3: 379990 | L3: Starting From: $379,990 | O3: 2086 | P3: 3107 | S3: 0 | U3: 4.999% (5.737% APR) FHA 30yr, fixed-rate special financing on select homes! | V3: https://www.chesmar.com/texas/houston-new-homes/conroe/artavia/ | W3: 2026-09-27
A4: hou-artavia#3 | B4: houston | C4: hou-artavia | D4: ARTAVIA | E4: David Weekley Homes | F4: Reserve Collection | G4: 45 | H4: 45 | I4: 1, 2 | J4: 354990 | L4: From: $354,990 | M4: 449990 | N4: $449,990 (quick move-in) | O4: 1713 | P4: 2888 | Q4: 7 | R4: 7 | S4: 5 | T4: 195 | V4: https://www.davidweekleyhomes.com/new-homes/tx/houston/conroe/artavia-45-homesites | W4: 2026-09-27
A5: hou-artavia#4 | B5: houston | C5: hou-artavia | D5: ARTAVIA | E5: David Weekley Homes | F5: Enclave Collection | G5: 50 | H5: 50 | I5: 1, 2 | J5: 422990 | L5: From: $422,990 | M5: 524990 | N5: From: $524,990 (highest plan) | O5: 2212 | P5: 3335 | Q5: 9 | R5: 9 | S5: 5 | T5: 195 | V5: https://www.davidweekleyhomes.com/new-homes/tx/houston/conroe/artavia-50-homesites | W5: 2026-09-27
A6: hou-artavia#5 | B6: houston | C6: hou-artavia | D6: ARTAVIA | E6: David Weekley Homes | F6: Parkview Collection | G6: 65 | H6: 65 | I6: 1, 2 | J6: 559990 | L6: From: $559,990 | M6: 674990 | N6: $674,990 (quick move-in) | O6: 2861 | P6: 4086 | Q6: 9 | R6: 10 | S6: 5 | T6: 189 | V6: https://www.davidweekleyhomes.com/new-homes/tx/houston/conroe/artavia | W6: 2026-09-27
A7: hou-artavia#6 | B7: houston | C7: hou-artavia | D7: ARTAVIA | E7: Highland Homes | F7: 50ft. lots | G7: 50 | H7: 50 | I7: 1, 2 | J7: 394990 | L7: from the $390s; lowest plan starting at $394,990 | M7: 499990 | N7: $499,990 (quick move-in, Cambridge Plan) | O7: 2164 | P7: 3440 | Q7: 17 | R7: 4 | S7: 4 | T7: 180 | U7: $30K Your Way! | V7: https://www.highlandhomes.com/houston/conroe/artavia/50ft-lots/section | W7: 2026-09-27
A8: hou-artavia#7 | B8: houston | C8: hou-artavia | D8: ARTAVIA | E8: Highland Homes | F8: 60ft. lots | G8: 60 | H8: 60 | I8: 1, 2 | J8: 503990 | L8: from the $500s; lowest plan starting at $503,990 | M8: 606990 | N8: Starting at $606,990 (highest plan) | O8: 2611 | P8: 3918 | Q8: 15 | R8: 4 | S8: 4 | T8: 189 | U8: $30K Your Way! | V8: https://www.highlandhomes.com/houston/conroe/artavia/60ft-lots/section | W8: 2026-09-27
A9: hou-artavia#8 | B9: houston | C9: hou-artavia | D9: ARTAVIA | E9: J. Patrick Homes | F9: ARTAVIA 55' lots | G9: 55 | H9: 55 | I9: 1, 2 | J9: 490000 | K9: yes | L9: from the $490s | O9: 2178 | P9: 3400 | Q9: 7 | S9: 0 | V9: https://www.jpatrickhomes.com/communities/artavia-55-lots/ | W9: 2026-09-27
A10: hou-artavia#9 | B10: houston | C10: hou-artavia | D10: ARTAVIA | E10: J. Patrick Homes | F10: ARTAVIA 70' lots | G10: 70 | H10: 70 | I10: 1, 2 | J10: 590000 | K10: yes | L10: from the $590s | O10: 2802 | P10: 4683 | Q10: 17 | S10: 0 | V10: https://www.jpatrickhomes.com/communities/artavia-70-lots/ | W10: 2026-09-27
A11: hou-artavia#10 | B11: houston | C11: hou-artavia | D11: ARTAVIA | E11: Jamestown Estate Homes | G11: 80 | H11: 80 | J11: 850000 | L11: Priced at $850,000 (available home); community site: 80' Lots from the $800's | M11: 1059990 | N11: Priced at $1,059,990 | Q11: 9 | R11: 3 | S11: 3 | T11: 245 | V11: https://jamestownestatehomes.com/artavia-homebuilders/ | W11: 2026-09-27
A12: hou-artavia#11 | B12: houston | C12: hou-artavia | D12: ARTAVIA | E12: Lennar | F12: Fairway Collection | G12: 55 | H12: 55 | J12: 330991 | L12: $330,991 - $418,990 | M12: 418990 | N12: $330,991 - $418,990 | O12: 2386 | P12: 2795 | Q12: 6 | R12: 10 | S12: 4 | T12: 142 | V12: https://www.lennar.com/new-homes/texas/houston/conroe/artavia | W12: 2026-09-27
A13: hou-artavia#12 | B13: houston | C13: hou-artavia | D13: ARTAVIA | E13: Perry Homes | F13: Artavia 45' | G13: 45 | H13: 45 | I13: 1, 2 | J13: 390000 | K13: yes | L13: From the $390s | O13: 1900 | P13: 2800 | S13: 0 | U13: Up to $55,000 for a limited time. Flex Cash* AND 4.99% rate (5.178% APR) | V13: https://www.perryhomes.com/new-homes/texas/houston/artavia | W13: 2026-09-27
A14: hou-artavia#13 | B14: houston | C14: hou-artavia | D14: ARTAVIA | E14: Perry Homes | F14: Artavia 50' | G14: 50 | H14: 50 | I14: 1, 2 | J14: 440000 | K14: yes | L14: From the $440s | O14: 2100 | P14: 3100 | S14: 0 | U14: Up to $55,000 for a limited time. Flex Cash* AND 4.99% rate (5.178% APR) | V14: https://www.perryhomes.com/new-homes/texas/houston/artavia | W14: 2026-09-27
A15: hou-artavia#14 | B15: houston | C15: hou-artavia | D15: ARTAVIA | E15: Perry Homes | F15: Artavia 55' - Valencia | G15: 55 | H15: 55 | I15: 1, 2 | J15: 540000 | K15: yes | L15: From the $540s | O15: 2600 | P15: 3500 | S15: 0 | U15: Up to $55,000 for a limited time. Flex Cash* AND 4.99% rate (5.178% APR) | V15: https://www.perryhomes.com/new-homes/texas/houston/artavia | W15: 2026-09-27
A16: hou-artavia#15 | B16: houston | C16: hou-artavia | D16: ARTAVIA | E16: Ravenna Homes | F16: ARTAVIA 70' | G16: 70 | H16: 70 | J16: 600000 | K16: yes | L16: From the $600's | M16: 878900 | N16: Now: $878,900 | O16: 3200 | P16: 4200 | R16: 4 | S16: 4 | T16: 206 | V16: https://www.ravennahomes.com/communities/artavia-70/ | W16: 2026-09-27
A17: hou-artavia#16 | B17: houston | C17: hou-artavia | D17: ARTAVIA | E17: Westin Homes | F17: ARTAVIA 40' | G17: 40 | H17: 40 | J17: 464990 | L17: Starting from $464,990 (lowest plan) | M17: 490990 | N17: Starting from $490,990 (highest plan) | O17: 2580 | P17: 2800 | Q17: 7 | R17: 5 | S17: 5 | T17: 173 | V17: https://www.westin-homes.com/communities/houston/artavia/artavia-40 | W17: 2026-09-27
A18: hou-artavia#17 | B18: houston | C18: hou-artavia | D18: ARTAVIA | E18: Westin Homes | F18: ARTAVIA 60' | G18: 60 | H18: 60 | J18: 558990 | L18: Starting from $558,990 (lowest plan) | M18: 612990 | N18: Starting from $612,990 (highest plan) | O18: 2818 | P18: 3788 | Q18: 6 | R18: 6 | S18: 5 | T18: 163 | V18: https://www.westin-homes.com/communities/houston/artavia/artavia-60 | W18: 2026-09-27
A19: hou-artavia#18 | B19: houston | C19: hou-artavia | D19: ARTAVIA | E19: Westin Homes | F19: ARTAVIA 65' Art Collection | G19: 65 | H19: 65 | J19: 745990 | L19: Starting from $745,990 (lowest plan) | M19: 818990 | N19: Starting from $818,990 (highest plan) | O19: 3568 | P19: 4500 | Q19: 8 | R19: 2 | S19: 2 | T19: 184 | V19: https://www.westin-homes.com/communities/houston/artavia/artavia-65-art-collection | W19: 2026-09-27
A20: hou-amira#1 | B20: houston | C20: hou-amira | D20: Amira | E20: Beazer Homes | F20: Amira 45' and 50' Homesites | G20: 45, 50 | J20: 349067 | L20: Starting $349,067 | M20: 548462 | N20: $548,462 (Sedona, quick move-in, 50' homesites) | O20: 1767 | P20: 3196 | R20: 14 | S20: 5 | T20: 182 | U20: For a limited time, receive up to $75,000 in options on your new to-be-built home when you use a Choice Lender!* | V20: https://www.beazer.com/houston-TX/tomball/amira | W20: 2026-09-27
A21: hou-amira#2 | B21: houston | C21: hou-amira | D21: Amira | E21: Perry Homes | F21: Amira 45' | G21: 45 | H21: 45 | J21: 370000 | K21: yes | L21: From the $370s | O21: 2000 | P21: 2100 | S21: 0 | U21: Up to $55,000 in incentives. Flex cash and low rate available for a limited time. | V21: https://www.perryhomes.com/new-homes/texas/houston/amira/amira-45 | W21: 2026-09-27
A22: hou-anniston#1 | B22: houston | C22: hou-anniston | D22: Anniston | E22: Lennar | F22: Cottage Collection | J22: 219991 | L22: From $219,991 | M22: 288990 | N22: $288,990 | O22: 1311 | P22: 2039 | Q22: 5 | R22: 8 | S22: 5 | T22: 159 | V22: https://www.lennar.com/new-homes/texas/houston/katy/anniston/cottage-collection | W22: 2026-09-27
A23: hou-anniston#2 | B23: houston | C23: hou-anniston | D23: Anniston | E23: Lennar | F23: Watermill Collection | J23: 235990 | L23: From $235,990 | M23: 291990 | N23: $291,990 | O23: 1084 | P23: 1968 | Q23: 6 | R23: 8 | S23: 5 | T23: 156 | V23: https://www.lennar.com/new-homes/texas/houston/katy/anniston/watermill-collection | W23: 2026-09-27
A24: hou-anniston#3 | B24: houston | C24: hou-anniston | D24: Anniston | E24: Lennar | F24: Classic Collection | J24: 277990 | L24: From $277,990 | M24: 422990 | N24: $422,990 | O24: 1602 | P24: 3223 | Q24: 6 | R24: 10 | S24: 5 | T24: 146 | V24: https://www.lennar.com/new-homes/texas/houston/katy/anniston/classic-collection | W24: 2026-09-27
A25: hou-anniston#4 | B25: houston | C25: hou-anniston | D25: Anniston | E25: Lennar | F25: Eventide Collection | J25: 276990 | L25: From $276,990 | M25: 356990 | N25: $356,990 | O25: 1572 | P25: 2637 | Q25: 7 | R25: 7 | S25: 5 | T25: 155 | V25: https://www.lennar.com/new-homes/texas/houston/katy/anniston/eventide-collection | W25: 2026-09-27
A26: hou-anniston#5 | B26: houston | C26: hou-anniston | D26: Anniston | E26: Lennar | F26: Richmond Collection | J26: 299990 | L26: From $299,990 | M26: 410990 | N26: $410,990 | O26: 2013 | P26: 3198 | Q26: 7 | R26: 8 | S26: 5 | T26: 133 | V26: https://www.lennar.com/new-homes/texas/houston/katy/anniston/richmond-collection | W26: 2026-09-27
A27: hou-anniston#6 | B27: houston | C27: hou-anniston | D27: Anniston | E27: Lennar | F27: Pinnacle Collection | J27: 335990 | L27: From $335,990 | M27: 443990 | N27: $443,990 | O27: 2423 | P27: 3671 | Q27: 7 | R27: 4 | S27: 4 | T27: 136 | V27: https://www.lennar.com/new-homes/texas/houston/katy/anniston/pinnacle-collection | W27: 2026-09-27
A28: hou-anniston#7 | B28: houston | C28: hou-anniston | D28: Anniston | E28: Lennar | F28: Fairway Collection | J28: 335990 | L28: From $335,990 | M28: 457990 | N28: $457,990 | O28: 2386 | P28: 3308 | Q28: 7 | R28: 5 | S28: 5 | T28: 138 | V28: https://www.lennar.com/new-homes/texas/houston/katy/anniston/fairway-collection | W28: 2026-09-27
A29: hou-anniston#8 | B29: houston | C29: hou-anniston | D29: Anniston | E29: Lennar | F29: Fairway II Collection | J29: 386990 | L29: Coming Soon; plans from $386,990 | M29: 495990 | N29: $495,990 | O29: 2386 | P29: 3308 | Q29: 7 | R29: 0 | S29: 0 | V29: https://www.lennar.com/new-homes/texas/houston/katy/anniston/fairway-ii-collection | W29: 2026-09-27
A30: hou-audubon#1 | B30: houston | C30: hou-audubon | D30: Audubon | E30: Aderra 62+ (age-restricted neighborhood) | F30: Aderra, Heron Run district | G30: 45 | H30: 45 | I30: 1 | J30: 300000 | K30: yes | L30: Homes are priced from the low $300,000s | M30: 387341 | N30: $387,341 (highest listed floor plan) | O30: 1362 | P30: 1740 | Q30: 4 | S30: 0 | V30: https://audubonliving.com/aderra/ | W30: 2026-09-27
A31: hou-audubon#2 | B31: houston | C31: hou-audubon | D31: Audubon | E31: Century Communities | F31: Lonestar Collection | J31: 200000 | K31: yes | L31: From the High $200s | M31: 366900 | N31: $366,900 (Beckenham, 15467 Park Perch Place) | R31: 7 | S31: 4 | T31: 168 | U31: Explore Our Special Financing Offers – Available for a Limited Time! | V31: https://www.centurycommunities.com/find-your-new-home/texas/houston-metro/magnolia/audubon/ | W31: 2026-09-27
A32: hou-audubon#3 | B32: houston | C32: hou-audubon | D32: Audubon | E32: Century Communities | F32: Liberty Collection | J32: 200000 | K32: yes | L32: From the High $200s | M32: 389900 | N32: $389,900 (Sandown, 40523 Slough Way, Oct. move-in) | R32: 9 | S32: 1 | T32: 162 | U32: Explore Our Special Financing Offers – Available for a Limited Time! | V32: https://www.centurycommunities.com/find-your-new-home/texas/houston-metro/magnolia/audubon/ | W32: 2026-09-27
A33: hou-audubon#4 | B33: houston | C33: hou-audubon | D33: Audubon | E33: Chesmar Homes | G33: 55 | H33: 55 | J33: 469990 | L33: Starting From: $469,990 | M33: 547990 | N33: Melody, Starting From $547,990 | O33: 2052 | P33: 3169 | Q33: 11 | S33: 0 | U33: 4.999% (5.737% APR) FHA 30yr, fixed-rate special financing on select homes! | V33: https://www.chesmar.com/texas/houston-new-homes/magnolia/audubon/ | W33: 2026-09-27
A34: hou-audubon#5 | B34: houston | C34: hou-audubon | D34: Audubon | E34: David Weekley Homes | F34: Terrace Collection | G34: 45 | H34: 45 | I34: 1, 2 | J34: 349990 | L34: From: $349,990 (The Flora) | M34: 422990 | N34: From: $422,990 (The Holly) | O34: 1815 | P34: 2814 | Q34: 8 | S34: 0 | U34: NEW EMPLOYEE PRICING EVENT | UP TO $40,000 IN NEW HOME SAVINGS | V34: https://www.davidweekleyhomes.com/new-homes/tx/houston/magnolia/audubon-45-homesites | W34: 2026-09-27
A35: hou-audubon#6 | B35: houston | C35: hou-audubon | D35: Audubon | E35: David Weekley Homes | F35: Ascent Collection | G35: 55 | H35: 55 | I35: 1, 2 | J35: 434990 | L35: From: $434,990 (The Wildflower) | M35: 591846 | N35: $591,846 (The Begonia, 16819 Deep Wingbeat Way) | O35: 2091 | P35: 3495 | Q35: 9 | R35: 10 | S35: 5 | T35: 196 | U35: NEW EMPLOYEE PRICING EVENT | UP TO $40,000 IN NEW HOME SAVINGS | V35: https://www.davidweekleyhomes.com/new-homes/tx/houston/magnolia/audubon-55 | W35: 2026-09-27
A36: hou-audubon#7 | B36: houston | C36: hou-audubon | D36: Audubon | E36: Drees Custom Homes | G36: 80 | H36: 80 | J36: 730000 | K36: yes | L36: From the $730s | M36: 899990 | N36: $899,990 (38265 Heron Nest Way) | O36: 3096 | P36: 5035 | Q36: 10 | R36: 4 | S36: 4 | T36: 229 | V36: https://audubonliving.com/drees-custom-homes/ | W36: 2026-09-27
A37: hou-audubon#8 | B37: houston | C37: hou-audubon | D37: Audubon | E37: Empire Homes | G37: 60 | H37: 60 | J37: 550000 | K37: yes | L37: From the $550s | O37: 2447 | P37: 3828 | S37: 0 | V37: https://audubonliving.com/empire-homes/ | W37: 2026-09-27
A38: hou-audubon#9 | B38: houston | C38: hou-audubon | D38: Audubon | E38: Perry Homes | F38: 45' model | G38: 45 | H38: 45 | J38: 370000 | K38: yes | L38: From the high $300s | O38: 1600 | P38: 2800 | S38: 3 | T38: 206 | V38: https://audubonliving.com/perry-homes/ | W38: 2026-09-27
A39: hou-audubon#10 | B39: houston | C39: hou-audubon | D39: Audubon | E39: Perry Homes | F39: 60' model | G39: 60 | H39: 60 | J39: 470000 | K39: yes | L39: From the high $400s | O39: 2400 | P39: 4100 | S39: 4 | T39: 214 | V39: https://audubonliving.com/perry-homes/ | W39: 2026-09-27
A40: hou-audubon#11 | B40: houston | C40: hou-audubon | D40: Audubon | E40: Perry Homes | F40: 70' model | G40: 70 | H40: 70 | J40: 600000 | K40: yes | L40: From the low $600s | O40: 3200 | P40: 4400 | S40: 0 | V40: https://audubonliving.com/perry-homes/ | W40: 2026-09-27
A41: hou-audubon#12 | B41: houston | C41: hou-audubon | D41: Audubon | E41: Ravenna Homes | F41: Audubon 60' | G41: 60 | H41: 60 | J41: 500000 | K41: yes | L41: From the $500's | M41: 749900 | N41: Now: $749,900 (Plan 3546AU, 38688 Night Brood Court) | R41: 7 | S41: 5 | T41: 202 | V41: https://www.ravennahomes.com/communities/audubon-60/ | W41: 2026-09-27
A42: hou-audubon#13 | B42: houston | C42: hou-audubon | D42: Audubon | E42: Sitterle Homes | F42: 60' Garden | G42: 60 | H42: 60 | J42: 400000 | K42: yes | L42: From the $400s | O42: 2164 | P42: 2880 | S42: 4 | T42: 242 | V42: https://audubonliving.com/sitterle-homes/ | W42: 2026-09-27
A43: hou-audubon#14 | B43: houston | C43: hou-audubon | D43: Audubon | E43: Sitterle Homes | F43: 80' | G43: 80 | H43: 80 | J43: 600000 | K43: yes | L43: From the $600s | O43: 3024 | P43: 3994 | S43: 2 | T43: 254 | V43: https://audubonliving.com/sitterle-homes/ | W43: 2026-09-27
A44: hou-audubon#15 | B44: houston | C44: hou-audubon | D44: Audubon | E44: Smith Douglas Homes | G44: 40, 50 | J44: 240000 | K44: yes | L44: $240s - $300s | M44: 404140 | N44: $404,140 (16490 Branchers Drive) | O44: 1500 | P44: 3000 | Q44: 14 | R44: 5 | S44: 5 | T44: 170 | V44: https://audubonliving.com/smith-douglas-homes/ | W44: 2026-09-27
A45: hou-audubon#16 | B45: houston | C45: hou-audubon | D45: Audubon | E45: Toll Brothers | F45: Pre-Selling By Appointment Only | G45: 80 | H45: 80 | I45: 1, 2 | J45: 749995 | L45: Anticipated from $749,995 | M45: 974995 | N45: Starting at $974,995 (highest home design) | O45: 4033 | P45: 5989 | Q45: 6 | S45: 0 | V45: https://www.tollbrothers.com/luxury-homes-for-sale/Texas/Toll-Brothers-at-Audubon | W45: 2026-09-27
A46: hou-audubon#17 | B46: houston | C46: hou-audubon | D46: Audubon | E46: Westin Homes | F46: Audubon - 70' | G46: 70 | H46: 70 | J46: 599886 | L46: Starting from $599,886 | M46: 743990 | N46: The Gray III, Starting from $743,990 | O46: 3345 | P46: 4500 | Q46: 6 | R46: 7 | S46: 5 | T46: 150 | V46: https://www.westin-homes.com/communities/houston/audubon/audubon-70 | W46: 2026-09-27
A47: hou-austin-point#1 | B47: houston | C47: hou-austin-point | D47: Austin Point | E47: Ashton Woods | F47: 50' | G47: 50 | H47: 50 | I47: 1, 2 | J47: 349990 | L47: Plans from $349,990 | M47: 434990 | N47: $434,990 | O47: 2147 | P47: 2966 | Q47: 6 | R47: 8 | S47: 5 | T47: 158 | U47: Use As You Choose Savings | V47: https://www.ashtonwoods.com/houston/austin-point | W47: 2026-09-27
A48: hou-austin-point#2 | B48: houston | C48: hou-austin-point | D48: Austin Point | E48: Beazer Homes | F48: 50' | G48: 50 | H48: 50 | J48: 390990 | L48: Starting $390,990 | O48: 2053 | P48: 2947 | S48: 2 | T48: 170 | U48: For a limited time, receive 50% off options up to $50,000 plus $10,000 in closing costs on your new to-be-built home when you use a Choice Lender! | V48: https://www.beazer.com/houston-TX/richmond/austin-point | W48: 2026-09-27
A49: hou-austin-point#3 | B49: houston | C49: hou-austin-point | D49: Austin Point | E49: CastleRock Communities | F49: 40' | G49: 40 | H49: 40 | J49: 200000 | K49: yes | L49: From the Mid $200s | O49: 1500 | P49: 2600 | S49: 0 | V49: https://www.austinpoint.com/model-homes/ | W49: 2026-09-27
A50: hou-austin-point#4 | B50: houston | C50: hou-austin-point | D50: Austin Point | E50: David Weekley Homes | F50: Terrace Collection (45') | G50: 45 | H50: 45 | I50: 1, 2 | J50: 336990 | L50: From: $336,990 | M50: 410990 | N50: From: $410,990 | O50: 1589 | P50: 2812 | Q50: 9 | R50: 10 | S50: 5 | T50: 188 | V50: https://www.davidweekleyhomes.com/new-homes/tx/houston/richmond/austin-point | W50: 2026-09-27
A51: hou-austin-point#5 | B51: houston | C51: hou-austin-point | D51: Austin Point | E51: Drees Custom Homes | F51: 35' (Austin Point Summit) | G51: 35 | H51: 35 | J51: 400000 | K51: yes | L51: From the Mid $400s | O51: 2357 | P51: 2512 | S51: 0 | V51: https://www.austinpoint.com/model-homes/ | W51: 2026-09-27
A52: hou-austin-point#6 | B52: houston | C52: hou-austin-point | D52: Austin Point | E52: Drees Custom Homes | F52: 70' (Austin Point Showcase) | G52: 70 | H52: 70 | J52: 600000 | K52: yes | L52: From the Low $600s | O52: 3100 | P52: 4500 | S52: 0 | V52: https://www.austinpoint.com/model-homes/ | W52: 2026-09-27
A53: hou-austin-point#7 | B53: houston | C53: hou-austin-point | D53: Austin Point | E53: Newmark Homes | F53: 45' | G53: 45 | H53: 45 | J53: 300000 | K53: yes | L53: From the High $300s | O53: 1700 | P53: 2800 | S53: 0 | V53: https://www.austinpoint.com/model-homes/ | W53: 2026-09-27
A54: hou-austin-point#8 | B54: houston | C54: hou-austin-point | D54: Austin Point | E54: Perry Homes | F54: Austin Point 40' | G54: 40 | H54: 40 | I54: 1, 2 | J54: 340000 | K54: yes | L54: From the $340s | O54: 1500 | P54: 2600 | Q54: 16 | R54: 6 | S54: 5 | T54: 196 | U54: Up to $55,000 for a limited time. Flex Cash* AND 4.99% rate (5.178% APR) | V54: https://www.perryhomes.com/new-homes/texas/houston/austin-point | W54: 2026-09-27
A55: hou-austin-point#9 | B55: houston | C55: hou-austin-point | D55: Austin Point | E55: Perry Homes | F55: Austin Point 60' | G55: 60 | H55: 60 | I55: 1, 2 | J55: 560000 | K55: yes | L55: From the $560s | O55: 2800 | P55: 4100 | Q55: 19 | R55: 6 | S55: 5 | T55: 189 | U55: Up to $55,000 for a limited time. Flex Cash* AND 4.99% rate (5.178% APR) | V55: https://www.perryhomes.com/new-homes/texas/houston/austin-point | W55: 2026-09-27
A56: hou-austin-point#10 | B56: houston | C56: hou-austin-point | D56: Austin Point | E56: Westin Homes | F56: Austin Point - 40' | G56: 40 | H56: 40 | J56: 379799 | L56: Starting from $379,799 | M56: 449890 | N56: Starting from $449,890 | O56: 2425 | P56: 2650 | Q56: 7 | R56: 8 | S56: 5 | T56: 154 | V56: https://www.westin-homes.com/communities/houston/austin-point/austin-point-40 | W56: 2026-09-27
A57: hou-austin-point#11 | B57: houston | C57: hou-austin-point | D57: Austin Point | E57: Westin Homes | F57: Austin Point - 60' | G57: 60 | H57: 60 | J57: 544874 | L57: Starting from $544,874 | M57: 652990 | N57: Starting from $652,990 | O57: 3429 | P57: 4263 | Q57: 7 | R57: 6 | S57: 5 | T57: 155 | V57: https://www.westin-homes.com/communities/houston/austin-point/austin-point-60 | W57: 2026-09-27
A58: hou-austin-point#12 | B58: houston | C58: hou-austin-point | D58: Austin Point | E58: William David Homes | F58: 70' | G58: 70 | H58: 70 | J58: 750000 | K58: yes | L58: From the $750s | O58: 3100 | P58: 4500 | S58: 0 | V58: https://www.austinpoint.com/model-homes/ | W58: 2026-09-27
A59: hou-baytown-crossings#1 | B59: houston | C59: hou-baytown-crossings | D59: Baytown Crossings | E59: Beazer Homes | F59: Ashbel Cove 50' | G59: 50 | H59: 50 | J59: 380000 | K59: yes | L59: From the $380s (50') *Model Home Now Closed - Final Opportunities* | S59: 0 | V59: https://friendswooddevelopment.com/communities/master-planned/baytown-crossings | W59: 2026-09-27
A60: hou-baytown-crossings#2 | B60: houston | C60: hou-baytown-crossings | D60: Baytown Crossings | E60: Beazer Homes | F60: Ashbel Cove 60' | G60: 60 | H60: 60 | J60: 380000 | K60: yes | L60: From the $380s (60') *Model Home Now Closed - Final Opportunities* | S60: 0 | V60: https://friendswooddevelopment.com/communities/master-planned/baytown-crossings | W60: 2026-09-27
A61: hou-baytown-crossings#3 | B61: houston | C61: hou-baytown-crossings | D61: Baytown Crossings | E61: Lennar | F61: Sterling Point 45' | G61: 45 | H61: 45 | J61: 220000 | K61: yes | L61: From the $220s (45') | S61: 0 | V61: https://friendswooddevelopment.com/communities/master-planned/baytown-crossings | W61: 2026-09-27
A62: hou-baytown-crossings#4 | B62: houston | C62: hou-baytown-crossings | D62: Baytown Crossings | E62: Lennar | F62: Sterling Point 50' | G62: 50 | H62: 50 | J62: 250000 | K62: yes | L62: From the $250s (50') | S62: 0 | V62: https://friendswooddevelopment.com/communities/master-planned/baytown-crossings | W62: 2026-09-27
A63: hou-baytown-crossings#5 | B63: houston | C63: hou-baytown-crossings | D63: Baytown Crossings | E63: Lennar | F63: Sterling Point 60' | G63: 60 | H63: 60 | J63: 320000 | K63: yes | L63: From the $320s (60') | S63: 0 | V63: https://friendswooddevelopment.com/communities/master-planned/baytown-crossings | W63: 2026-09-27
A64: hou-baytown-crossings#6 | B64: houston | C64: hou-baytown-crossings | D64: Baytown Crossings | E64: Lennar | F64: Burnet Fields 50' | G64: 50 | H64: 50 | J64: 210000 | K64: yes | L64: From the $210s (50') | S64: 0 | V64: https://friendswooddevelopment.com/communities/master-planned/baytown-crossings | W64: 2026-09-27
A65: hou-baytown-crossings#7 | B65: houston | C65: hou-baytown-crossings | D65: Baytown Crossings | E65: Lennar | F65: Scott's Bend, Watermill Collection | J65: 193991 | L65: From $193,991 | M65: 278990 | N65: $278,990 | O65: 1084 | P65: 1968 | Q65: 6 | R65: 8 | S65: 5 | T65: 155 | V65: https://www.lennar.com/new-homes/texas/houston/baytown/scotts-bend/watermill-collection | W65: 2026-09-27
A66: hou-baytown-crossings#8 | B66: houston | C66: hou-baytown-crossings | D66: Baytown Crossings | E66: Lennar | F66: Scott's Bend, Fairway Collection | J66: 353990 | L66: From $353,990 | M66: 466990 | N66: $466,990 | O66: 2386 | P66: 3308 | Q66: 7 | R66: 3 | S66: 3 | T66: 139 | V66: https://www.lennar.com/new-homes/texas/houston/baytown/scotts-bend/fairway-collection | W66: 2026-09-27
A67: hou-baytown-crossings#9 | B67: houston | C67: hou-baytown-crossings | D67: Baytown Crossings | E67: Lennar | F67: Scott's Bend, Coastline Collection | J67: 271990 | L67: From $271,990 | M67: 365990 | N67: $365,990 | O67: 1600 | P67: 2943 | Q67: 14 | R67: 1 | S67: 1 | T67: 145 | V67: https://www.lennar.com/new-homes/texas/houston/baytown/scotts-bend/coastline-collection | W67: 2026-09-27
A68: hou-baytown-crossings#10 | B68: houston | C68: hou-baytown-crossings | D68: Baytown Crossings | E68: Lennar | F68: Scott's Bend, Classic Collection | J68: 270990 | L68: From $270,990 | M68: 377990 | N68: $377,990 | O68: 1602 | P68: 3223 | Q68: 6 | R68: 6 | S68: 5 | T68: 146 | V68: https://www.lennar.com/new-homes/texas/houston/baytown/scotts-bend/classic-collection | W68: 2026-09-27
A69: hou-baytown-crossings#11 | B69: houston | C69: hou-baytown-crossings | D69: Baytown Crossings | E69: Lennar | F69: Scott's Bend, Pinnacle Collection | J69: 380990 | L69: From $380,990 | M69: 477990 | N69: $477,990 | O69: 2423 | P69: 3671 | Q69: 7 | R69: 2 | S69: 2 | T69: 145 | V69: https://www.lennar.com/new-homes/texas/houston/baytown/scotts-bend/pinnacle-collection | W69: 2026-09-27
A70: hou-bluestem#1 | B70: houston | C70: hou-bluestem | D70: Bluestem | E70: CastleRock Communities | F70: Bluestem | I70: 1, 2 | O70: 1362 | P70: 2513 | Q70: 8 | R70: 8 | S70: 0 | U70: $0 Down Payment | V70: https://www.c-rock.com/community/texas/houston/bluestem | W70: 2026-09-27
A71: hou-bluestem#2 | B71: houston | C71: hou-bluestem | D71: Bluestem | E71: First America Homes | F71: Bluestem Heritage Collection | I71: 1, 2 | J71: 259857 | L71: HOMES FROM $259,857 | M71: 321000 | N71: MANSFIELD FROM $321K | O71: 1556 | P71: 2416 | Q71: 6 | R71: 4 | S71: 4 | T71: 166 | U71: More Than Ever New Included Features | V71: https://www.firstamericahomes.com/new-homes/tx/houston-metro/brookshire/bluestem-heritage-collection/ | W71: 2026-09-27
A72: hou-bluestem#3 | B72: houston | C72: hou-bluestem | D72: Bluestem | E72: First America Homes | F72: Bluestem Signature Collection (coming soon) | S72: 0 | V72: https://www.firstamericahomes.com/new-homes/tx/houston-metro/brookshire/bluestem/ | W72: 2026-09-27
A73: hou-bluestem#4 | B73: houston | C73: hou-bluestem | D73: Bluestem | E73: Legend Homes | F73: Bluestem | I73: 1, 2 | R73: 15 | S73: 5 | T73: 150 | U73: Open Door Deal: From now through Oct. 31, enjoy our best sales event of the year with rates as low as 5.49% PLUS up to $10,000 in closing costs paid on select homes! | V73: https://www.livelegendhomes.com/communities/houston/katy-brookshire/waller/brookshire/bluestem | W73: 2026-09-27
A74: hou-briarley#1 | B74: houston | C74: hou-briarley | D74: Briarley | E74: Chesmar Homes | J74: 489990 | L74: Starting From: $489,990 | O74: 2637 | P74: 3636 | R74: 0 | S74: 0 | U74: 4.999% (5.737% APR) FHA 30yr, fixed-rate special financing on select homes! | V74: https://www.chesmar.com/texas/houston-new-homes/montgomery/briarley/ | W74: 2026-09-27
A75: hou-briarley#2 | B75: houston | C75: hou-briarley | D75: Briarley | E75: David Weekley Homes | F75: Regency Collection | G75: 80 | H75: 80 | I75: 1, 2 | J75: 597990 | L75: From: $597,990 | M75: 797990 | N75: From: $797,990 (Plan T360, The Miranda) | O75: 3145 | P75: 5585 | Q75: 12 | R75: 3 | S75: 3 | T75: 177 | U75: NEW EMPLOYEE PRICING EVENT | UP TO $40,000 IN NEW HOME SAVINGS | V75: https://www.davidweekleyhomes.com/new-homes/tx/houston/montgomery/briarley | W75: 2026-09-27
A76: hou-briarley#3 | B76: houston | C76: hou-briarley | D76: Briarley | E76: Highland Homes | I76: 1, 2 | J76: 575990 | L76: Starting at $575,990 | M76: 794990 | N76: Starting at $794,990 | O76: 2932 | P76: 4767 | Q76: 14 | R76: 2 | S76: 2 | T76: 183 | U76: $25K Your Way! | V76: https://www.highlandhomes.com/houston/montgomery/briarley | W76: 2026-09-27
A77: hou-briarley#4 | B77: houston | C77: hou-briarley | D77: Briarley | E77: J. Patrick Homes | I77: 1, 2 | J77: 670000 | K77: yes | L77: from the $670s | O77: 3488 | P77: 5580 | Q77: 15 | S77: 0 | V77: https://www.jpatrickhomes.com/communities/briarley/ | W77: 2026-09-27
A78: hou-briarley#5 | B78: houston | C78: hou-briarley | D78: Briarley | E78: Perry Homes | F78: Briarley 60' | G78: 60 | H78: 60 | I78: 1, 2 | J78: 520000 | K78: yes | L78: From the $520s | O78: 2600 | P78: 4000 | S78: 2 | T78: 182 | U78: Up to $55,000 in incentives. Flex cash and low rate available for a limited time. | V78: https://www.perryhomes.com/new-homes/texas/houston/briarley/briarley-60 | W78: 2026-09-27
A79: hou-briarley#6 | B79: houston | C79: hou-briarley | D79: Briarley | E79: Perry Homes | F79: Briarley 70' | G79: 70 | H79: 70 | J79: 600000 | K79: yes | L79: From the $600s | O79: 3000 | P79: 5000 | S79: 3 | T79: 212 | U79: Up to $55,000 in incentives. Flex cash and low rate available for a limited time. | V79: https://www.perryhomes.com/new-homes/texas/houston/briarley/briarley-70 | W79: 2026-09-27
A80: hou-bridgeland#1 | B80: houston | C80: hou-bridgeland | D80: Bridgeland | E80: Perry Homes | F80: Bridgeland Central 40' | G80: 40 | H80: 40 | I80: 1, 2 | J80: 420000 | K80: yes | L80: From the $420s | O80: 1500 | P80: 2400 | S80: 0 | U80: Up to $55,000 for a limited time. Flex Cash* AND 4.99% rate (5.178% APR) | V80: https://www.perryhomes.com/new-homes/texas/houston/bridgeland | W80: 2026-09-27
A81: hou-bridgeland#2 | B81: houston | C81: hou-bridgeland | D81: Bridgeland | E81: Perry Homes | F81: Bridgeland 45' | G81: 45 | H81: 45 | I81: 1, 2 | J81: 390000 | K81: yes | L81: From the $390s | O81: 1900 | P81: 2800 | S81: 0 | U81: Up to $55,000 for a limited time. Flex Cash* AND 4.99% rate (5.178% APR) | V81: https://www.perryhomes.com/new-homes/texas/houston/bridgeland | W81: 2026-09-27
A82: hou-bridgeland#3 | B82: houston | C82: hou-bridgeland | D82: Bridgeland | E82: Perry Homes | F82: Bridgeland Central 50' | G82: 50 | H82: 50 | I82: 1, 2 | J82: 530000 | K82: yes | L82: From the $530s | O82: 2300 | P82: 3200 | S82: 0 | U82: Up to $55,000 for a limited time. Flex Cash* AND 4.99% rate (5.178% APR) | V82: https://www.perryhomes.com/new-homes/texas/houston/bridgeland | W82: 2026-09-27
A83: hou-bridgeland#4 | B83: houston | C83: hou-bridgeland | D83: Bridgeland | E83: Perry Homes | F83: Bridgeland 50' | G83: 50 | H83: 50 | I83: 1, 2 | J83: 510000 | K83: yes | L83: From the $510s | O83: 2200 | P83: 3200 | S83: 0 | U83: Up to $55,000 for a limited time. Flex Cash* AND 4.99% rate (5.178% APR) | V83: https://www.perryhomes.com/new-homes/texas/houston/bridgeland | W83: 2026-09-27
A84: hou-bridgeland#5 | B84: houston | C84: hou-bridgeland | D84: Bridgeland | E84: Perry Homes | F84: Bridgeland 55' | G84: 55 | H84: 55 | I84: 1, 2 | J84: 580000 | K84: yes | L84: From the $580s | O84: 2400 | P84: 3700 | S84: 0 | U84: Up to $55,000 for a limited time. Flex Cash* AND 4.99% rate (5.178% APR) | V84: https://www.perryhomes.com/new-homes/texas/houston/bridgeland | W84: 2026-09-27
A85: hou-bridgeland#6 | B85: houston | C85: hou-bridgeland | D85: Bridgeland | E85: Perry Homes | F85: Bridgeland 80' | G85: 80 | H85: 80 | I85: 1, 2 | J85: 870000 | K85: yes | L85: From the $870s | O85: 3400 | P85: 5600 | S85: 0 | U85: Up to $55,000 for a limited time. Flex Cash* AND 4.99% rate (5.178% APR) | V85: https://www.perryhomes.com/new-homes/texas/houston/bridgeland | W85: 2026-09-27
A86: hou-bridgeland#7 | B86: houston | C86: hou-bridgeland | D86: Bridgeland | E86: David Weekley Homes | F86: Bridgeland Central: Emerald Heights - Landmark Row Collection | I86: 1, 2 | J86: 429000 | K86: yes | L86: From the $429s | O86: 1536 | P86: 3047 | Q86: 6 | R86: 9 | S86: 5 | T86: 205 | U86: NEW EMPLOYEE PRICING EVENT | UP TO $40,000 IN NEW HOME SAVINGS | V86: https://www.davidweekleyhomes.com/new-homes/tx/houston/cypress/lakeland-heights-42 | W86: 2026-09-27
A87: hou-bridgeland#8 | B87: houston | C87: hou-bridgeland | D87: Bridgeland | E87: David Weekley Homes | F87: Easthaven at Bridgeland Central - Vision Collection | G87: 55 | H87: 55 | I87: 2 | J87: 484000 | K87: yes | L87: Priced From $484s | M87: 519990 | N87: From: $519,990 | O87: 2523 | P87: 2988 | Q87: 5 | R87: 9 | S87: 5 | T87: 194 | U87: NEW EMPLOYEE PRICING EVENT | UP TO $40,000 IN NEW HOME SAVINGS | V87: https://www.davidweekleyhomes.com/new-homes/tx/houston/cypress/bridgeland-central-55-homesites | W87: 2026-09-27
A88: hou-bridgeland#9 | B88: houston | C88: hou-bridgeland | D88: Bridgeland | E88: David Weekley Homes | F88: Prairieland Village - Summit Collection | G88: 60 | H88: 60 | I88: 1, 2 | J88: 549000 | K88: yes | L88: Priced From $549s | M88: 655990 | N88: From: $655,990 | O88: 2734 | P88: 3817 | Q88: 9 | R88: 5 | S88: 5 | T88: 214 | U88: NEW EMPLOYEE PRICING EVENT | UP TO $40,000 IN NEW HOME SAVINGS | V88: https://www.davidweekleyhomes.com/new-homes/tx/houston/cypress/parkland-village-60 | W88: 2026-09-27
A89: hou-bridgeland#10 | B89: houston | C89: hou-bridgeland | D89: Bridgeland | E89: David Weekley Homes | F89: Prairieland Village - Grove Collection | J89: 429990 | L89: From $429,990 | S89: 0 | U89: FINAL OPPORTUNITIES! CLOSE OUT | V89: https://www.davidweekleyhomes.com/neighborhoods/tx/houston/bridgeland-prairieland-village | W89: 2026-09-27
A90: hou-bridgeland#11 | B90: houston | C90: hou-bridgeland | D90: Bridgeland | E90: Highland Homes | F90: 40ft lots | G90: 40 | H90: 40 | J90: 380000 | K90: yes | L90: From the $380s | S90: 3 | T90: 190 | V90: https://www.highlandhomes.com/houston/cypress/bridgeland | W90: 2026-09-27
A91: hou-bridgeland#12 | B91: houston | C91: hou-bridgeland | D91: Bridgeland | E91: Highland Homes | F91: 65ft lots | G91: 65 | H91: 65 | J91: 750000 | K91: yes | L91: From the $750s | S91: 3 | T91: 240 | V91: https://www.highlandhomes.com/houston/cypress/bridgeland | W91: 2026-09-27
A92: hou-bridgeland#13 | B92: houston | C92: hou-bridgeland | D92: Bridgeland | E92: Highland Homes | F92: Bridgeland Central - The Villas | I92: 2 | J92: 380000 | K92: yes | L92: From the $380s | S92: 3 | T92: 239 | V92: https://www.highlandhomes.com/houston/cypress/bridgeland-central | W92: 2026-09-27
A93: hou-bridgeland#14 | B93: houston | C93: hou-bridgeland | D93: Bridgeland | E93: Highland Homes | F93: Bridgeland Central - The Cottages | I93: 2 | J93: 400000 | K93: yes | L93: From the $400s | S93: 3 | T93: 221 | V93: https://www.highlandhomes.com/houston/cypress/bridgeland-central | W93: 2026-09-27
A94: hou-bridgeland#15 | B94: houston | C94: hou-bridgeland | D94: Bridgeland | E94: Coventry Homes | F94: Bridgeland 40' | G94: 40 | H94: 40 | J94: 344990 | L94: Starting at $344,990 | M94: 419990 | N94: From $419,990 | O94: 1526 | P94: 2437 | Q94: 10 | R94: 4 | S94: 4 | T94: 209 | V94: https://www.coventryhomes.com/new-homes/tx/cypress/bridgeland-40/ | W94: 2026-09-27
A95: hou-bridgeland#16 | B95: houston | C95: hou-bridgeland | D95: Bridgeland | E95: Coventry Homes | F95: Bridgeland 55' | G95: 55 | H95: 55 | J95: 474990 | L95: Starting at $474,990 | M95: 654990 | N95: From $654,990 | O95: 2493 | P95: 3584 | Q95: 11 | R95: 4 | S95: 4 | T95: 202 | V95: https://www.coventryhomes.com/new-homes/tx/cypress/bridgeland-55/ | W95: 2026-09-27
A96: hou-bridgeland#17 | B96: houston | C96: hou-bridgeland | D96: Bridgeland | E96: Chesmar Homes | F96: Bridgeland | J96: 314990 | L96: Starting From $314,990 | O96: 1533 | P96: 2671 | S96: 0 | V96: https://www.chesmar.com/communities/texas/houston-new-homes/ | W96: 2026-09-27
A97: hou-bridgeland#18 | B97: houston | C97: hou-bridgeland | D97: Bridgeland | E97: Chesmar Homes | F97: Bridgeland Courtyard | J97: 357990 | L97: Starting From: $357,990 | S97: 0 | V97: https://www.chesmar.com/texas/houston-new-homes/cypress/bridgeland-courtyard/ | W97: 2026-09-27
A98: hou-bridgeland#19 | B98: houston | C98: hou-bridgeland | D98: Bridgeland | E98: Westin Homes | F98: Bridgeland 50' (Creekland Village) | G98: 50 | H98: 50 | J98: 534954 | L98: Starting from $534,954 | M98: 593990 | N98: Starting from $593,990 | O98: 3000 | P98: 3114 | Q98: 4 | R98: 7 | S98: 5 | T98: 187 | V98: https://www.westin-homes.com/communities/houston/bridgeland/bridgeland-50-creekland-village | W98: 2026-09-27
A99: hou-bridgeland#20 | B99: houston | C99: hou-bridgeland | D99: Bridgeland | E99: Westin Homes | F99: Bridgeland 60' (Prairieland Village) | G99: 60 | H99: 60 | J99: 694972 | L99: Starting from $694,972 | M99: 767990 | N99: Starting from $767,990 | O99: 3429 | P99: 3957 | Q99: 8 | R99: 5 | S99: 5 | T99: 189 | V99: https://www.westin-homes.com/communities/houston/bridgeland/bridgeland-60-prairieland-village | W99: 2026-09-27
A100: hou-bridgeland#21 | B100: houston | C100: hou-bridgeland | D100: Bridgeland | E100: Beazer Homes | F100: Bridgeland 40', 45', 50' Homesites | G100: 40, 45, 50 | J100: 332990 | L100: Starting $332,990 | O100: 1642 | P100: 3196 | R100: 8 | S100: 5 | T100: 202 | U100: For a limited time, receive up to $25,000 in flex savings on your new to-be-built home when you use a Choice Lender!* | V100: https://www.beazer.com/houston-TX/cypress/bridgeland | W100: 2026-09-27
...

Sheet Communities
A1: community_id | B1: market | C1: community | D1: developer | E1: county | F1: city | G1: zip | H1: school_district | I1: acres | J1: planned_homes | K1: first_homes | L1: rclco_rank | M1: rclco_sales | N1: rclco_year | O1: n_builders | P1: n_product_lines | Q1: lot_widths_ft | R1: from_min | S1: from_median | T1: from_max | U1: qmi_n | V1: qmi_median_price | W1: qmi_median_sqft | X1: qmi_median_ppsf | Y1: zip_zhvi | Z1: zip_zhvi_month | AA1: zip_zhvi_yoy | AB1: zip_zhvi_5y | AC1: zip_redfin_median_sale | AD1: zip_redfin_ppsf | AE1: zip_redfin_sold_90d | AF1: zip_redfin_dom | AG1: zip_redfin_period_end | AH1: lat_zip_centroid | AI1: lon_zip_centroid | AJ1: nearest_cbd | AK1: miles_to_nearest_cbd | AL1: website | AM1: community_price_text
A2: hou-artavia | B2: houston | C2: ARTAVIA | D2: AIRIA Development Company | E2: Montgomery | F2: Conroe | G2: 77302 | H2: Conroe ISD | I2: 2842 | J2: 6500 | O2: 10 | P2: 18 | Q2: 40, 45, 50, 55, 60, 65, 70, 80 | R2: 330991 | S2: 488995 | T2: 850000 | U2: 49 | V2: 517990 | W2: 2948 | X2: 182 | Y2: 326778 | Z2: 2026-08 | AA2: -0.0227 | AB2: 0.0986 | AC2: 335775 | AD2: 153 | AE2: 264 | AF2: 114 | AG2: 2026-05-31 | AH2: 30.20341 | AI2: -95.33118 | AJ2: Houston | AK2: 30.7 | AL2: https://artaviatx.com/
A3: hou-amira | B3: houston | C3: Amira | D3: Johnson Development | E3: Harris | F3: Tomball | G3: 77377 | H3: Tomball ISD | I3: 554 | J3: 1100 | K3: 2019 | O3: 2 | P3: 2 | Q3: 45, 50 | R3: 349067 | S3: 359534 | T3: 370000 | U3: 5 | V3: 418112 | W3: 2562 | X3: 182 | Y3: 396798 | Z3: 2026-08 | AA3: -0.0119 | AB3: 0.1655 | AC3: 380000 | AD3: 164 | AE3: 200 | AF3: 63 | AG3: 2026-05-31 | AH3: 30.0706 | AI3: -95.71555 | AJ3: Houston | AK3: 29.8 | AL3: https://amiratexas.com/ | AM3: New Homes FROM THE LOW $300s
A4: hou-anniston | B4: houston | C4: Anniston | D4: Friendswood Development Company | E4: Harris | F4: Katy | G4: 77493 | H4: Katy ISD | L4: 12 | M4: 775 | O4: 1 | P4: 8 | R4: 219991 | S4: 288990 | T4: 386990 | U4: 34 | V4: 310990 | W4: 2173 | X4: 142 | Y4: 336733 | Z4: 2026-08 | AA4: -0.0396 | AB4: 0.0929 | AC4: 340000 | AD4: 159 | AE4: 735 | AF4: 67 | AG4: 2026-05-31 | AH4: 29.8532 | AI4: -95.8315 | AJ4: Houston | AK4: 28.4 | AL4: https://friendswooddevelopment.com/communities/master-planned/anniston | AM4: Lennar - from the $260s
A5: hou-audubon | B5: houston | C5: Audubon | D5: Audubon Magnolia Development, LLC (managed by Sam Yager Inc.) | E5: Montgomery | F5: Magnolia | G5: 77354 | H5: Magnolia ISD | I5: 3000 | J5: 5000 | O5: 12 | P5: 17 | Q5: 40, 45, 50, 55, 60, 70, 80 | R5: 200000 | S5: 469990 | T5: 749995 | U5: 42 | V5: 568995 | W5: 2742 | X5: 196 | Y5: 378164 | Z5: 2026-08 | AA5: -0.0149 | AB5: 0.1508 | AC5: 338065 | AD5: 164 | AE5: 359 | AF5: 80.5 | AG5: 2026-05-31 | AH5: 30.22054 | AI5: -95.72072 | AJ5: Houston | AK5: 38.1 | AL5: https://audubonliving.com/ | AM5: From the $300s - $1M+
A6: hou-austin-point | B6: houston | C6: Austin Point | D6: The Signorelli Company | E6: Fort Bend | F6: Richmond | G6: 77469 | H6: Lamar CISD | I6: 4700 | J6: 10000 | O6: 9 | P6: 12 | Q6: 35, 40, 45, 50, 60, 70 | R6: 200000 | S6: 385394 | T6: 750000 | U6: 32 | V6: 429995 | W6: 2600 | X6: 163 | Y6: 337586 | Z6: 2026-08 | AA6: -0.0227 | AB6: 0.1256 | AC6: 330440 | AD6: 156 | AE6: 361 | AF6: 55 | AG6: 2026-05-31 | AH6: 29.4914 | AI6: -95.7021 | AJ6: Houston | AK6: 27.3 | AL6: https://www.austinpoint.com/ | AM6: New homes from the $200s to $900s in Fort Bend County.
A7: hou-baytown-crossings | B7: houston | C7: Baytown Crossings | D7: Friendswood Development Company | E7: Harris | F7: Baytown | G7: 77521 | H7: Goose Creek CISD | I7: 520 | J7: 1600 | L7: 35 | M7: 264 | O7: 2 | P7: 11 | Q7: 45, 50, 60 | R7: 193991 | S7: 271990 | T7: 380990 | U7: 16 | V7: 285990 | W7: 1966 | X7: 146 | Y7: 253942 | Z7: 2026-08 | AA7: -0.01 | AB7: 0.1239 | AC7: 257875 | AD7: 134 | AE7: 196 | AF7: 41 | AG7: 2026-05-31 | AH7: 29.8119 | AI7: -94.9633 | AJ7: Houston | AK7: 24.6 | AL7: https://friendswooddevelopment.com/communities/master-planned/baytown-crossings
A8: hou-bluestem | B8: houston | C8: Bluestem | D8: The Signorelli Company | E8: Waller | F8: Brookshire | G8: 77423 | H8: Royal ISD | I8: 356 | J8: 1300 | K8: 2024 | O8: 3 | P8: 4 | R8: 259857 | S8: 259857 | T8: 259857 | U8: 9 | V8: 304990 | W8: 1961 | X8: 155 | Y8: 365601 | Z8: 2026-08 | AA8: -0.0282 | AB8: 0.1051 | AC8: 334990 | AD8: 159 | AE8: 229 | AF8: 76.5 | AG8: 2026-05-31 | AH8: 29.8331 | AI8: -95.9869 | AJ8: Houston | AK8: 37.3 | AL8: https://www.bluestemtx.com/
A9: hou-briarley | B9: houston | C9: Briarley | D9: Johnson Development | E9: Montgomery | F9: Montgomery | G9: 77316 | H9: Montgomery ISD | I9: 388 | O9: 5 | P9: 6 | Q9: 60, 70, 80 | R9: 489990 | S9: 586990 | T9: 670000 | U9: 10 | V9: 655490 | W9: 3587 | X9: 182 | Y9: 413912 | Z9: 2026-08 | AA9: -0.0244 | AB9: 0.1668 | AC9: 374990 | AD9: 162 | AE9: 505 | AF9: 88 | AG9: 2026-05-31 | AH9: 30.3062 | AI9: -95.6864 | AJ9: Houston | AK9: 42.2 | AL9: https://briarleytx.com/ | AM9: New homes from the $500s on spacious 60′-80′ homesites
A10: hou-bridgeland | B10: houston | C10: Bridgeland | D10: Howard Hughes | E10: Harris | F10: Cypress | G10: 77433 | H10: Waller ISD; Cy-Fair ISD | I10: 11500 | L10: 11 | M10: 812 | O10: 17 | P10: 34 | Q10: 40, 45, 50, 55, 60, 65, 70, 80, 90 | R10: 256991 | S10: 429495 | T10: 1200000 | U10: 84 | V10: 537530 | W10: 2634 | X10: 214 | Y10: 424653 | Z10: 2026-08 | AA10: -0.0127 | AB10: 0.1618 | AC10: 427790 | AD10: 175 | AE10: 677 | AF10: 58 | AG10: 2026-05-31 | AH10: 29.94082 | AI10: -95.75261 | AJ10: Houston | AK10: 26.1 | AL10: https://www.bridgeland.com/
A11: hou-brookewater | B11: houston | C11: Brookewater | D11: Land Tejas / Starwood Land | E11: Fort Bend | F11: Rosenberg | G11: 77471 | H11: Lamar CISD | I11: 850 | J11: 2400 | O11: 9 | P11: 11 | Q11: 40, 45, 50, 55, 60 | R11: 297990 | S11: 323990 | T11: 499461 | U11: 31 | V11: 379790 | W11: 2392 | X11: 162 | Y11: 280072 | Z11: 2026-08 | AA11: -0.022 | AB11: 0.1345 | AC11: 351242.5 | AD11: 142 | AE11: 166 | AF11: 102.5 | AG11: 2026-05-31 | AH11: 29.5485 | AI11: -95.862 | AJ11: Houston | AK11: 33 | AL11: https://livebrookewater.com/ | AM11: New Homes from the $300s - $600s
A12: hou-colton | B12: houston | C12: COLTON | D12: AIRIA Development Company | E12: Montgomery | F12: Todd Mission | G12: 77316 | H12: Magnolia ISD | I12: 5700 | J12: 11000 | O12: 11 | P12: 14 | Q12: 45, 50, 55, 60, 65, 70, 80 | R12: 275991 | S12: 497495 | T12: 800000 | U12: 45 | V12: 519390 | W12: 2996 | X12: 175 | Y12: 413912 | Z12: 2026-08 | AA12: -0.0244 | AB12: 0.1668 | AC12: 374990 | AD12: 162 | AE12: 505 | AF12: 88 | AG12: 2026-05-31 | AH12: 30.3062 | AI12: -95.6864 | AJ12: Houston | AK12: 42.2 | AL12: https://coltontx.com/
A13: hou-candela | B13: houston | C13: Candela | D13: Johnson Development | E13: Fort Bend | F13: Richmond | G13: 77406 | H13: Lamar CISD | I13: 578 | O13: 3 | P13: 12 | Q13: 40, 50, 60 | R13: 329990 | S13: 469701 | T13: 630000 | U13: 48 | V13: 474900 | W13: 2628 | X13: 181 | Y13: 416996 | Z13: 2026-08 | AA13: -0.0184 | AB13: 0.1568 | AC13: 420000 | AD13: 172 | AE13: 319 | AF13: 78 | AG13: 2026-05-31 | AH13: 29.68245 | AI13: -95.84077 | AJ13: Houston | AK13: 28.8 | AL13: https://candelatx.com/ | AM13: New Homes from the $300s
A14: hou-canterra-creek | B14: houston | C14: Canterra Creek | D14: Land Tejas / Starwood Land | E14: Brazoria | F14: Iowa Colony | G14: 77583 | H14: Alvin ISD | I14: 380 | O14: 5 | P14: 5 | Q14: 60 | R14: 299900 | S14: 349945 | T14: 399990 | U14: 3 | V14: 496998 | W14: 3405 | X14: 150 | Y14: 317552 | Z14: 2026-08 | AA14: -0.0444 | AB14: 0.053 | AC14: 315000 | AD14: 155 | AE14: 248 | AF14: 70 | AG14: 2026-05-31 | AH14: 29.3742 | AI14: -95.4538 | AJ14: Houston | AK14: 27.2 | AL14: https://canterracreek.com/ | AM14: Trending home designs starting from the $300s
A15: hou-cielo | B15: houston | C15: Cielo | D15: The Signorelli Company | E15: Montgomery | F15: Conroe | G15: 77303 | H15: Conroe ISD | I15: 256 | J15: 837 | K15: 2024 | O15: 5 | P15: 5 | R15: 232990 | S15: 244990 | T15: 260955 | U15: 15 | V15: 306030 | W15: 2026 | X15: 151 | Y15: 267140 | Z15: 2026-08 | AA15: -0.0265 | AB15: 0.074 | AC15: 255000 | AD15: 148 | AE15: 179 | AF15: 79 | AG15: 2026-05-31 | AH15: 30.37264 | AI15: -95.41233 | AJ15: Houston | AK15: 42.4 | AL15: https://www.cieloconroe.com/
A16: hou-creekhaven | B16: houston | C16: Creekhaven | D16: Land Tejas / Starwood Land | E16: Brazoria | F16: Iowa Colony | G16: 77583 | H16: Alvin ISD | I16: 955 | J16: 2100 | O16: 7 | P16: 9 | Q16: 40, 50, 60 | R16: 252990 | S16: 289888 | T16: 333990 | U16: 21 | V16: 317990 | W16: 1784 | X16: 170 | Y16: 317552 | Z16: 2026-08 | AA16: -0.0444 | AB16: 0.053 | AC16: 315000 | AD16: 155 | AE16: 248 | AF16: 70 | AG16: 2026-05-31 | AH16: 29.3742 | AI16: -95.4538 | AJ16: Houston | AK16: 27.2 | AL16: https://creekhaventx.com/ | AM16: New Homes from the High $200s–$600s
A17: hou-cross-creek-west | B17: houston | C17: Cross Creek West | D17: Johnson Development | E17: Fort Bend | F17: Fulshear | G17: 77441 | H17: Lamar CISD | I17: 1258 | J17: 3000 | O17: 10 | P17: 14 | Q17: 45, 50, 55, 60, 65, 70 | R17: 340990 | S17: 542387 | T17: 1000000 | U17: 15 | V17: 499880 | W17: 2833 | X17: 173 | Y17: 509526 | Z17: 2026-08 | AA17: -0.0282 | AB17: 0.2034 | AC17: 485000 | AD17: 175 | AE17: 329 | AF17: 63 | AG17: 2026-05-31 | AH17: 29.6974 | AI17: -95.9096 | AJ17: Houston | AK17: 32.7 | AL17: https://www.crosscreekwesttx.com/
A18: hou-cypress-green | B18: houston | C18: Cypress Green | D18: Land Tejas / Starwood Land | E18: Harris | F18: Hockley | G18: 77447 | H18: Waller ISD | I18: 646 | J18: 2300 | L18: 47 | M18: 193 | O18: 7 | P18: 10 | R18: 249990 | S18: 279990 | T18: 312991 | U18: 33 | V18: 299990 | W18: 1922 | X18: 147 | Y18: 303050 | Z18: 2026-08 | AA18: -0.0376 | AB18: 0.072 | AC18: 307450 | AD18: 155 | AE18: 396 | AF18: 83 | AG18: 2026-05-31 | AH18: 30.0646 | AI18: -95.76562 | AJ18: Houston | AK18: 31.7 | AL18: https://cypressgreentx.com/ | AM18: High $200s-$500s
A19: hou-dunham-pointe | B19: houston | C19: Dunham Pointe | D19: Archie Dunham | E19: Harris | F19: Cypress | G19: 77433 | H19: Cy-Fair ISD | I19: 1327 | O19: 5 | P19: 8 | Q19: 50, 60, 65, 70, 80 | R19: 599900 | S19: 790490 | T19: 847900 | U19: 20 | V19: 961688 | W19: 4194 | X19: 228 | Y19: 424653 | Z19: 2026-08 | AA19: -0.0127 | AB19: 0.1618 | AC19: 427790 | AD19: 175 | AE19: 677 | AF19: 58 | AG19: 2026-05-31 | AH19: 29.9453 | AI19: -95.7414 | AJ19: Houston | AK19: 25.7 | AL19: https://www.dunhampointecypress.com/
A20: hou-elyson | B20: houston | C20: Elyson | D20: Brookfield Residential | E20: Harris | F20: Katy | G20: 77493 | H20: Katy ISD | L20: 41 | M20: 413 | O20: 9 | P20: 21 | Q20: 40, 45, 50, 55, 60, 65, 70, 80 | R20: 309000 | S20: 430214 | T20: 800000 | U20: 35 | V20: 441840 | W20: 2425 | X20: 192 | Y20: 336733 | Z20: 2026-08 | AA20: -0.0396 | AB20: 0.0929 | AC20: 340000 | AD20: 159 | AE20: 735 | AF20: 67 | AG20: 2026-05-31 | AH20: 29.8877 | AI20: -95.79284 | AJ20: Houston | AK20: 26.8 | AL20: https://www.elyson.com/
A21: hou-emberly | B21: houston | C21: Emberly | D21: Land Tejas / Starwood Land | E21: Fort Bend | F21: Beasley | G21: 77417 | H21: Lamar CISD | I21: 933 | O21: 6 | P21: 6 | R21: 238990 | S21: 265445 | T21: 325990 | U21: 12 | V21: 269990 | W21: 1670 | X21: 146 | Y21: 280735 | Z21: 2026-08 | AA21: -0.0073 | AB21: 0.0554 | AC21: 277495 | AD21: 140 | AE21: 46 | AF21: 117 | AG21: 2026-05-31 | AH21: 29.46356 | AI21: -95.95199 | AJ21: Houston | AK21: 40.5 | AL21: https://emberlytexas.com/ | AM21: New Homes for Sale in Fort Bend from the High $200s-$500s
A22: hou-evergreen | B22: houston | C22: Evergreen | D22: Shea Homes | E22: Montgomery | F22: Conroe | G22: 77302 | H22: Conroe ISD | I22: 740 | J22: 2000 | O22: 4 | P22: 9 | Q22: 40, 45, 50, 60, 70 | R22: 339990 | S22: 440000 | T22: 670000 | U22: 3 | V22: 414990 | W22: 2327 | X22: 189 | Y22: 326778 | Z22: 2026-08 | AA22: -0.0227 | AB22: 0.0986 | AC22: 335775 | AD22: 153 | AE22: 264 | AF22: 114 | AG22: 2026-05-31 | AH22: 30.2221 | AI22: -95.3449 | AJ22: Houston | AK22: 31.9 | AL22: https://evergreen-texas.com/
A23: hou-everly | B23: houston | C23: Everly | D23: Johnson Development | E23: Harris | F23: Hockley | G23: 77447 | H23: Waller ISD | I23: 351 | J23: 1059 | O23: 3 | P23: 6 | Q23: 45, 50, 60 | R23: 389900 | S23: 479450 | T23: 560000 | U23: 14 | V23: 432490 | W23: 2157 | X23: 188 | Y23: 303050 | Z23: 2026-08 | AA23: -0.0376 | AB23: 0.072 | AC23: 307450 | AD23: 155 | AE23: 396 | AF23: 83 | AG23: 2026-05-31 | AH23: 30.0553 | AI23: -95.8248 | AJ23: Houston | AK23: 34 | AL23: https://www.everlytx.com/ | AM23: New homes from the $400s
A24: hou-fulbrook-on-fulshear-creek | B24: houston | C24: Fulbrook on Fulshear Creek | D24: Trend Development | E24: Fort Bend | F24: Fulshear | G24: 77441 | H24: Lamar CISD | O24: 2 | P24: 2 | Q24: 60 | R24: 598990 | S24: 604495 | T24: 610000 | U24: 1 | V24: 605990 | W24: 3017 | X24: 201 | Y24: 509526 | Z24: 2026-08 | AA24: -0.0282 | AB24: 0.2034 | AC24: 485000 | AD24: 175 | AE24: 329 | AF24: 63 | AG24: 2026-05-31 | AH24: 29.6974 | AI24: -95.9096 | AJ24: Houston | AK24: 32.7 | AL24: https://www.fulbrookhomes.com/ | AM24: New construction homes from the $500s
A25: hou-grand-central-park | B25: houston | C25: Grand Central Park | D25: Johnson Development | E25: Montgomery | F25: Conroe | G25: 77304 | H25: Conroe ISD | J25: 1700 | O25: 6 | P25: 9 | Q25: 40, 45, 50, 55, 60, 70 | R25: 357990 | S25: 480990 | T25: 856960 | U25: 19 | V25: 514990 | W25: 2800 | X25: 194 | Y25: 331918 | Z25: 2026-08 | AA25: -0.0161 | AB25: 0.1046 | AC25: 360000 | AD25: 165 | AE25: 226 | AF25: 105 | AG25: 2026-05-31 | AH25: 30.3278 | AI25: -95.516 | AJ25: Houston | AK25: 40.2 | AL25: https://www.grandcentralparktx.com/ | AM25: new homes from the $300s+
A26: hou-grand-magnolia | B26: houston | C26: Grand Magnolia | D26: Land Tejas / Starwood Land | E26: Montgomery | F26: Magnolia | G26: 77355, 77484, 77354 | H26: Waller ISD | I26: 2755 | J26: 6900 | O26: 9 | P26: 16 | Q26: 50, 60 | R26: 218991 | S26: 304990 | T26: 400000 | U26: 36 | V26: 401420 | W26: 2055 | X26: 173 | Y26: 367076 | Z26: 2026-08 | AA26: -0.0098 | AB26: 0.148 | AC26: 310500 | AD26: 162 | AE26: 200 | AF26: 73 | AG26: 2026-05-31 | AH26: 30.1563 | AI26: -95.7493 | AJ26: Houston | AK26: 35.6 | AL26: https://grandmagnoliatx.com/ | AM26: NEW HOMES FROM THE $200s
A27: hou-grange | B27: houston | C27: Grange | D27: Johnson Development | E27: Waller | F27: Katy | G27: 77493 | H27: Katy ISD | I27: 1130 | J27: 2400 | O27: 8 | P27: 10 | Q27: 40, 45, 50, 55, 60 | R27: 370000 | S27: 459495 | T27: 630000 | U27: 13 | V27: 489145 | W27: 2776 | X27: 182 | Y27: 336733 | Z27: 2026-08 | AA27: -0.0396 | AB27: 0.0929 | AC27: 340000 | AD27: 159 | AE27: 735 | AF27: 67 | AG27: 2026-05-31 | AH27: 29.8532 | AI27: -95.8315 | AJ27: Houston | AK27: 28.4 | AL27: https://www.liveingrange.com/ | AM27: new homes from the high $300s–Millions
A28: hou-harvest-green | B28: houston | C28: Harvest Green | D28: Johnson Development | E28: Fort Bend | F28: Richmond | G28: 77406 | H28: Fort Bend ISD | I28: 1700 | O28: 6 | P28: 8 | Q28: 45, 60, 65, 75, 90 | R28: 475000 | S28: 833892 | T28: 1300000 | U28: 23 | V28: 834853 | W28: 3700 | X28: 238 | Y28: 416996 | Z28: 2026-08 | AA28: -0.0184 | AB28: 0.1568 | AC28: 420000 | AD28: 172 | AE28: 319 | AF28: 78 | AG28: 2026-05-31 | AH28: 29.6461 | AI28: -95.7945 | AJ28: Houston | AK28: 26.7 | AL28: https://www.harvestgreentexas.com/
A29: hou-indigo | B29: houston | C29: Indigo | D29: Meristem Communities | E29: Fort Bend | F29: Richmond | G29: 77406, 77407 | H29: Fort Bend ISD | I29: 235 | J29: 800 | K29: 2024 | O29: 5 | P29: 12 | Q29: 35, 40, 50 | R29: 367990 | S29: 405000 | T29: 455000 | U29: 35 | V29: 415000 | W29: 2177 | X29: 203 | Y29: 416996 | Z29: 2026-08 | AA29: -0.0184 | AB29: 0.1568 | AC29: 420000 | AD29: 172 | AE29: 319 | AF29: 78 | AG29: 2026-05-31 | AH29: 29.6461 | AI29: -95.7945 | AJ29: Houston | AK29: 26.7 | AL29: https://www.indigocommunity.com/
A30: hou-jordan-ranch | B30: houston | C30: Jordan Ranch | D30: Johnson Development | E30: Fort Bend | F30: Fulshear | G30: 77423, 77494 | L30: 49t | M30: 211 | O30: 7 | P30: 17 | Q30: 40, 45, 50, 55, 60, 65, 70 | R30: 300000 | S30: 450000 | T30: 670000 | U30: 8 | V30: 534594 | W30: 2951 | X30: 178 | Y30: 365601 | Z30: 2026-08 | AA30: -0.0282 | AB30: 0.1051 | AC30: 334990 | AD30: 159 | AE30: 229 | AF30: 76.5 | AG30: 2026-05-31 | AH30: 29.75754 | AI30: -95.88094 | AJ30: Houston | AK30: 30.7 | AL30: https://www.jordanranchtexas.com/ | AM30: from the $300’s to $1 million +
A31: hou-jubilee | B31: houston | C31: Jubilee | D31: Johnson Development | E31: Harris | F31: Hockley | G31: 77447 | H31: Waller ISD | O31: 10 | P31: 18 | Q31: 40, 45, 50, 55, 60, 70, 80 | R31: 290000 | S31: 377495 | T31: 730000 | U31: 37 | V31: 435000 | W31: 2458 | X31: 172 | Y31: 303050 | Z31: 2026-08 | AA31: -0.0376 | AB31: 0.072 | AC31: 307450 | AD31: 155 | AE31: 396 | AF31: 83 | AG31: 2026-05-31 | AH31: 30.0553 | AI31: -95.8248 | AJ31: Houston | AK31: 34 | AL31: https://www.liveinjubilee.com/
A32: hou-kresston | B32: houston | C32: Kresston | D32: Johnson Development | E32: Montgomery | F32: Magnolia | G32: 77316 | H32: Magnolia ISD | I32: 1400 | J32: 3200 | O32: 12 | P32: 16 | Q32: 40, 50, 55, 60, 65, 70, 80 | R32: 299990 | S32: 440000 | T32: 790000 | U32: 21 | V32: 394914 | W32: 2581 | X32: 159 | Y32: 413912 | Z32: 2026-08 | AA32: -0.0244 | AB32: 0.1668 | AC32: 374990 | AD32: 162 | AE32: 505 | AF32: 88 | AG32: 2026-05-31 | AH32: 30.3062 | AI32: -95.6864 | AJ32: Houston | AK32: 42.2 | AL32: https://kresston.com/
A33: hou-lago-mar | B33: houston | C33: Lago Mar | D33: Land Tejas / Starwood Land | E33: Galveston | F33: Texas City | G33: 77568 | H33: Dickinson ISD | I33: 2033 | L33: 47 | M33: 380 | O33: 13 | P33: 15 | Q33: 50, 60 | R33: 200000 | S33: 310000 | T33: 534990 | U33: 36 | V33: 341445 | W33: 1993 | X33: 170 | Y33: 252710 | Z33: 2026-08 | AA33: -0.0272 | AB33: 0.0535 | AC33: 270000 | AD33: 146 | AE33: 154 | AF33: 76 | AG33: 2026-05-31 | AH33: 29.40285 | AI33: -95.06348 | AJ33: Houston | AK33: 30.8 | AL33: https://lagomarintexascity.com/ | AM33: homes from the high $200s – $500s
A34: hou-legacy | B34: houston | C34: Legacy | D34: Hillwood Communities | E34: Galveston | F34: League City | G34: 77546, 77573 | H34: Clear Creek ISD | I34: 700 | J34: 1630 | O34: 10 | P34: 10 | Q34: 50, 60, 65, 70, 80 | R34: 397990 | S34: 607132 | T34: 1000000 | U34: 25 | V34: 599900 | W34: 2805 | X34: 202 | Y34: 401979 | Z34: 2026-08 | AA34: 0.0038 | AB34: 0.1711 | AC34: 447500 | AD34: 183 | AE34: 196 | AF34: 35.5 | AG34: 2026-05-31 | AH34: 29.5111 | AI34: -95.193 | AJ34: Houston | AK34: 20.2 | AL34: https://www.legacybyhillwood.com/ | AM34: prices starting from the $400s
A35: hou-marvida | B35: houston | C35: Marvida | D35: Land Tejas / Starwood Land | E35: Harris | F35: Cypress | G35: 77433 | H35: Cypress-Fairbanks ISD | I35: 856 | J35: 2500 | L35: 31 | M35: 518 | O35: 5 | P35: 6 | Q35: 45, 55 | R35: 280000 | S35: 435000 | T35: 540000 | U35: 7 | V35: 349990 | W35: 2198 | X35: 190 | Y35: 424653 | Z35: 2026-08 | AA35: -0.0127 | AB35: 0.1618 | AC35: 427790 | AD35: 175 | AE35: 677 | AF35: 58 | AG35: 2026-05-31 | AH35: 29.89655 | AI35: -95.74473 | AJ35: Houston | AK35: 24.4 | AL35: https://marvidahouston.com/
A36: hou-mavera | B36: houston | C36: Mavera | D36: PulteGroup | E36: Montgomery | F36: Conroe | G36: 77302 | H36: Conroe ISD | I36: 820 | J36: 3000 | O36: 4 | P36: 6 | R36: 200000 | S36: 249990 | T36: 301990 | U36: 15 | V36: 304380 | W36: 1777 | X36: 177 | Y36: 326778 | Z36: 2026-08 | AA36: -0.0227 | AB36: 0.0986 | AC36: 335775 | AD36: 153 | AE36: 264 | AF36: 114 | AG36: 2026-05-31 | AH36: 30.2221 | AI36: -95.3449 | AJ36: Houston | AK36: 31.9
A37: hou-meridiana | B37: houston | C37: Meridiana | D37: Rise Communities | E37: Brazoria | F37: Iowa Colony | G37: 77578, 77583 | H37: Alvin ISD | I37: 3000 | J37: 5500 | K37: 2016 | L37: 24 | M37: 527 | O37: 10 | P37: 25 | Q37: 40, 45, 50, 55, 60, 65, 70 | R37: 269990 | S37: 443995 | T37: 640000 | U37: 73 | V37: 524900 | W37: 2545 | X37: 201 | Y37: 439597 | Z37: 2026-08 | AA37: -0.0248 | AB37: 0.1334 | AC37: 456000 | AD37: 176 | AE37: 243 | AF37: 117 | AG37: 2026-05-31 | AH37: 29.45405 | AI37: -95.37728 | AJ37: Houston | AK37: 21.2 | AL37: https://www.meridianatexas.com/ | AM37: NEW HOMES FROM THE $200’S – $1MIL+
A38: hou-mill-creek | B38: houston | C38: Mill Creek | D38: Forestar | E38: Montgomery | F38: Magnolia | G38: 77354 | H38: Magnolia ISD | O38: 1 | P38: 2 | R38: 219990 | S38: 266490 | T38: 312990 | U38: 8 | V38: 307490 | W38: 2145 | X38: 158 | Y38: 378164 | Z38: 2026-08 | AA38: -0.0149 | AB38: 0.1508 | AC38: 338065 | AD38: 164 | AE38: 359 | AF38: 80.5 | AG38: 2026-05-31 | AH38: 30.2079 | AI38: -95.643 | AJ38: Houston | AK38: 35 | AL38: https://millcreek-community.com/ | AM38: New Homes from the high $200s to $350s
A39: hou-moran-ranch | B39: houston | C39: Moran Ranch | E39: Montgomery | F39: Willis | G39: 77378 | H39: Willis ISD | I39: 500 | J39: 900 | O39: 2 | P39: 4 | Q39: 60 | R39: 199990 | S39: 247490 | T39: 353240 | U39: 3 | V39: 226990 | W39: 1451 | X39: 156 | Y39: 246210 | Z39: 2026-08 | AA39: -0.0147 | AB39: 0.0544 | AC39: 235000 | AD39: 161 | AE39: 98 | AF39: 109 | AG39: 2026-05-31 | AH39: 30.4781 | AI39: -95.3849 | AJ39: Houston | AK39: 49.6
A40: hou-oakberry-trails | B40: houston | C40: Oakberry Trails | D40: Ryko Development | E40: Waller | F40: Waller | G40: 77484 | H40: Waller ISD | I40: 215 | J40: 800 | O40: 3 | P40: 5 | Q40: 40, 50 | R40: 245990 | S40: 284990 | T40: 308990 | U40: 14 | V40: 321470 | W40: 2093 | X40: 150 | Y40: 353605 | Z40: 2026-08 | AA40: -0.0117 | AB40: 0.0931 | AC40: 290000 | AD40: 145 | AE40: 235 | AF40: 81.5 | AG40: 2026-05-31 | AH40: 30.0835 | AI40: -95.9281 | AJ40: Houston | AK40: 40.2 | AL40: https://www.oakberrytrails.com/ | AM40: new homes for sale priced from the low $300s
A41: hou-pomona | B41: houston | C41: Pomona | D41: Hillwood Communities | E41: Brazoria | F41: Manvel | G41: 77578 | H41: Alvin ISD | O41: 3 | P41: 6 | Q41: 40, 42, 45, 50, 55, 60 | R41: 327990 | S41: 383990 | T41: 601990 | U41: 19 | V41: 425000 | W41: 2273 | X41: 192 | Y41: 439597 | Z41: 2026-08 | AA41: -0.0248 | AB41: 0.1334 | AC41: 456000 | AD41: 176 | AE41: 243 | AF41: 117 | AG41: 2026-05-31 | AH41: 29.52213 | AI41: -95.4065 | AJ41: Houston | AK41: 16.6 | AL41: https://www.pomonabyhillwood.com/
A42: hou-riceland | B42: houston | C42: Riceland | D42: McGrath Real Estate Partners | E42: Chambers | F42: Mont Belvieu | G42: 77523 | H42: Barbers Hill ISD | I42: 1500 | J42: 4500 | O42: 5 | P42: 12 | Q42: 42, 50, 60, 65, 70 | R42: 300000 | S42: 415995 | T42: 720000 | U42: 29 | V42: 525000 | W42: 2908 | X42: 193 | Y42: 376784 | Z42: 2026-08 | AA42: 0.0068 | AB42: 0.1268 | AC42: 356040 | AD42: 162 | AE42: 157 | AF42: 87.5 | AG42: 2026-05-31 | AH42: 29.86418 | AI42: -94.86919 | AJ42: Houston | AK42: 30.9 | AL42: https://www.ricelandtx.com/ | AM42: Starting From the $300s
A43: hou-river-ranch | B43: houston | C43: River Ranch | D43: Land Tejas / Starwood Land | E43: Liberty | F43: Dayton | G43: 77535 | H43: Dayton ISD | I43: 2500 | J43: 6725 | O43: 18 | P43: 24 | Q43: 50, 55, 60 | R43: 197990 | S43: 272990 | T43: 395990 | U43: 69 | V43: 309990 | W43: 2031 | X43: 156 | Y43: 323731 | Z43: 2026-08 | AA43: -0.0068 | AB43: 0.1602 | AC43: 331281 | AD43: 161 | AE43: 215 | AF43: 157 | AG43: 2026-05-31 | AH43: 30.0548 | AI43: -94.9223 | AJ43: Houston | AK43: 33.6 | AL43: https://www.riverranchdayton.com/ | AM43: New Homes High $200s - $500s
A44: hou-sienna | B44: houston | C44: Sienna | D44: Johnson Development | E44: Fort Bend | F44: Missouri City | G44: 77459 | H44: Fort Bend ISD | I44: 10800 | J44: 16500 | K44: 1996 | L44: 38 | M44: 432 | O44: 13 | P44: 32 | Q44: 40, 42, 45, 50, 55, 60, 65, 70, 80, 90, 100 | R44: 279990 | S44: 544995 | T44: 1000000 | U44: 77 | V44: 599739 | W44: 2966 | X44: 199 | Y44: 395000 | Z44: 2026-08 | AA44: -0.0155 | AB44: 0.1512 | AC44: 410000 | AD44: 163 | AE44: 338 | AF44: 78 | AG44: 2026-05-31 | AH44: 29.46569 | AI44: -95.51117 | AJ44: Houston | AK44: 22.1 | AL44: https://www.siennatx.com/ | AM44: New Homes Low $300s-Million+
A45: hou-sierra-vista | B45: houston | C45: Sierra Vista | D45: Land Tejas / Starwood Land | E45: Brazoria | F45: Rosharon | G45: 77583 | H45: Alvin ISD | L45: 41 | M45: 244 | O45: 6 | P45: 6 | Q45: 60 | R45: 200000 | S45: 328990 | T45: 383900 | U45: 7 | V45: 379990 | W45: 1848 | X45: 198 | Y45: 317552 | Z45: 2026-08 | AA45: -0.0444 | AB45: 0.053 | AC45: 315000 | AD45: 155 | AE45: 248 | AF45: 70 | AG45: 2026-05-31 | AH45: 29.42784 | AI45: -95.44892 | AJ45: Houston | AK45: 23.5 | AL45: https://sierravistahouston.com/ | AM45: HIGH $200s - $500s
A46: hou-sorella | B46: houston | C46: Sorella | D46: Johnson Development | E46: Harris | F46: Tomball | G46: 77377 | H46: Waller ISD | I46: 248 | J46: 750 | O46: 3 | P46: 4 | R46: 266990 | S46: 275990 | T46: 400000 | U46: 10 | V46: 347219 | W46: 2040 | X46: 170 | Y46: 396798 | Z46: 2026-08 | AA46: -0.0119 | AB46: 0.1655 | AC46: 380000 | AD46: 164 | AE46: 200 | AF46: 63 | AG46: 2026-05-31 | AH46: 30.0599 | AI46: -95.6722 | AJ46: Houston | AK46: 27.5 | AL46: https://sorellaliving.com/
A47: hou-sunterra | B47: houston | C47: Sunterra | D47: Land Tejas / Starwood Land | E47: Waller | F47: Katy | G47: 77493, 77423 | H47: Katy ISD; Royal ISD | I47: 1039 | J47: 2200 | L47: 5 | M47: 1024 | O47: 17 | P47: 18 | Q47: 40, 50, 60 | R47: 230000 | S47: 313495 | T47: 484990 | U47: 31 | V47: 359998 | W47: 2104 | X47: 169 | Y47: 336733 | Z47: 2026-08 | AA47: -0.0396 | AB47: 0.0929 | AC47: 340000 | AD47: 159 | AE47: 735 | AF47: 67 | AG47: 2026-05-31 | AH47: 29.83719 | AI47: -95.85509 | AJ47: Houston | AK47: 29.6 | AL47: https://sunterratx.com/ | AM47: from the high $200s to the $800s
A48: hou-sunterra-lakes | B48: houston | C48: Sunterra Lakes | D48: Land Tejas / Starwood Land | E48: Waller | F48: Brookshire | G48: 77423 | H48: Royal ISD | I48: 1463 | J48: 4000 | O48: 8 | P48: 10 | R48: 244000 | S48: 262990 | T48: 384990 | U48: 34 | V48: 324900 | W48: 2234 | X48: 148 | Y48: 365601 | Z48: 2026-08 | AA48: -0.0282 | AB48: 0.1051 | AC48: 334990 | AD48: 159 | AE48: 229 | AF48: 76.5 | AG48: 2026-05-31 | AH48: 29.8331 | AI48: -95.9869 | AJ48: Houston | AK48: 37.3 | AL48: https://sunterralakestx.com/ | AM48: New Homes $300s-$600s
A49: hou-sweetgrass-village | B49: houston | C49: Sweetgrass Village | E49: Harris | F49: Crosby | G49: 77532 | H49: Crosby ISD | O49: 3 | P49: 5 | R49: 209990 | S49: 209995 | T49: 277990 | U49: 10 | V49: 252695 | W49: 1970 | X49: 138 | Y49: 263179 | Z49: 2026-08 | AA49: -0.0283 | AB49: 0.1073 | AC49: 246500 | AD49: 137 | AE49: 379 | AF49: 59 | AG49: 2026-05-31 | AH49: 29.9329 | AI49: -95.0572 | AJ49: Houston | AK49: 22.2
A50: hou-tamarron | B50: houston | C50: Tamarron | D50: D.R. Horton | E50: Fort Bend | F50: Fulshear | G50: 77441, 77494 | H50: Lamar CISD | L50: 9 | M50: 974 | O50: 1 | P50: 2 | R50: 280990 | S50: 287995 | T50: 295000 | U50: 4 | V50: 302490 | W50: 1540 | X50: 194 | Y50: 509526 | Z50: 2026-08 | AA50: -0.0282 | AB50: 0.2034 | AC50: 485000 | AD50: 175 | AE50: 329 | AF50: 63 | AG50: 2026-05-31 | AH50: 29.6974 | AI50: -95.9096 | AJ50: Houston | AK50: 32.7
A51: hou-the-george | B51: houston | C51: The George | D51: Johnson Development | E51: Fort Bend | F51: Richmond | G51: 77469 | H51: Lamar CISD | I51: 1500 | O51: 8 | P51: 8 | Q51: 40, 45, 50, 60 | R51: 359990 | S51: 462950 | T51: 611990 | U51: 20 | V51: 575950 | W51: 2616 | X51: 220 | Y51: 337586 | Z51: 2026-08 | AA51: -0.0227 | AB51: 0.1256 | AC51: 330440 | AD51: 156 | AE51: 361 | AF51: 55 | AG51: 2026-05-31 | AH51: 29.4914 | AI51: -95.7021 | AJ51: Houston | AK51: 27.3 | AL51: https://lifeatthegeorge.com/
A52: hou-grand-prairie | B52: houston | C52: The Grand Prairie | D52: EMBER Real Estate & Development | E52: Harris | F52: Hockley | G52: 77447 | H52: Waller ISD | I52: 1730 | L52: 17 | M52: 639 | O52: 6 | P52: 10 | Q52: 40, 45, 50, 60 | R52: 230000 | S52: 320000 | T52: 600000 | U52: 3 | V52: 629990 | W52: 2815 | X52: 224 | Y52: 303050 | Z52: 2026-08 | AA52: -0.0376 | AB52: 0.072 | AC52: 307450 | AD52: 155 | AE52: 396 | AF52: 83 | AG52: 2026-05-31 | AH52: 30.0553 | AI52: -95.8248 | AJ52: Houston | AK52: 34 | AL52: https://thegrandprairietx.com/
A53: hou-the-highlands | B53: houston | C53: The Highlands | D53: Caldwell Companies | E53: Montgomery | F53: Porter | G53: 77365 | H53: New Caney ISD | I53: 2300 | O53: 13 | P53: 18 | Q53: 45, 50, 55, 60, 65, 75 | R53: 343990 | S53: 459995 | T53: 750000 | U53: 49 | V53: 496509 | W53: 2390 | X53: 212 | Y53: 308025 | Z53: 2026-08 | AA53: -0.0147 | AB53: 0.1122 | AC53: 361250 | AD53: 158 | AE53: 256 | AF53: 80 | AG53: 2026-05-31 | AH53: 30.1135 | AI53: -95.2745 | AJ53: Houston | AK53: 25.1 | AL53: https://thehighlands.com/
A54: hou-the-woodlands-hills | B54: houston | C54: The Woodlands Hills | D54: Howard Hughes | E54: Montgomery | F54: Willis | G54: 77318 | H54: Willis ISD | I54: 2000 | O54: 9 | P54: 16 | Q54: 40, 45, 50, 55, 60, 65, 75 | R54: 293990 | S54: 491495 | T54: 684990 | U54: 34 | V54: 640000 | W54: 2956 | X54: 194 | Y54: 333902 | Z54: 2026-08 | AA54: -0.0139 | AB54: 0.1289 | AC54: 324900 | AD54: 163 | AE54: 199 | AF54: 103 | AG54: 2026-05-31 | AH54: 30.40053 | AI54: -95.50555 | AJ54: Houston | AK54: 45 | AL54: https://thewoodlandshills.com/ | AM54: New homes are available from the upper $200s to $800s.
A55: hou-towne-lake | B55: houston | C55: Towne Lake | D55: Caldwell Companies | E55: Harris | F55: Cypress | G55: 77433 | H55: Cy-Fair ISD | O55: 7 | P55: 7 | Q55: 55, 65, 90 | R55: 448600 | S55: 900000 | T55: 1200000 | U55: 1 | V55: 875000 | W55: 2872 | X55: 305 | Y55: 424653 | Z55: 2026-08 | AA55: -0.0127 | AB55: 0.1618 | AC55: 427790 | AD55: 175 | AE55: 677 | AF55: 58 | AG55: 2026-05-31 | AH55: 29.9453 | AI55: -95.7414 | AJ55: Houston | AK55: 25.7 | AL55: https://townelaketexas.com/
A56: hou-two-step-farm | B56: houston | C56: Two Step Farm | D56: Oxland Group | E56: Montgomery | F56: Montgomery | G56: 77316 | H56: Montgomery ISD | I56: 1860 | J56: 4000 | O56: 12 | P56: 21 | Q56: 35, 40, 42, 50, 60, 80 | R56: 287990 | S56: 417445 | T56: 900000 | U56: 56 | V56: 442450 | W56: 2298 | X56: 190 | Y56: 413912 | Z56: 2026-08 | AA56: -0.0244 | AB56: 0.1668 | AC56: 374990 | AD56: 162 | AE56: 505 | AF56: 88 | AG56: 2026-05-31 | AH56: 30.3062 | AI56: -95.6864 | AJ56: Houston | AK56: 42.2 | AL56: https://twostepfarm.com/ | AM56: from the mid $300s to $1M+
A57: hou-valencia | B57: houston | C57: Valencia | D57: Hillwood Communities | E57: Brazoria | F57: Manvel | G57: 77578 | H57: Alvin ISD | I57: 440 | J57: 938 | O57: 4 | P57: 10 | Q57: 45, 50, 60, 70 | R57: 370000 | S57: 495495 | T57: 700000 | U57: 30 | V57: 612400 | W57: 2912 | X57: 208 | Y57: 439597 | Z57: 2026-08 | AA57: -0.0248 | AB57: 0.1334 | AC57: 456000 | AD57: 176 | AE57: 243 | AF57: 117 | AG57: 2026-05-31 | AH57: 29.4854 | AI57: -95.3623 | AJ57: Houston | AK57: 19 | AL57: https://www.valenciabyhillwood.com/ | AM57: New home prices range from the $300s – $800s
A58: hou-wildrye | B58: houston | C58: Wildrye | D58: Land Tejas / Starwood Land | E58: Harris | F58: Waller | G58: 77484 | H58: Waller ISD | I58: 528 | J58: 1400 | O58: 8 | P58: 10 | Q58: 40, 45, 55, 60 | R58: 249990 | S58: 349490 | T58: 459990 | U58: 12 | V58: 374995 | W58: 2382 | X58: 156 | Y58: 353605 | Z58: 2026-08 | AA58: -0.0117 | AB58: 0.0931 | AC58: 290000 | AD58: 145 | AE58: 235 | AF58: 81.5 | AG58: 2026-05-31 | AH58: 30.0835 | AI58: -95.9281 | AJ58: Houston | AK58: 40.2 | AL58: https://livewildrye.com/ | AM58: NEW HOMES IN WALLER, TX FROM THE HIGH $200S-$600S
A59: hou-woodforest | B59: houston | C59: Woodforest | D59: Johnson Development | E59: Montgomery | F59: Montgomery | G59: 77316 | H59: Conroe ISD | I59: 3000 | J59: 5500 | O59: 4 | P59: 6 | Q59: 60 | R59: 289990 | S59: 479990 | T59: 1400000 | U59: 7 | V59: 417990 | W59: 1809 | X59: 215 | Y59: 413912 | Z59: 2026-08 | AA59: -0.0244 | AB59: 0.1668 | AC59: 374990 | AD59: 162 | AE59: 505 | AF59: 88 | AG59: 2026-05-31 | AH59: 30.28006 | AI59: -95.56639 | AJ59: Houston | AK59: 37.8 | AL59: https://www.woodforesttx.com/ | AM59: homes are priced from the low $300,000s
A60: hou-woodhavyn | B60: houston | C60: Woodhavyn | D60: Shea Homes | E60: Montgomery | F60: Magnolia | G60: 77354 | H60: Magnolia ISD | I60: 300 | O60: 3 | P60: 6 | Q60: 40, 50, 60 | R60: 320000 | S60: 404995 | T60: 499995 | U60: 19 | V60: 439990 | W60: 2471 | X60: 197 | Y60: 378164 | Z60: 2026-08 | AA60: -0.0149 | AB60: 0.1508 | AC60: 338065 | AD60: 164 | AE60: 359 | AF60: 80.5 | AG60: 2026-05-31 | AH60: 30.2079 | AI60: -95.643 | AJ60: Houston | AK60: 35 | AL60: https://woodhavyn.com/
A61: hou-woodsons-reserve | B61: houston | C61: Woodson's Reserve | D61: Toll Brothers | E61: Montgomery | F61: Spring | G61: 77386 | H61: Conroe ISD | I61: 692 | O61: 2 | P61: 8 | Q61: 45, 50, 60, 70, 80 | R61: 404995 | S61: 570448 | T61: 820900 | U61: 18 | V61: 697100 | W61: 3448 | X61: 204 | Y61: 367501 | Z61: 2026-08 | AA61: -0.01 | AB61: 0.1563 | AC61: 435000 | AD61: 169 | AE61: 263 | AF61: 35 | AG61: 2026-05-31 | AH61: 30.1003 | AI61: -95.3565 | AJ61: Houston | AK61: 23.5 | AL61: https://woodsonsreserve.com/ | AM61: New Homes Starting In The High $300s
A62: hou-balmoral | B62: houston | C62: Balmoral | D62: Land Tejas / Starwood Land | E62: Harris | F62: Humble | G62: 77346 | H62: Humble ISD | I62: 750 | O62: 1 | P62: 1 | R62: 302990 | S62: 302990 | T62: 302990 | U62: 0 | Y62: 308933 | Z62: 2026-08 | AA62: -0.0162 | AB62: 0.1041 | AC62: 315000 | AD62: 136 | AE62: 267 | AF62: 53 | AG62: 2026-05-31 | AH62: 29.992 | AI62: -95.1773 | AJ62: Houston | AK62: 19.7 | AL62: https://balmoralhouston.com/ | AM62: Balmoral offers homes from the $200's by leading Houston builders.
A63: hou-beacon-hill | B63: houston | C63: Beacon Hill | D63: Wolff Companies | E63: Waller | F63: Waller | H63: Waller ISD | I63: 587 | J63: 870 | K63: 2021 | O63: 1 | P63: 1 | R63: 240000 | S63: 240000 | T63: 240000 | U63: 0 | AL63: https://wolffcompanies.com/current-projects/beacon-hill/ | AM63: priced from $240s to $470s
A64: hou-breckenridge-forest | B64: houston | C64: Breckenridge Forest | D64: D.R. Horton | F64: Spring | L64: 27 | M64: 541 | O64: 1 | P64: 1 | U64: 0
A65: hou-caldwell-crossing | B65: houston | C65: Caldwell Crossing (formerly Caldwell Ranch) | D65: D.R. Horton | E65: Brazoria | F65: Iowa Colony | G65: 77583 | H65: Alvin ISD | L65: 47 | M65: 382 | O65: 1 | P65: 2 | R65: 303490 | S65: 321245 | T65: 339000 | U65: 0 | Y65: 317552 | Z65: 2026-08 | AA65: -0.0444 | AB65: 0.053 | AC65: 315000 | AD65: 155 | AE65: 248 | AF65: 70 | AG65: 2026-05-31 | AH65: 29.3742 | AI65: -95.4538 | AJ65: Houston | AK65: 27.2 | AL65: https://www.drhorton.com/texas/houston/iowa-colony/caldwell-crossing | AM65: From $303,490
A66: hou-cane-island | B66: houston | C66: Cane Island | D66: Rise Communities | E66: Harris | F66: Katy | G66: 77493 | H66: Katy ISD | I66: 1100 | L66: 46 | M66: 228 | O66: 1 | P66: 1 | Q66: 100 | R66: 1750000 | S66: 1750000 | T66: 1750000 | U66: 0 | Y66: 336733 | Z66: 2026-08 | AA66: -0.0396 | AB66: 0.0929 | AC66: 340000 | AD66: 159 | AE66: 735 | AF66: 67 | AG66: 2026-05-31 | AH66: 29.8532 | AI66: -95.8315 | AJ66: Houston | AK66: 28.4 | AL66: https://caneisland.com/ | AM66: incredible new homes from the $400s to the millions
A67: hou-cross-creek-ranch | B67: houston | C67: Cross Creek Ranch | D67: Johnson Development | E67: Fort Bend | F67: Fulshear | I67: 3200 | L67: 49 | M67: 376 | O67: 0 | P67: 0 | U67: 0 | AL67: https://www.johnsondevelopment.com/fulshear-tx/mpc_cross_creek_ranch
A68: hou-dellrose | B68: houston | C68: Dellrose | D68: Precedent Land Company | E68: Harris | F68: Hockley | G68: 77447 | I68: 600 | O68: 5 | P68: 5 | R68: 300000 | S68: 300000 | T68: 300000 | U68: 0 | Y68: 303050 | Z68: 2026-08 | AA68: -0.0376 | AB68: 0.072 | AC68: 307450 | AD68: 155 | AE68: 396 | AF68: 83 | AG68: 2026-05-31 | AH68: 30.0553 | AI68: -95.8248 | AJ68: Houston | AK68: 34 | AL68: https://dellroseliving.com/ | AM68: From the High $200's to the $500's
A69: hou-freeman-ranch | B69: houston | C69: Freeman Ranch | F69: Katy | O69: 1 | P69: 1 | R69: 288900 | S69: 288900 | T69: 288900 | U69: 0
A70: hou-imperial | B70: houston | C70: Imperial | D70: Johnson Development | E70: Fort Bend | F70: Sugar Land | G70: 77498 | H70: Fort Bend ISD | I70: 720 | O70: 1 | P70: 1 | R70: 579990 | S70: 579990 | T70: 579990 | U70: 0 | Y70: 321100 | Z70: 2026-08 | AA70: -0.0192 | AB70: 0.1777 | AC70: 302500 | AD70: 152 | AE70: 88 | AF70: 33.5 | AG70: 2026-05-31 | AH70: 29.641 | AI70: -95.6558 | AJ70: Houston | AK70: 19 | AL70: https://www.imperialsugarland.com/ | AM70: priced from the $700,000s
A71: hou-magnolia-woods | B71: houston | C71: Magnolia Woods | D71: LGI Homes | E71: Montgomery | F71: Magnolia | G71: 77354 | H71: Magnolia ISD | J71: 1300 | K71: 2025 | O71: 2 | P71: 2 | Q71: 70 | R71: 282900 | S71: 398900 | T71: 514900 | U71: 0 | Y71: 378164 | Z71: 2026-08 | AA71: -0.0149 | AB71: 0.1508 | AC71: 338065 | AD71: 164 | AE71: 359 | AF71: 80.5 | AG71: 2026-05-31 | AH71: 30.2079 | AI71: -95.643 | AJ71: Houston | AK71: 35 | AL71: https://www.lgihomes.com/texas/houston/magnolia-woods
A72: hou-mirabella | B72: houston | C72: Mirabella | D72: Century Communities | E72: Waller | F72: Brookshire | G72: 77423 | O72: 1 | P72: 2 | R72: 200000 | S72: 200000 | T72: 200000 | U72: 0 | Y72: 365601 | Z72: 2026-08 | AA72: -0.0282 | AB72: 0.1051 | AC72: 334990 | AD72: 159 | AE72: 229 | AF72: 76.5 | AG72: 2026-05-31 | AH72: 29.8331 | AI72: -95.9869 | AJ72: Houston | AK72: 37.3
A73: hou-northgrove | B73: houston | C73: NorthGrove | D73: Toll Brothers | E73: Montgomery | F73: Magnolia | G73: 77354 | H73: Magnolia ISD | O73: 5 | P73: 5 | U73: 0 | Y73: 378164 | Z73: 2026-08 | AA73: -0.0149 | AB73: 0.1508 | AC73: 338065 | AD73: 164 | AE73: 359 | AF73: 80.5 | AG73: 2026-05-31 | AH73: 30.2079 | AI73: -95.643 | AJ73: Houston | AK73: 35 | AL73: https://northgrovetx.com/
A74: hou-riverstone | B74: houston | C74: Riverstone | D74: Johnson Development | E74: Fort Bend | F74: Sugar Land | G74: 77459, 77479 | H74: Fort Bend ISD | O74: 1 | P74: 1 | R74: 1590000 | S74: 1590000 | T74: 1590000 | U74: 0 | Y74: 395000 | Z74: 2026-08 | AA74: -0.0155 | AB74: 0.1512 | AC74: 410000 | AD74: 163 | AE74: 338 | AF74: 78 | AG74: 2026-05-31 | AH74: 29.5264 | AI74: -95.5338 | AJ74: Houston | AK74: 18.9 | AL74: https://www.riverstone.com/ | AM74: Homes are priced from $1.49 million.
A75: hou-tavola | B75: houston | C75: Tavola | D75: Friendswood Development Company | E75: Montgomery | F75: New Caney | G75: 77357 | H75: New Caney ISD | L75: 31t | M75: 248 | O75: 4 | P75: 9 | Q75: 40, 50, 55, 65 | R75: 210000 | S75: 320000 | T75: 490000 | U75: 0 | Y75: 260830 | Z75: 2026-08 | AA75: -0.0305 | AB75: 0.0279 | AC75: 264096 | AD75: 146 | AE75: 251 | AF75: 78 | AG75: 2026-05-31 | AH75: 30.1569 | AI75: -95.1811 | AJ75: Houston | AK75: 29.6 | AL75: https://friendswooddevelopment.com/communities/master-planned/tavola
A76: hou-the-woodlands | B76: houston | C76: The Woodlands | D76: Howard Hughes | E76: Montgomery | F76: The Woodlands | G76: 77380, 77389 | H76: Conroe ISD, Magnolia ISD, Tomball ISD | I76: 28545 | K76: 1974 | O76: 1 | P76: 1 | U76: 0 | Y76: 392675 | Z76: 2026-08 | AA76: 0.0116 | AB76: 0.2549 | AC76: 435000 | AD76: 198 | AE76: 79 | AF76: 37 | AG76: 2026-05-31 | AH76: 30.137 | AI76: -95.4684 | AJ76: Houston | AK76: 26.7 | AL76: https://www.thewoodlands.com/
A77: hou-trinity-landing | B77: houston | C77: Trinity Landing | D77: M/I Homes and Meritage Homes | E77: Liberty | F77: Dayton | G77: 77535 | H77: Dayton ISD | I77: 309 | J77: 1000 | O77: 1 | P77: 1 | R77: 250000 | S77: 250000 | T77: 250000 | U77: 0 | Y77: 323731 | Z77: 2026-08 | AA77: -0.0068 | AB77: 0.1602 | AC77: 331281 | AD77: 161 | AE77: 215 | AF77: 157 | AG77: 2026-05-31 | AH77: 30.0548 | AI77: -94.9223 | AJ77: Houston | AK77: 33.6
A78: hou-valley-ranch | B78: houston | C78: Valley Ranch (Azalea District) | D78: The Signorelli Company | E78: Montgomery | F78: New Caney | G78: 77365 | H78: New Caney ISD | I78: 1400 | O78: 1 | P78: 2 | U78: 0 | Y78: 308025 | Z78: 2026-08 | AA78: -0.0147 | AB78: 0.1122 | AC78: 361250 | AD78: 158 | AE78: 256 | AF78: 80 | AG78: 2026-05-31 | AH78: 30.1135 | AI78: -95.2745 | AJ78: Houston | AK78: 25.1 | AL78: https://www.valley-ranch.com/
A79: dfw-aster-park | B79: dfw | C79: Aster Park | D79: Land Tejas / Starwood Land | E79: Collin | F79: McKinney | G79: 75071 | H79: Prosper ISD | I79: 414 | J79: 1100 | O79: 6 | P79: 9 | Q79: 40, 50, 60, 70 | R79: 451990 | S79: 598990 | T79: 749995 | U79: 18 | V79: 797995 | W79: 3466 | X79: 239 | Y79: 474418 | Z79: 2026-08 | AA79: -0.0615 | AB79: 0.1105 | AC79: 449995 | AD79: 192 | AE79: 630 | AF79: 72 | AG79: 2026-05-31 | AH79: 33.2458 | AI79: -96.6307 | AJ79: Dallas | AK79: 33.8 | AL79: https://asterparktx.com/
A80: dfw-cambridge-crossing | B80: dfw | C80: Cambridge Crossing | D80: The Cambridge Companies | E80: Collin | F80: Celina | G80: 75009 | H80: Celina ISD | I80: 639 | K80: 2020 | O80: 4 | P80: 5 | Q80: 50, 60, 74 | R80: 490000 | S80: 585990 | T80: 810000 | U80: 21 | V80: 699990 | W80: 3232 | X80: 225 | Y80: 515792 | Z80: 2026-08 | AA80: -0.0923 | AB80: 0.1076 | AC80: 480000 | AD80: 187 | AE80: 401 | AF80: 119 | AG80: 2026-05-31 | AH80: 33.3389 | AI80: -96.753 | AJ80: Dallas | AK80: 38.9 | AL80: https://cambridgecrossingcelina.com/
A81: dfw-castle-hills | B81: dfw | C81: Castle Hills | D81: Bright Realty | E81: Denton | F81: Lewisville | G81: 75056 | H81: Lewisville ISD | I81: 2900 | K81: 1998 | O81: 5 | P81: 5 | R81: 600000 | S81: 600000 | T81: 600000 | U81: 5 | V81: 643000 | W81: 2428 | X81: 262 | Y81: 484938 | Z81: 2026-08 | AA81: -0.027 | AB81: 0.1788 | AC81: 525350 | AD81: 223 | AE81: 161 | AF81: 36 | AG81: 2026-05-31 | AH81: 33.05975 | AI81: -96.89173 | AJ81: Dallas | AK81: 20.3 | AL81: https://castlehills.com/
A82: dfw-chisholm-trail-ranch | B82: dfw | C82: Chisholm Trail Ranch | D82: Walton Development and Management | E82: Tarrant | F82: Fort Worth | G82: 76036 | H82: Crowley ISD | I82: 600 | J82: 1000 | O82: 2 | P82: 2 | Q82: 50 | R82: 332990 | S82: 332990 | T82: 332990 | U82: 5 | V82: 415490 | W82: 2938 | X82: 141 | Y82: 314417 | Z82: 2026-08 | AA82: -0.0263 | AB82: 0.0625 | AC82: 330000 | AD82: 171 | AE82: 279 | AF82: 85 | AG82: 2026-05-31 | AH82: 32.571 | AI82: -97.4213 | AJ82: Fort Worth | AK82: 13.8 | AL82: https://ctr-ftw.com/
A83: dfw-creekside-royse-city | B83: dfw | C83: Creekside | D83: Land Tejas / Starwood Land | E83: Rockwall | F83: Royse City | G83: 75189 | H83: Royse City ISD | I83: 287 | J83: 525 | O83: 4 | P83: 4 | Q83: 40, 50, 60 | R83: 268990 | S83: 299494 | T83: 304900 | U83: 17 | V83: 328650 | W83: 2034 | X83: 160 | Y83: 316660 | Z83: 2026-08 | AA83: -0.0447 | AB83: 0.0295 | AC83: 336995 | AD83: 154 | AE83: 298 | AF83: 99 | AG83: 2026-05-31 | AH83: 32.9421 | AI83: -96.3117 | AJ83: Dallas | AK83: 30.4 | AL83: https://creeksideroysecity.com/ | AM83: Starting in the High $200s
A84: dfw-devonshire | B84: dfw | C84: Devonshire | D84: Haynes Development | E84: Kaufman | F84: Forney | G84: 75126 | H84: Forney ISD | I84: 925 | J84: 3000 | K84: 2008 | L84: 45 | M84: 395 | O84: 8 | P84: 13 | Q84: 40, 45, 50, 55, 60, 65 | R84: 280000 | S84: 370000 | T84: 500000 | U84: 13 | V84: 425000 | W84: 2452 | X84: 177 | Y84: 307261 | Z84: 2026-08 | AA84: -0.051 | AB84: -0.0142 | AC84: 330000 | AD84: 152 | AE84: 434 | AF84: 82 | AG84: 2026-05-31 | AH84: 32.77723 | AI84: -96.43646 | AJ84: Dallas | AK84: 20.9 | AL84: https://www.devonshireliving.com/ | AM84: prices from the $300s to $600s
A85: dfw-eastridge | B85: dfw | C85: Eastridge | D85: Green Brick Partners in partnership with Meritage Homes | E85: Collin | F85: McKinney | G85: 75071 | H85: McKinney ISD | I85: 547 | J85: 2400 | L85: 39 | M85: 427 | O85: 2 | P85: 2 | Q85: 40, 50 | R85: 274990 | S85: 274990 | T85: 274990 | U85: 5 | V85: 309990 | W85: 1703 | X85: 181 | Y85: 474418 | Z85: 2026-08 | AA85: -0.0615 | AB85: 0.1105 | AC85: 449995 | AD85: 192 | AE85: 630 | AF85: 72 | AG85: 2026-05-31 | AH85: 33.2458 | AI85: -96.6307 | AJ85: Dallas | AK85: 33.8 | AL85: https://eastridgetx.com/ | AM85: homes ranging from the low $300s to high $400s
A86: dfw-elevon | B86: dfw | C86: Elevon | D86: MA Partners | E86: Collin | F86: Lavon | G86: 75166, 75173 | H86: Community ISD | J86: 4000 | L86: 43 | M86: 407 | O86: 11 | P86: 15 | Q86: 30, 40, 45, 50, 60 | R86: 245990 | S86: 290000 | T86: 580000 | U86: 40 | V86: 342220 | W86: 2156 | X86: 168 | Y86: 340815 | Z86: 2026-08 | AA86: -0.0772 | AB86: -0.0434 | AC86: 337490 | AD86: 162 | AE86: 182 | AF86: 78 | AG86: 2026-05-31 | AH86: 33.02777 | AI86: -96.41303 | AJ86: Dallas | AK86: 28.2 | AL86: https://elevontx.com/
A87: dfw-fields | B87: dfw | C87: Fields | D87: Hunt Realty / Karahan | E87: Denton | F87: Frisco | G87: 75033 | H87: Frisco ISD | I87: 2500 | O87: 11 | P87: 2 | Q87: 50, 60 | R87: 700000 | S87: 2100000 | T87: 3500000 | U87: 1 | V87: 899990 | W87: 3687 | X87: 244 | Y87: 649110 | Z87: 2026-08 | AA87: -0.032 | AB87: 0.1701 | AC87: 713250 | AD87: 224 | AE87: 170 | AF87: 38.5 | AG87: 2026-05-31 | AH87: 33.1848 | AI87: -96.8443 | AJ87: Dallas | AK87: 28.3 | AL87: https://fieldsfrisco.com/
A88: dfw-furst-ranch | B88: dfw | C88: Furst Ranch | D88: Land Tejas / Starwood Land | E88: Denton | F88: Flower Mound / Argyle / Bartonville | G88: 76226 | H88: Argyle ISD | I88: 2000 | O88: 6 | P88: 9 | Q88: 50, 60, 70, 80 | R88: 598990 | S88: 769000 | T88: 1125995 | U88: 30 | V88: 902550 | W88: 3451 | X88: 258 | Y88: 575122 | Z88: 2026-08 | AA88: -0.0182 | AB88: 0.1332 | AC88: 574000 | AD88: 202 | AE88: 285 | AF88: 58 | AG88: 2026-05-31 | AH88: 33.1055 | AI88: -97.1775 | AJ88: Fort Worth | AK88: 25.8
A89: dfw-gateway-parks | B89: dfw | C89: Gateway Parks | D89: Gateway Holdings, LLC | E89: Kaufman | F89: Forney | G89: 75126 | H89: Forney ISD | I89: 540 | J89: 1850 | O89: 6 | P89: 6 | Q89: 50, 60 | R89: 200000 | S89: 359000 | T89: 500000 | U89: 11 | V89: 359000 | W89: 2243 | X89: 158 | Y89: 307261 | Z89: 2026-08 | AA89: -0.051 | AB89: -0.0142 | AC89: 330000 | AD89: 152 | AE89: 434 | AF89: 82 | AG89: 2026-05-31 | AH89: 32.7426 | AI89: -96.4529 | AJ89: Dallas | AK89: 20.1 | AL89: https://www.gatewayforney.com/homes/gateway-parks/ | AM89: priced from the mid $200s
A90: dfw-goodland | B90: dfw | C90: Goodland | D90: Provident Realty Advisors | E90: Ellis | F90: Venus | G90: 76084 | H90: Midlothian ISD | I90: 5000 | O90: 4 | P90: 8 | Q90: 40, 50, 53, 60 | R90: 382990 | S90: 416495 | T90: 552990 | U90: 31 | V90: 594990 | W90: 2730 | X90: 205 | Y90: 390008 | Z90: 2026-08 | AA90: -0.0172 | AB90: 0.0826 | AC90: 425000 | AD90: 188 | AE90: 103 | AF90: 70 | AG90: 2026-05-31 | AH90: 32.49068 | AI90: -97.08316 | AJ90: Fort Worth | AK90: 23.3 | AL90: https://goodlandtx.com/ | AM90: New homes from the mid $300s are now available in our Prairie Ridge and Feather Grass villages.
A91: dfw-harvest | B91: dfw | C91: Harvest by Hillwood | D91: Hillwood Communities | E91: Denton | F91: Argyle | G91: 76226 | H91: Argyle ISD | L91: 44t | M91: 417 | O91: 2 | P91: 2 | Q91: 35 | R91: 300000 | S91: 364500 | T91: 429000 | U91: 8 | V91: 444000 | W91: 2172 | X91: 208 | Y91: 575122 | Z91: 2026-08 | AA91: -0.0182 | AB91: 0.1332 | AC91: 574000 | AD91: 202 | AE91: 285 | AF91: 58 | AG91: 2026-05-31 | AH91: 33.11514 | AI91: -97.22449 | AJ91: Fort Worth | AK91: 25.6 | AL91: https://www.harvestbyhillwood.com/
A92: dfw-heartland | B92: dfw | C92: Heartland | D92: Huffines Communities | E92: Kaufman | F92: Heartland | G92: 75114, 75126 | H92: Crandall ISD | I92: 1600 | O92: 10 | P92: 12 | Q92: 40, 50, 60 | R92: 242990 | S92: 292990 | T92: 344990 | U92: 29 | V92: 354990 | W92: 2203 | X92: 168 | Y92: 254321 | Z92: 2026-08 | AA92: -0.0404 | AB92: 0.0017 | AC92: 260437.5 | AD92: 153 | AE92: 202 | AF92: 68.5 | AG92: 2026-05-31 | AH92: 32.66943 | AI92: -96.45561 | AJ92: Dallas | AK92: 21.2 | AL92: https://heartlandtexas.com/ | AM92: Homes from the $240s-$610s
A93: dfw-inspiration | B93: dfw | C93: Inspiration | D93: Huffines Communities | E93: Collin | F93: St. Paul | G93: 75098 | H93: Wylie ISD | I93: 638 | O93: 5 | P93: 6 | Q93: 50, 80 | R93: 455990 | S93: 599000 | T93: 689990 | U93: 15 | V93: 689950 | W93: 3497 | X93: 222 | Y93: 415460 | Z93: 2026-08 | AA93: -0.0554 | AB93: 0.0964 | AC93: 449950 | AD93: 191 | AE93: 202 | AF93: 53 | AG93: 2026-05-31 | AH93: 33.07143 | AI93: -96.55656 | AJ93: Dallas | AK93: 24.7 | AL93: https://inspirationtexas.com/
A94: dfw-karis | B94: dfw | C94: Karis | D94: The Nehemiah Company | E94: Tarrant | F94: Crowley | G94: 76036 | H94: Crowley ISD | I94: 565 | J94: 2025 | O94: 3 | P94: 4 | Q94: 35, 50, 60 | R94: 265990 | S94: 386188 | T94: 426990 | U94: 6 | V94: 319490 | W94: 2064 | X94: 164 | Y94: 314417 | Z94: 2026-08 | AA94: -0.0263 | AB94: 0.0625 | AC94: 330000 | AD94: 171 | AE94: 279 | AF94: 85 | AG94: 2026-05-31 | AH94: 32.59164 | AI94: -97.36096 | AJ94: Fort Worth | AK94: 11.5 | AL94: https://www.karistx.com/
A95: dfw-lakehaven | B95: dfw | C95: Lakehaven | D95: Green Brick Partners | E95: Collin | F95: Farmersville | G95: 75442 | H95: Farmersville ISD | L95: 48t | M95: 375 | O95: 2 | P95: 2 | Q95: 40, 50, 60 | R95: 239990 | S95: 239990 | T95: 239990 | U95: 5 | V95: 329990 | W95: 2653 | X95: 128 | Y95: 333668 | Z95: 2026-08 | AA95: -0.0412 | AB95: 0.0838 | AC95: 295421.5 | AD95: 142 | AE95: 110 | AF95: 146.5 | AG95: 2026-05-31 | AH95: 33.1761 | AI95: -96.3464 | AJ95: Dallas | AK95: 38 | AL95: https://lakehaventx.com/ | AM95: homes starting in the mid $200s
A96: dfw-landmark-by-hillwood | B96: dfw | C96: Landmark by Hillwood | D96: Hillwood Communities | E96: Denton | F96: Denton | G96: 76207, 76226 | H96: Denton ISD | I96: 3200 | O96: 9 | P96: 10 | Q96: 40, 45, 50, 60, 70 | R96: 371990 | S96: 500990 | T96: 706900 | U96: 33 | V96: 572347 | W96: 2460 | X96: 222 | Y96: 347760 | Z96: 2026-08 | AA96: -0.0444 | AB96: 0.0594 | AC96: 423500 | AD96: 219 | AE96: 91 | AF96: 50 | AG96: 2026-05-31 | AH96: 33.222 | AI96: -97.1761 | AJ96: Fort Worth | AK96: 33.5 | AL96: https://www.landmarkbyhillwood.com/ | AM96: New homes from high $300s to $1M+
A97: dfw-legacy-hills | B97: dfw | C97: Legacy Hills | D97: Centurion American | E97: Collin | F97: Celina | G97: 75009 | H97: Celina ISD | I97: 3200 | O97: 12 | P97: 21 | Q97: 40, 50, 60 | R97: 320999 | S97: 397470 | T97: 516990 | U97: 67 | V97: 459990 | W97: 2372 | X97: 188 | Y97: 515792 | Z97: 2026-08 | AA97: -0.0923 | AB97: 0.1076 | AC97: 480000 | AD97: 187 | AE97: 401 | AF97: 119 | AG97: 2026-05-31 | AH97: 33.35091 | AI97: -96.8235 | AJ97: Dallas | AK97: 39.7 | AL97: https://www.legacyhillscelina.com/
A98: dfw-liberty | B98: dfw | C98: Liberty by Hillwood | D98: Hillwood Communities | E98: Collin | F98: Melissa | G98: 75454 | H98: Melissa ISD | I98: 535 | K98: 2003 | O98: 1 | P98: 1 | R98: 499990 | S98: 499990 | T98: 499990 | U98: 5 | V98: 649547 | W98: 3487 | X98: 182 | Y98: 422689 | Z98: 2026-08 | AA98: -0.0575 | AB98: 0.079 | AC98: 435450 | AD98: 182 | AE98: 142 | AF98: 65 | AG98: 2026-05-31 | AH98: 33.29153 | AI98: -96.55353 | AJ98: Dallas | AK98: 38.3 | AL98: https://www.libertybyhillwood.com/
A99: dfw-light-farms | B99: dfw | C99: Light Farms | D99: Republic Property Group | E99: Collin | F99: Celina | G99: 75009 | H99: Prosper ISD | I99: 1070 | O99: 1 | P99: 2 | Q99: 40, 80 | R99: 529000 | S99: 864000 | T99: 1199000 | U99: 4 | V99: 627000 | W99: 2935 | X99: 212 | Y99: 515792 | Z99: 2026-08 | AA99: -0.0923 | AB99: 0.1076 | AC99: 480000 | AD99: 187 | AE99: 401 | AF99: 119 | AG99: 2026-05-31 | AH99: 33.28159 | AI99: -96.79369 | AJ99: Dallas | AK99: 34.9 | AL99: https://lightfarmstx.com/ | AM99: $473,000+
A100: dfw-madero | B100: dfw | C100: Madero | D100: Green Brick Partners | E100: Denton | F100: Haslet | G100: 76052 | H100: Northwest ISD | K100: 2022 | O100: 1 | P100: 2 | Q100: 50, 60 | R100: 334990 | S100: 334990 | T100: 334990 | U100: 5 | V100: 362990 | W100: 2131 | X100: 170 | Y100: 391465 | Z100: 2026-08 | AA100: -0.0263 | AB100: 0.0418 | AC100: 390000 | AD100: 174 | AE100: 324 | AF100: 59 | AG100: 2026-05-31 | AH100: 32.9791 | AI100: -97.3713 | AJ100: Fort Worth | AK100: 15.6 | AL100: https://trophysignaturehomes.com/communities/dallas-ft-worth/haslet/madero | AM100: PRICED FROM $334,990 - $463,990
...

Sheet Builders
A1: builder_id | B1: market | C1: builder | D1: rolodex_id | E1: rolodex_section | F1: rolodex_repetition | G1: rolodex_printer_fit | H1: rolodex_track_record | I1: sec_filer | J1: n_communities | K1: counties | L1: lot_widths_ft | M1: from_min | N1: from_median | O1: from_max | P1: qmi_n | Q1: qmi_median_price | R1: qmi_median_sqft | S1: qmi_median_ppsf | T1: homes_closed | U1: homes_closed_year | V1: homes_closed_scope
A2: b-houston-perry-homes | B2: houston | C2: Perry Homes | D2: HOU-013 | E2: National builder | F2: Yes | G2: No | H2: No | J2: 34 | K2: Brazoria, Chambers, Fort Bend, Galveston, Harris, Montgomery, Waller | L2: 40, 45, 50, 55, 60, 65, 70, 75, 80 | M2: 310000 | N2: 490000 | O2: 940000 | P2: 146 | Q2: 574900 | R2: 2724 | S2: 206 | T2: 1809 | U2: 2025 | V2: BUILDER Local Leaders 2026, Houston metro
A3: b-houston-david-weekley-homes | B3: houston | C3: David Weekley Homes | D3: HOU-023 | E3: National builder | F3: Yes | G3: No | H3: No | J3: 29 | K3: Brazoria, Chambers, Fort Bend, Galveston, Harris, Montgomery, Waller | L3: 35, 40, 42, 45, 50, 55, 60, 65, 70, 80 | M3: 287990 | N3: 397990 | O3: 750000 | P3: 220 | Q3: 464962 | R3: 2450 | S3: 197
A4: b-houston-highland-homes | B4: houston | C4: Highland Homes | D4: HOU-168 | E4: Two of three counts | F4: Yes | G4: Partly | H4: No | J4: 27 | K4: Brazoria, Chambers, Fort Bend, Galveston, Harris, Montgomery, Waller | L4: 40, 42, 45, 50, 55, 60, 65, 70, 80 | M4: 304990 | N4: 465000 | O4: 800000 | P4: 100 | Q4: 479995 | R4: 2466 | S4: 196 | T4: 968 | U4: 2025 | V4: BUILDER Local Leaders 2026, Houston metro
A5: b-houston-westin-homes | B5: houston | C5: Westin Homes | D5: HOU-068 | E5: Two of three counts | F5: Yes | G5: Partly | H5: No | J5: 26 | K5: Brazoria, Fort Bend, Galveston, Harris, Montgomery, Waller | L5: 40, 45, 50, 55, 60, 65, 70 | M5: 349623 | N5: 539511 | O5: 767785 | P5: 160 | Q5: 559779 | R5: 3332 | S5: 172 | T5: 1062 | U5: 2025 | V5: Houston and Austin
A6: b-houston-chesmar-homes | B6: houston | C6: Chesmar Homes | D6: HOU-045 | E6: Two of three counts | F6: Partly | G6: Partly | H6: No | J6: 23 | K6: Brazoria, Chambers, Fort Bend, Harris, Montgomery, Waller | L6: 40, 42, 45, 50, 55, 60, 65, 70 | M6: 269990 | N6: 339995 | O6: 518990 | P6: 0 | T6: 1087 | U6: 2025 | V6: BUILDER Local Leaders 2026, Houston metro, Sekisui House U.S. across its Houston brands
A7: b-houston-lennar | B7: houston | C7: Lennar | D7: HOU-166 | E7: Lennar and the firms it owns | F7: Yes | G7: No | H7: Yes | I7: Lennar | J7: 19 | K7: Brazoria, Fort Bend, Galveston, Harris, Liberty, Montgomery, Waller | L7: 40, 45, 50, 55, 60, 65 | M7: 193991 | N7: 272490 | O7: 400000 | P7: 107 | Q7: 291990 | R7: 1975 | S7: 145 | T7: 6362 | U7: 2025 | V7: BUILDER Local Leaders 2026, Houston metro
A8: b-houston-beazer-homes | B8: houston | C8: Beazer Homes | D8: HOU-201 | E8: National builder | F8: Yes | G8: No | H8: No | I8: Beazer Homes | J8: 17 | K8: Brazoria, Fort Bend, Galveston, Harris, Montgomery, Waller | L8: 40, 45, 50, 55, 60, 65 | M8: 281990 | N8: 349067 | O8: 574273 | P8: 51 | Q8: 396439 | R8: 2344 | S8: 190
A9: b-houston-coventry-homes | B9: houston | C9: Coventry Homes | D9: HOU-033 | E9: Two of three counts | F9: Partly | G9: Partly | H9: No | I9: Dream Finders Homes | J9: 17 | K9: Brazoria, Fort Bend, Galveston, Harris, Liberty, Montgomery | L9: 40, 45, 50, 55, 60, 65, 70, 75 | M9: 270990 | N9: 417490 | O9: 964990 | P9: 93 | Q9: 474990 | R9: 2586 | S9: 191 | T9: 1048 | U9: 2025 | V9: BUILDER Local Leaders 2026, Houston metro, Dream Finders Homes, the parent
A10: b-houston-castlerock-communities | B10: houston | C10: CastleRock Communities | D10: HOU-022 | E10: Two of three counts | F10: Yes | G10: Partly | H10: No | J10: 16 | K10: Brazoria, Fort Bend, Galveston, Harris, Liberty, Montgomery, Waller | L10: 40 | M10: 200000 | N10: 244995 | O10: 280000 | P10: 11 | Q10: 289037 | R10: 1915 | S10: 150 | T10: 1465 | U10: 2025 | V10: company-wide
A11: b-houston-newmark-homes | B11: houston | C11: Newmark Homes | D11: HOU-069 | E11: Two of three counts | F11: Partly | G11: Partly | H11: No | J11: 13 | K11: Brazoria, Fort Bend, Harris, Montgomery, Waller | L11: 40, 45, 50, 60, 65, 70 | M11: 300000 | N11: 420990 | O11: 784990 | P11: 59 | Q11: 496554 | R11: 2695 | S11: 200 | T11: 483 | U11: 2025 | V11: Houston and Austin
A12: b-houston-d-r-horton | B12: houston | C12: D.R. Horton | D12: HOU-132 | E12: National builder | F12: Yes | G12: No | H12: Yes | I12: D.R. Horton | J12: 11 | K12: Brazoria, Fort Bend, Galveston, Harris, Liberty, Montgomery, Waller | L12: 50, 60 | M12: 219990 | N12: 287995 | O12: 395990 | P12: 38 | Q12: 299990 | R12: 2031 | S12: 156 | T12: 4925 | U12: 2025 | V12: BUILDER Local Leaders 2026, Houston metro
A13: b-houston-drees-custom-homes | B13: houston | C13: Drees Custom Homes | D13: HOU-202 | E13: National builder | F13: Partly | G13: No | H13: No | J13: 11 | K13: Brazoria, Fort Bend, Galveston, Harris, Montgomery, Waller | L13: 35, 45, 55, 60, 70, 80 | M13: 389900 | N13: 590000 | O13: 730000 | P13: 10 | Q13: 604990 | R13: 2797 | S13: 204
A14: b-houston-drb-homes | B14: houston | C14: DRB Homes | D14: HOU-034 | E14: National builder | F14: Partly | G14: No | H14: No | J14: 10 | K14: Brazoria, Fort Bend, Harris, Liberty, Montgomery, Waller | L14: 50, 60 | M14: 232990 | N14: 297490 | O14: 419990 | P14: 7 | Q14: 339990 | R14: 1932 | S14: 168
A15: b-houston-j-patrick-homes | B15: houston | C15: J. Patrick Homes | D15: HOU-067 | E15: Two of three counts | F15: Partly | G15: Partly | H15: No | J15: 10 | K15: Fort Bend, Harris, Montgomery, Waller | L15: 40, 55, 60, 70, 80, 90 | M15: 370000 | N15: 590000 | O15: 900000 | P15: 0
A16: b-houston-partners-in-building | B16: houston | C16: Partners in Building | D16: HOU-072 | E16: Custom and hybrid job | F16: No | G16: Yes | H16: No | J16: 9 | K16: Fort Bend, Galveston, Harris, Montgomery | L16: 75, 80, 90, 100 | M16: 750000 | N16: 1000000 | O16: 1300000 | P16: 4 | Q16: 987470 | R16: 4316 | S16: 221 | T16: 286 | U16: 2025 | V16: four markets in two states
A17: b-houston-toll-brothers | B17: houston | C17: Toll Brothers | D17: HOU-203 | E17: National builder | F17: Yes | G17: No | H17: Partly | I17: Toll Brothers | J17: 9 | K17: Fort Bend, Harris, Montgomery | L17: 45, 50, 60, 65, 70, 80, 90 | M17: 379995 | N17: 600000 | O17: 839995 | P17: 33 | Q17: 567000 | R17: 3065 | S17: 201
A18: b-houston-village-builders | B18: houston | C18: Village Builders | D18: HOU-166 | E18: Lennar and the firms it owns | F18: Yes | G18: No | H18: Yes | I18: Lennar | J18: 9 | K18: Fort Bend, Galveston, Harris, Montgomery, Waller | L18: 45, 50, 55, 65 | M18: 245990 | N18: 325495 | O18: 495990 | P18: 12 | Q18: 302990 | R18: 2088 | S18: 150
A19: b-houston-century-communities | B19: houston | C19: Century Communities | D19: HOU-009 | E19: National builder | F19: Yes | G19: Partly | H19: No | I19: Century Communities | J19: 8 | K19: Galveston, Harris, Liberty, Montgomery, Waller | M19: 200000 | N19: 250000 | O19: 349990 | P19: 38 | Q19: 324900 | R19: 2008 | S19: 167 | T19: 1017 | U19: 2025 | V19: BUILDER Local Leaders 2026, Houston metro
A20: b-houston-ashton-woods | B20: houston | C20: Ashton Woods | D20: HOU-024 | E20: National builder | F20: Yes | G20: No | H20: No | J20: 6 | K20: Fort Bend, Harris, Waller | L20: 40, 50, 60 | M20: 312240 | N20: 373990 | O20: 484990 | P20: 25 | Q20: 404990 | R20: 2499 | S20: 155 | T20: 1115 | U20: 2025 | V20: BUILDER Local Leaders 2026, Houston metro
A21: b-houston-colina-homes | B21: houston | C21: Colina Homes | D21: HOU-064 | E21: Two of three counts | F21: Yes | G21: Partly | H21: No | J21: 6 | K21: Brazoria, Galveston, Harris, Liberty, Montgomery, Waller | L21: 40, 60 | M21: 200000 | N21: 277495 | O21: 333990 | P21: 29 | Q21: 334990 | R21: 1830 | S21: 183 | T21: 540 | U21: 2025 | V21: BUILDER firm page
A22: b-houston-long-lake-ltd | B22: houston | C22: Long Lake, Ltd. | D22: HOU-130 | E22: Two of three counts | F22: Yes | G22: Partly | H22: No | J22: 6 | K22: Harris, Liberty, Montgomery, Waller | M22: 200000 | N22: 240000 | O22: 290000 | P22: 20 | Q22: 441790 | R22: 2655 | S22: 162 | T22: 782 | U22: 2025 | V22: Builder 100 firm page
A23: b-houston-m-i-homes | B23: houston | C23: M/I Homes | D23: HOU-012 | E23: National builder | F23: Yes | G23: No | H23: No | I23: M/I Homes | J23: 6 | K23: Harris, Liberty, Montgomery | L23: 50, 60 | M23: 199990 | N23: 284995 | O23: 400000 | P23: 5 | Q23: 344990 | R23: 2198 | S23: 159
A24: b-houston-ravenna-homes | B24: houston | C24: Ravenna Homes | D24: HOU-070 | E24: Two of three counts | F24: Partly | G24: Partly | H24: No | J24: 6 | K24: Fort Bend, Harris, Montgomery | L24: 50, 55, 60, 65, 70 | M24: 400000 | N24: 500000 | O24: 600000 | P24: 29 | Q24: 678900 | R24: 3188 | S24: 208
A25: b-houston-shea-homes | B25: houston | C25: Shea Homes | D25: HOU-204 | E25: National builder | F25: Yes | G25: No | H25: No | J25: 6 | K25: Brazoria, Fort Bend, Galveston, Harris, Montgomery | L25: 40, 50, 60, 65, 70 | M25: 335990 | N25: 523490 | O25: 639990 | P25: 17 | Q25: 499990 | R25: 2548 | S25: 197
A26: b-houston-tri-pointe-homes | B26: houston | C26: Tri Pointe Homes | D26: HOU-205 | E26: National builder | F26: Yes | G26: No | H26: No | I26: Tri Pointe Homes | J26: 6 | K26: Fort Bend, Harris, Montgomery | L26: 45, 50, 60, 70, 75, 80 | M26: 300000 | N26: 699950 | O26: 900000 | P26: 29 | Q26: 698722 | R26: 3779 | S26: 200
A27: b-houston-tricoast-homes | B27: houston | C27: Tricoast Homes | D27: HOU-062 | E27: Two of three counts | F27: Yes | G27: Partly | H27: No | J27: 6 | K27: Brazoria, Fort Bend, Galveston, Liberty, Waller | L27: 40, 50, 55, 60 | M27: 324000 | N27: 354990 | O27: 399990 | P27: 13 | Q27: 394900 | R27: 2526 | S27: 152
A28: b-houston-brohn-homes | B28: houston | C28: Brohn Homes | D28: HOU-073 | E28: Two of three counts | F28: Yes | G28: Partly | H28: No | J28: 5 | K28: Brazoria, Harris, Montgomery, Waller | M28: 200000 | N28: 259990 | O28: 300000 | P28: 19 | Q28: 332990 | R28: 2051 | S28: 164
A29: b-houston-davidson-homes | B29: houston | C29: Davidson Homes | D29: HOU-209 | E29: National builder | F29: Yes | G29: No | H29: No | J29: 5 | K29: Brazoria, Fort Bend, Galveston, Liberty, Waller | M29: 284990 | N29: 293990 | O29: 302990 | P29: 17 | Q29: 369570 | R29: 1991 | S29: 185
A30: b-houston-empire-homes | B30: houston | C30: Empire Homes | D30: HOU-210 | E30: Two of three counts | F30: Yes | G30: Partly | H30: No | J30: 5 | K30: Fort Bend, Harris, Liberty, Montgomery | L30: 45, 50, 60 | M30: 300000 | N30: 372500 | O30: 550000 | P30: 21 | Q30: 379791 | R30: 1970 | S30: 212 | T30: 1056 | U30: 2025 | V30: company-wide
A31: b-houston-lgi-homes | B31: houston | C31: LGI Homes | D31: HOU-014 | E31: National builder | F31: Yes | G31: No | H31: No | I31: LGI Homes | J31: 5 | K31: Brazoria, Fort Bend, Galveston, Montgomery | M31: 282900 | N31: 288900 | O31: 300900 | P31: 0
A32: b-houston-pulte-homes | B32: houston | C32: Pulte Homes | D32: HOU-167 | E32: National builder | F32: Yes | G32: No | H32: Yes | I32: PulteGroup | J32: 5 | K32: Brazoria, Galveston, Liberty, Montgomery | L32: 45, 50 | M32: 244990 | N32: 312990 | O32: 426990 | P32: 19 | Q32: 346560 | R32: 2029 | S32: 175 | T32: 1146 | U32: 2025 | V32: BUILDER Local Leaders 2026, Houston metro
A33: b-houston-jamestown-estate-homes | B33: houston | C33: Jamestown Estate Homes | D33: HOU-071 | E33: Two of three counts | F33: Partly | G33: Yes | H33: No | J33: 4 | K33: Fort Bend, Harris, Montgomery | L33: 70, 80, 100 | M33: 850000 | N33: 878480 | O33: 1000000 | P33: 6 | Q33: 937330 | R33: 3545 | S33: 267 | T33: 75 | U33: 2026 | V33: The firm's own site, about seventy-five a year
A34: b-houston-k-hovnanian-homes | B34: houston | C34: K. Hovnanian Homes | D34: HOU-206 | E34: National builder | F34: Yes | G34: Partly | H34: No | I34: Hovnanian Enterprises | J34: 4 | K34: Harris, Liberty, Montgomery, Waller | L34: 40, 50, 60 | M34: 226990 | N34: 342495 | O34: 500000 | P34: 3 | Q34: 332951 | R34: 2253 | S34: 148 | T34: 1030 | U34: 2024 | V34: BUILDER Local Leaders 2025, Houston metro, Hovnanian Enterprises
A35: b-houston-smith-douglas-homes | B35: houston | C35: Smith Douglas Homes | D35: HOU-074 | E35: Two of three counts | F35: Yes | G35: Partly | H35: No | I35: Smith Douglas Homes | J35: 4 | K35: Brazoria, Liberty, Montgomery | L35: 40, 50, 60 | M35: 212990 | N35: 246495 | O35: 327990 | P35: 15 | Q35: 318990 | R35: 1878 | S35: 160 | T35: 324 | U35: 2022 | V35: Builder, on the Devon Street Homes purchase
A36: b-houston-autograph-homes | B36: houston | C36: Autograph Homes | D36: HOU-211 | E36: Two of three counts | F36: Yes | G36: Partly | H36: No | J36: 3 | K36: Chambers, Fort Bend, Montgomery | L36: 42 | M36: 300000 | N36: 367990 | O36: 424900 | P36: 15 | Q36: 413922 | R36: 2162 | S36: 187
A37: b-houston-first-america-homes | B37: houston | C37: First America Homes | D37: HOU-007 | E37: Two of three counts | F37: Yes | G37: Partly | H37: No | J37: 3 | K37: Montgomery, Waller | M37: 259857 | N37: 260406 | O37: 260955 | P37: 9 | Q37: 319124 | R37: 2026 | S37: 166 | T37: 750 | U37: 2025 | V37: two markets
A38: b-houston-imagination-homes | B38: houston | C38: Imagination Homes | D38: HOU-076 | E38: Two of three counts | F38: Yes | G38: Partly | H38: No | J38: 3 | K38: Brazoria, Waller | M38: 300000 | N38: 300000 | O38: 300000 | P38: 6 | Q38: 320985 | R38: 2172 | S38: 152
A39: b-houston-mckinley-homes | B39: houston | C39: McKinley Homes | D39: HOU-212 | E39: Two of three counts | F39: Yes | G39: Partly | H39: No | J39: 3 | K39: Liberty, Montgomery | M39: 345990 | N39: 345990 | O39: 400000 | P39: 10 | Q39: 402546 | R39: 2034 | S39: 198 | T39: 450 | U39: 2025 | V39: company-wide
A40: b-houston-risewell-homes | B40: houston | C40: Risewell Homes | D40: HOU-075 | E40: Two of three counts | F40: Partly | G40: Partly | H40: No | J40: 3 | K40: Harris, Waller | L40: 40, 50 | M40: 269990 | N40: 304495 | O40: 400000 | P40: 5 | Q40: 427990 | R40: 2449 | S40: 190
A41: b-houston-william-david-homes | B41: houston | C41: William David Homes | D41: HOU-213 | E41: Two of three counts | F41: Partly | G41: Partly | H41: No | J41: 3 | K41: Fort Bend, Harris, Montgomery | L41: 70 | M41: 750000 | N41: 825000 | O41: 900000 | P41: 0
A42: b-houston-adams-homes | B42: houston | C42: Adams Homes | D42: HOU-214 | E42: National builder | F42: Yes | G42: No | H42: No | J42: 2 | K42: Galveston, Liberty | M42: 200000 | N42: 200000 | O42: 200000 | P42: 10 | Q42: 284150 | R42: 1820 | S42: 156
A43: b-houston-caldwell-homes | B43: houston | C43: Caldwell Homes | D43: HOU-131 | E43: Two of three counts | F43: Yes | G43: Partly | H43: No | J43: 2 | K43: Harris, Montgomery | L43: 55, 65, 90 | M43: 448600 | N43: 459800 | O43: 471000 | P43: 6 | Q43: 521576 | R43: 2180 | S43: 247
A44: b-houston-gracepoint-homes | B44: houston | C44: Gracepoint Homes | D44: HOU-215 | E44: Two of three counts | F44: Partly | G44: Partly | H44: No | J44: 2 | K44: Fort Bend, Montgomery | L44: 65 | M44: 579990 | N44: 634995 | O44: 690000 | P44: 0
A45: b-houston-legend-homes | B45: houston | C45: Legend Homes | D45: HOU-010 | E45: Two of three counts | F45: Yes | G45: Partly | H45: No | J45: 2 | K45: Liberty, Waller | M45: 320000 | N45: 320000 | O45: 320000 | P45: 7 | Q45: 304990 | R45: 2050 | S45: 150
A46: b-houston-stonemanor-homes | B46: houston | C46: StoneManor Homes | D46: HOU-216 | E46: Two of three counts | F46: Yes | G46: Partly | H46: No | J46: 2 | K46: Brazoria, Montgomery | M46: 329990 | N46: 349990 | O46: 374990 | P46: 15 | Q46: 419990 | R46: 1996 | S46: 198
A47: b-houston-terrata-homes | B47: houston | C47: Terrata Homes | D47: HOU-217 | E47: National builder | F47: Yes | G47: Partly | H47: No | J47: 2 | K47: Brazoria, Montgomery | L47: 70 | M47: 383900 | N47: 449400 | O47: 514900 | P47: 0
A48: b-houston-ar-homes | B48: houston | C48: AR Homes | J48: 1 | K48: Fort Bend | P48: 0
A49: b-houston-aderra-62-age-restricted-neighborhood | B49: houston | C49: Aderra 62+ (age-restricted neighborhood) | J49: 1 | K49: Montgomery | L49: 45 | M49: 300000 | N49: 300000 | O49: 300000 | P49: 0
A50: b-houston-bavaria-builders | B50: houston | C50: Bavaria Builders | J50: 1 | K50: Harris | M50: 900000 | N50: 900000 | O50: 900000 | P50: 0
A51: b-houston-braziel-building-group | B51: houston | C51: Braziel Building Group | J51: 1 | K51: Harris | M51: 900000 | N51: 900000 | O51: 900000 | P51: 0
A52: b-houston-brickland-custom-homes-inc | B52: houston | C52: Brickland Custom Homes, Inc | J52: 1 | K52: Harris | M52: 900000 | N52: 900000 | O52: 900000 | P52: 0
A53: b-houston-brookfield-residential | B53: houston | C53: Brookfield Residential | D53: HOU-207 | E53: National builder | F53: Yes | G53: Partly | H53: No | J53: 1 | K53: Harris | L53: 40, 45, 50, 60 | M53: 328740 | N53: 419990 | O53: 534990 | P53: 5 | Q53: 569990 | R53: 2772 | S53: 191
A54: b-houston-centex | B54: houston | C54: Centex | D54: HOU-167 | E54: National builder | F54: Yes | G54: No | H54: Yes | J54: 1 | K54: Montgomery | M54: 221990 | N54: 235990 | O54: 249990 | P54: 10 | Q54: 296235 | R54: 1662 | S54: 174 | T54: 1146 | U54: 2025 | V54: BUILDER Local Leaders 2026, Houston metro
A55: b-houston-dsld-homes | B55: houston | C55: DSLD Homes | D55: HOU-134 | E55: National builder | F55: Yes | G55: No | H55: No | J55: 1 | K55: Montgomery | M55: 348990 | N55: 348990 | O55: 348990 | P55: 5 | Q55: 329990 | R55: 1819 | S55: 190 | T55: 3989 | U55: 2025 | V55: company-wide, six states
A56: b-houston-del-webb | B56: houston | C56: Del Webb | D56: HOU-167 | E56: National builder | F56: Yes | G56: No | H56: Yes | I56: PulteGroup | J56: 1 | K56: Harris | M56: 414990 | N56: 414990 | O56: 414990 | P56: 5 | Q56: 529620 | R56: 1809 | S56: 292
A57: b-houston-fedrick-harris-estate-homes | B57: houston | C57: Fedrick Harris Estate Homes | D57: HOU-069 | E57: Two of three counts | F57: Partly | G57: Partly | H57: No | J57: 1 | K57: Harris | L57: 90 | M57: 1000000 | N57: 1000000 | O57: 1000000 | P57: 3 | Q57: 1706624 | R57: 5123 | S57: 333 | T57: 483 | U57: 2025 | V57: Houston and Austin
